Workbook

Sheet Input
A1: Display | B1: Workstream | C1: Service_Title | D1: Customer_Story | E1: Suggested_Path | F1: Assumptions | G1: Estimated_Low_Hours | H1: Estimated_High_Hours | I1: Contracted_Hours | J1: Requires_Clarification | K1: Function | L1: Potential_Variance | M1: Library_ID | N1: Project_ID | O1: Internal_Notes | P1: Task_Link
A2: Now | B2: Discovery Interviews + Workshops | C2: Direct Sales Team Stakeholder Interviews | D2: Taoglas needs to understand current pain points and CRM adoption challenges across their Direct Sales organization spanning 3 regions with standardized processes. | E2: A8 to conduct structured interviews with Direct Sales stakeholders across all regions to document current state challenges and CRM utilization gaps. | F2: - Up to 3 to 4 one-hour workshops - Access to Direct Sales executives and regional managers across 3 regions - Louise (CRM Head) to coordinate scheduling across regions - A8 to provide interview framework focused on pipeline management and forecasting - All sessions recorded and transcribed for documentation (for all A8 meetings) | G2: 6 | H2: 10 | I2: =IF(AND(G2<>"",H2<>""),ROUNDUP(AVERAGE(G2:H2),0),"") -> 8 | J2: FALSE | K2: Strategy
A3: Now | B3: Discovery Interviews + Workshops | C3: Distribution Sales Team Stakeholder Interviews | D3: Taoglas needs to understand unique process requirements and CRM challenges within their Distribution Sales channel with key stakeholders. | E3: A8 to conduct targeted interviews with Distribution Sales stakeholders to document channel-specific workflows and integration requirements. | F3: - Up to 3 to 4 one-hour workshops - Access to lead Distribution Sales stakeholders - Distribution-specific process documentation and system requirements - Understanding of distributor relationship management needs - Channel conflict and territory management considerations documented | G3: 6 | H3: 10 | I3: =IF(AND(G3<>"",H3<>""),ROUNDUP(AVERAGE(G3:H3),0),"") -> 8 | J3: FALSE | K3: Strategy
A4: Now | B4: Discovery Interviews + Workshops | C4: M&I Sales Team Stakeholder Interviews | D4: Taoglas needs to understand the most complex and unique sales processes within their M&I division to inform standardization opportunities. | E4: A8 to conduct detailed interviews with M&I stakeholders to document complex deal structures and specialized requirements. | F4: - Up to 3 to 4 one-hour workshops - Access to M&I sales leadership and key contributors - Taoglas to provide walkthroughs for complex deals and approval process - A8 to note integration-specific CRM and process requirements | G4: 6 | H4: 10 | I4: =IF(AND(G4<>"",H4<>""),ROUNDUP(AVERAGE(G4:H4),0),"") -> 8 | J4: FALSE | K4: Strategy
A5: Now | B5: Discovery Interviews + Workshops | C5: Marketing Operations Stakeholder Interviews | D5: Taoglas needs to understand current marketing operations workflows and the potential transition from external partner to internal management with Alan (Marketing Ops Head). | E5: A8 to conduct interviews with marketing stakeholders including Alan to document lead generation handoff processes and HubSpot marketing utilization. | F5: - Up to 3 to 4 one-hour workshops - Access to Alan (Marketing Operations Head) and marketing team - Taoglas to provide current external partner workflow documentation - Lead generation to sales handoff process mapping - Marketing automation and segmentation requirements assessment | G5: 8 | H5: 12 | I5: =IF(AND(G5<>"",H5<>""),ROUNDUP(AVERAGE(G5:H5),0),"") -> 10 | J5: FALSE | K5: Strategy
A6: Now | B6: Discovery Interviews + Workshops | C6: Customer Service & Order Management Interviews | D6: Taoglas needs to understand how Customer Service and Order Management teams interface with CRM and other technologies for customer lifecycle management and support workflows. | E6: A8 to interview Customer Service/Order Management stakeholders to document customer journey touchpoints and CRM utilization patterns. | F6: - Up to 2 to 3 one-hour workshops - Access to 2 Customer Service/Order Management stakeholders - Taoglas to provide current customer support workflow documentation - A8 to focus on order management and CRM integration requirements | G6: 4 | H6: 6 | I6: =IF(AND(G6<>"",H6<>""),ROUNDUP(AVERAGE(G6:H6),0),"") -> 5 | J6: FALSE | K6: Strategy
A7: Now | B7: Discovery Interviews + Workshops | C7: Engineering & Operations Support Workshops | D7: Taoglas needs to understand how Engineering (Design services/NPI) and Operations teams support sales processes despite operating primarily in SAP systems. | E7: A8 to facilitate workshops with Engineering and Operations teams to identify sales support touchpoints and potential CRM integration opportunities. | F7: - Up to 2 to 3 one-hour workshops - Taoglas to provide access to Engineering and Operations team representatives - Taoglas to provide SAP system workflow documentation and integration docs - A8 to focus on sales support process (quotes, technical specs, delivery) | G7: 3 | H7: 6 | I7: =IF(AND(G7<>"",H7<>""),ROUNDUP(AVERAGE(G7:H7),0),"") -> 5 | J7: FALSE | K7: Strategy
A8: Now | B8: Discovery Interviews + Workshops | C8: Finance & Revenue Operations Leadership Interviews | D8: Taoglas needs to align finance and revenue operations requirements with CRM optimization including forecasting accuracy and pipeline reporting needs. | E8: A8 to conduct interviews with Eileen (Group Financial Controller) and RevOps stakeholders to document financial reporting and forecasting requirements. | F8: - Up to 2 to 3 one-hour workshops - Access to Eileen O'Reilly (Group Financial Controller) and RevOps team - Current forecasting processes and accuracy challenges documented - Financial reporting requirements from CRM data - Revenue recognition and pipeline tracking alignment | G8: 3 | H8: 6 | I8: =IF(AND(G8<>"",H8<>""),ROUNDUP(AVERAGE(G8:H8),0),"") -> 5 | J8: FALSE | K8: Strategy
A9: Now | B9: Discovery Interviews + Workshops | C9: Technical Architecture Workshops | D9: Taoglas needs evaluation of their complete technology stack including HubSpot, Tacton CPQ, SAP B1 and their Microsoft ecosystem to identify optimization and integration opportunities. | E9: A8 to assess entire technical architecture and document high-level system dependencies integration capabilities and data flow across all platforms. | F9: - Up to 3 one-hour workshops - Access to system architecture documentation for all platforms - Technical stakeholders available for interviews (HubSpot, Tacton, SAP) - System access for evaluation (sandbox environments preferred) - Taoglas to provide documentation when it exists - AI initiative coordination with Cadre team requirements likely here | G9: 6 | H9: 10 | I9: =IF(AND(G9<>"",H9<>""),ROUNDUP(AVERAGE(G9:H9),0),"") -> 8 | J9: FALSE | K9: Solutions Engineering
A10: Now | B10: Strategy Development + Design | C10: Gap Analysis & Opportunity Assessment | D10: Taoglas needs a comprehensive analysis of gaps between their current GTM processes and CRM utilization to prioritize improvement initiatives across their complex sales organization. | E10: A8 to conduct detailed gap analysis comparing current state against HubSpot best practices and industry standards for primary GTM teams. | F10: - Assumes current state documentation provided by Taoglas and all discovery workshops are complete - Gap prioritization based on business impact and adoption feasibility - ROI estimation for improvement opportunities across channels - Quick wins identification and validation | G10: 5 | H10: 10 | I10: =IF(AND(G10<>"",H10<>""),ROUNDUP(AVERAGE(G10:H10),0),"") -> 8 | J10: FALSE | K10: Strategy
A11: Now | B11: Strategy Development + Design | C11: GTM Documentation Review and Workshops | D11: Taoglas needs collaborative sessions to define and prioritize requirements for FUTURE state CRM optimization across each functional area with cross-team alignment. | E11: A8 to facilitate requirements workshops with GTM teams plus cross-functional sessions to define detailed requirements and identify dependencies. | F11: - This service line/story is a hybrid of A8 documentation, feedback by Taoglas, and workshops to align on the direction of the implementation phase - Key stakeholders from each functional area available for workshops - Workshop sessions recorded and documented in structured format - Complex cross-functional dependencies flagged - Requirements prioritization may use the MoSCoW method (Must Should Could Won't) - AI initiative requirements coordination considerations | G11: 12 | H11: 18 | I11: =IF(AND(G11<>"",H11<>""),ROUNDUP(AVERAGE(G11:H11),0),"") -> 15 | J11: FALSE | K11: Strategy
A12: Now | B12: Strategy Development + Design | C12: Reporting Strategy + Design | D12: Taoglas needs a comprehensive reporting strategy that leverages their custom HubSpot object architecture to provide actionable insights for GTM, operations, and leadership teams. | E12: A8 to design comprehensive reporting strategy and requirements documentation for Taoglas's HubSpot instance including custom report specifications, high-level data visualization requirements, and user role-based reporting access. | F12: - Recommendations for HubSpot's object architecture completed to compliment this service - Taoglas to share key performance indicators and success metrics during discovery workshops - Taoglas to share current reporting tools and processes being used - Clear definition of reporting user personas and access requirements - Reporting frequency requirements defined (real-time, weekly, monthly, quarterly) | G12: 6 | H12: 10 | I12: =IF(AND(G12<>"",H12<>""),ROUNDUP(AVERAGE(G12:H12),0),"") -> 8 | J12: FALSE | K12: Strategy
A13: Now | B13: Strategy Development + Design | C13: GTM Process Standardization Framework + Documentation | D13: Taoglas needs a strategic framework for standardizing (and connecting) processes across GTM teams while maintaining team/channel-specific flexibility where required. | E13: A8 to develop marketing and sales process standardization framework balancing consistency with team-specific requirements and regional variations. | F13: - A8 to create future-facing process mapping for primary GTM teams - Standardization opportunities identified and validated with Taoglas stakeholders - Channel-specific exception handling and approval workflows defined - Pipeline stage standardization with channel-appropriate customizations - Training and adoption strategy considerations integrated - Process swimlanes and technical dependencies with AI, CPQ, product library, and ERP are clearly defined | G13: 15 | H13: 20 | I13: =IF(AND(G13<>"",H13<>""),ROUNDUP(AVERAGE(G13:H13),0),"") -> 18 | J13: FALSE | K13: Strategy
... A20: Now | B20: Flex Hours | C20: Flex Hours | D20: Taoglas needs additional consulting capacity to take advantage of quick win opportunities in their current HubSpot instance. | E20: A8 to provide flexible consulting and implementation support for opportunities like updating deal stages, light reporting updates, and define a more strategic account creation process. | F20: - These hours may also be used for additional stakeholder interviews or workshops - Coordination support with external partners and vendors as needed - Other quick win opportunities include: Data entry methods to support better forecasting, net new company/logo creation process, required deal stages and data | G20: 15 | H20: 15 | I20: =IF(AND(G20<>"",H20<>""),ROUNDUP(AVERAGE(G20:H20),0),"") -> 15 | J20: FALSE | K20: Consulting
I21: =IF(AND(G21<>"",H21<>""),ROUNDUP(AVERAGE(G21:H21),0),"") | J21: FALSE
I22: =IF(AND(G22<>"",H22<>""),ROUNDUP(AVERAGE(G22:H22),0),"") | J22: FALSE
I23: =IF(AND(G23<>"",H23<>""),ROUNDUP(AVERAGE(G23:H23),0),"") | J23: FALSE
I24: =IF(AND(G24<>"",H24<>""),ROUNDUP(AVERAGE(G24:H24),0),"") | J24: FALSE
I25: =IF(AND(G25<>"",H25<>""),ROUNDUP(AVERAGE(G25:H25),0),"") | J25: FALSE
I26: =IF(AND(G26<>"",H26<>""),ROUNDUP(AVERAGE(G26:H26),0),"") | J26: FALSE
I27: =IF(AND(G27<>"",H27<>""),ROUNDUP(AVERAGE(G27:H27),0),"") | J27: FALSE
I28: =IF(AND(G28<>"",H28<>""),ROUNDUP(AVERAGE(G28:H28),0),"") | J28: FALSE
I29: =IF(AND(G29<>"",H29<>""),ROUNDUP(AVERAGE(G29:H29),0),"") | J29: FALSE
I30: =IF(AND(G30<>"",H30<>""),ROUNDUP(AVERAGE(G30:H30),0),"") | J30: FALSE
I31: =IF(AND(G31<>"",H31<>""),ROUNDUP(AVERAGE(G31:H31),0),"") | J31: FALSE
I32: =IF(AND(G32<>"",H32<>""),ROUNDUP(AVERAGE(G32:H32),0),"") | J32: FALSE
... I145: =IF(AND(G145<>"",H145<>""),ROUNDUP(AVERAGE(G145:H145),0),"") | J145: FALSE
J146: FALSE
J147: FALSE

Sheet ClickUp Import
A1: Task Type | B1: Task Name | C1: Description Content | D1: High Hours Estimate | E1: Contracted Hours
A2: Workstream | B2: Custom Integration Strategy + Technology Planning
A3: Customer Story | B3: Future-State Solution Architecture & Integration Design | C3: Taoglas needs detailed design of optimal future-state CRM architecture including enhanced integrations with Tacton AEB SAP and coordination with AI initiatives. A8 to design comprehensive future-state architecture with optimized system integrations process workflows and AI initiative coordination points. - This document is specific to integration planning - Requirements documentation completed across all functional areas - Technical constraints and integration capabilities documented - Architecture diagrams created in Lucid for stakeholder review - Integration specifications for Tacton and SAP and potential new systems - AI initiative coordination points and handoff specifications defined - Custom development is not included in this phase or scope | D3: 14 | E3: 12
A4: Customer Story | B4: Integration Data Flow Requirements + Mapping | C4: Taoglas needs a clear definition of required integrations to ensure critical data flows are established for go-live (or next implementation phase) while identifying future integration opportunities. A8 to define integration requirements including sync rules, ownership responsibilities, and technical specifications for essential integrations needed for HubSpot (re)launch. - This document is specific to integration requirements - A8 to support technical capabilities assessment of integration options - Taoglas to provide transparency on resource availability for integration development - Timeline constraints documented for launch or any future phases - Integration field mapping requirements not included in this scope, only critical fields to be noted - Custom development is not included in this phase or scope | D4: 14 | E4: 12
A5: Customer Story | B5: AI Initiative Coordination & Integration Strategy | C5: Taoglas needs additional strategic guidance on bringing on AI solutions into their HubSpot platform while following best practices concurrent Cadre AI initiatives to ensure alignment and avoid conflicts. A8 to develop coordination strategy between CRM optimization and AI initiatives including data sharing integration points and timeline alignment. - Cadre AI initiative scope and timeline documentation available - Regular coordination meetings established with Cadre team - Data sharing and integration requirements between initiatives defined - Timeline coordination to avoid resource conflicts | D5: 15 | E5: 12
A6: Workstream | B6: Discovery Interviews + Workshops
A7: Customer Story | B7: Direct Sales Team Stakeholder Interviews | C7: Taoglas needs to understand current pain points and CRM adoption challenges across their Direct Sales organization spanning 3 regions with standardized processes. A8 to conduct structured interviews with Direct Sales stakeholders across all regions to document current state challenges and CRM utilization gaps. - Up to 3 to 4 one-hour workshops - Access to Direct Sales executives and regional managers across 3 regions - Louise (CRM Head) to coordinate scheduling across regions - A8 to provide interview framework focused on pipeline management and forecasting - All sessions recorded and transcribed for documentation (for all A8 meetings) | D7: 10 | E7: 8
A8: Customer Story | B8: Distribution Sales Team Stakeholder Interviews | C8: Taoglas needs to understand unique process requirements and CRM challenges within their Distribution Sales channel with key stakeholders. A8 to conduct targeted interviews with Distribution Sales stakeholders to document channel-specific workflows and integration requirements. - Up to 3 to 4 one-hour workshops - Access to lead Distribution Sales stakeholders - Distribution-specific process documentation and system requirements - Understanding of distributor relationship management needs - Channel conflict and territory management considerations documented | D8: 10 | E8: 8
A9: Customer Story | B9: M&I Sales Team Stakeholder Interviews | C9: Taoglas needs to understand the most complex and unique sales processes within their M&I division to inform standardization opportunities. A8 to conduct detailed interviews with M&I stakeholders to document complex deal structures and specialized requirements. - Up to 3 to 4 one-hour workshops - Access to M&I sales leadership and key contributors - Taoglas to provide walkthroughs for complex deals and approval process - A8 to note integration-specific CRM and process requirements | D9: 10 | E9: 8
A10: Customer Story | B10: Marketing Operations Stakeholder Interviews | C10: Taoglas needs to understand current marketing operations workflows and the potential transition from external partner to internal management with Alan (Marketing Ops Head). A8 to conduct interviews with marketing stakeholders including Alan to document lead generation handoff processes and HubSpot marketing utilization. - Up to 3 to 4 one-hour workshops - Access to Alan (Marketing Operations Head) and marketing team - Taoglas to provide current external partner workflow documentation - Lead generation to sales handoff process mapping - Marketing automation and segmentation requirements assessment | D10: 12 | E10: 10
A11: Customer Story | B11: Customer Service & Order Management Interviews | C11: Taoglas needs to understand how Customer Service and Order Management teams interface with CRM and other technologies for customer lifecycle management and support workflows. A8 to interview Customer Service/Order Management stakeholders to document customer journey touchpoints and CRM utilization patterns. - Up to 2 to 3 one-hour workshops - Access to 2 Customer Service/Order Management stakeholders - Taoglas to provide current customer support workflow documentation - A8 to focus on order management and CRM integration requirements | D11: 6 | E11: 5
A12: Customer Story | B12: Engineering & Operations Support Workshops | C12: Taoglas needs to understand how Engineering (Design services/NPI) and Operations teams support sales processes despite operating primarily in SAP systems. A8 to facilitate workshops with Engineering and Operations teams to identify sales support touchpoints and potential CRM integration opportunities. - Up to 2 to 3 one-hour workshops - Taoglas to provide access to Engineering and Operations team representatives - Taoglas to provide SAP system workflow documentation and integration docs - A8 to focus on sales support process (quotes, technical specs, delivery) | D12: 6 | E12: 5
A13: Customer Story | B13: Finance & Revenue Operations Leadership Interviews | C13: Taoglas needs to align finance and revenue operations requirements with CRM optimization including forecasting accuracy and pipeline reporting needs. A8 to conduct interviews with Eileen (Group Financial Controller) and RevOps stakeholders to document financial reporting and forecasting requirements. - Up to 2 to 3 one-hour workshops - Access to Eileen O'Reilly (Group Financial Controller) and RevOps team - Current forecasting processes and accuracy challenges documented - Financial reporting requirements from CRM data - Revenue recognition and pipeline tracking alignment | D13: 6 | E13: 5
A14: Customer Story | B14: Technical Architecture Workshops | C14: Taoglas needs evaluation of their complete technology stack including HubSpot, Tacton CPQ, SAP B1 and their Microsoft ecosystem to identify optimization and integration opportunities. A8 to assess entire technical architecture and document high-level system dependencies integration capabilities and data flow across all platforms. - Up to 3 one-hour workshops - Access to system architecture documentation for all platforms - Technical stakeholders available for interviews (HubSpot, Tacton, SAP) - System access for evaluation (sandbox environments preferred) - Taoglas to provide documentation when it exists - AI initiative coordination with Cadre team requirements likely here | D14: 10 | E14: 8
A15: Workstream | B15: Flex Hours
A16: Customer Story | B16: Flex Hours | C16: Taoglas needs additional consulting capacity to take advantage of quick win opportunities in their current HubSpot instance. A8 to provide flexible consulting and implementation support for opportunities like updating deal stages, light reporting updates, and define a more strategic account creation process. - These hours may also be used for additional stakeholder interviews or workshops - Coordination support with external partners and vendors as needed - Other quick win opportunities include: Data entry methods to support better forecasting, net new company/logo creation process, required deal stages and data | D16: 15 | E16: 15
A17: Workstream | B17: Phase 1 Implementation Planning
A18: Customer Story | B18: Phased Implementation Roadmap & Resource Planning | C18: Taoglas needs an implementation plan via a 4-to-6-month roadmap that enables prioritization and resource allocation guidance across multiple workstreams. A8 to create an implementation roadmap that supports Taoglas's business goals gleaned from this strategy engagement. - Solution architecture and strategic framework completed - 6-month implementation planning highlight partner vs Taoglas responsibilities and estimates resource requirements - Includes change management/training timeline and dependencies - Dependencies and critical path identification across all workstreams | D18: 12 | E18: 10
A19: Customer Story | B19: Change Management & Training Strategy Development | C19: Taoglas needs a comprehensive train-the-trainer strategy to drive user adoption and organizational change leveraging internal champions for CRM optimization success. A8 to develop a change management strategy emphasizing train-the-trainer methodology with internal champion identification and adoption measurement. - Assumes all discovery is complete and Taoglas has identified any major platform changes - Taoglas to identify internal champions and provide feedback on A8's training approach for each team - A8 to recommend success metrics and ongoing reinforcement strategy - Timeline alignment with implementation phases and system rollouts | D19: 6 | E19: 5
A20: Customer Story | B20: Executive Stakeholder Alignment & Presentation | C20: Taoglas needs support for executive presentation and stakeholder buy-in to ensure leadership support the upcoming CRM optimization initiative and resource allocation. A8 to create executive presentation materials and facilitate stakeholder alignment sessions to secure leadership buy-in and implementation approvals. - Executive presentation deck with ROI justification and timeline overview - Taoglas to support key stakeholder availability for alignment meetings and decision sessions - Decision-making process and approval requirements clearly documented - Implementation budget and resource authorization obtained from leadership - Ongoing executive communication and progress reporting strategy defined | D20: 5 | E20: 4
A21: Workstream | B21: Strategy Development + Design
A22: Customer Story | B22: Gap Analysis & Opportunity Assessment | C22: Taoglas needs a comprehensive analysis of gaps between their current GTM processes and CRM utilization to prioritize improvement initiatives across their complex sales organization. A8 to conduct detailed gap analysis comparing current state against HubSpot best practices and industry standards for primary GTM teams. - Assumes current state documentation provided by Taoglas and all discovery workshops are complete - Gap prioritization based on business impact and adoption feasibility - ROI estimation for improvement opportunities across channels - Quick wins identification and validation | D22: 10 | E22: 8
A23: Customer Story | B23: GTM Documentation Review and Workshops | C23: Taoglas needs collaborative sessions to define and prioritize requirements for FUTURE state CRM optimization across each functional area with cross-team alignment. A8 to facilitate requirements workshops with GTM teams plus cross-functional sessions to define detailed requirements and identify dependencies. - This service line/story is a hybrid of A8 documentation, feedback by Taoglas, and workshops to align on the direction of the implementation phase - Key stakeholders from each functional area available for workshops - Workshop sessions recorded and documented in structured format - Complex cross-functional dependencies flagged - Requirements prioritization may use the MoSCoW method (Must Should Could Won't) - AI initiative requirements coordination considerations | D23: 18 | E23: 15
A24: Customer Story | B24: Reporting Strategy + Design | C24: Taoglas needs a comprehensive reporting strategy that leverages their custom HubSpot object architecture to provide actionable insights for GTM, operations, and leadership teams. A8 to design comprehensive reporting strategy and requirements documentation for Taoglas's HubSpot instance including custom report specifications, high-level data visualization requirements, and user role-based reporting access. - Recommendations for HubSpot's object architecture completed to compliment this service - Taoglas to share key performance indicators and success metrics during discovery workshops - Taoglas to share current reporting tools and processes being used - Clear definition of reporting user personas and access requirements - Reporting frequency requirements defined (real-time, weekly, monthly, quarterly) | D24: 10 | E24: 8
A25: Customer Story | B25: GTM Process Standardization Framework + Documentation | C25: Taoglas needs a strategic framework for standardizing (and connecting) processes across GTM teams while maintaining team/channel-specific flexibility where required. A8 to develop marketing and sales process standardization framework balancing consistency with team-specific requirements and regional variations. - A8 to create future-facing process mapping for primary GTM teams - Standardization opportunities identified and validated with Taoglas stakeholders - Channel-specific exception handling and approval workflows defined - Pipeline stage standardization with channel-appropriate customizations - Training and adoption strategy considerations integrated - Process swimlanes and technical dependencies with AI, CPQ, product library, and ERP are clearly defined | D25: 20 | E25: 18
A26: Workstream | B26: Project Management | E26: 35
A27: Customer Story | B27: Project Kickoff, Onboarding, and Closeout
A28: Customer Story | B28: Recurring Project Check-ins
A29: Customer Story | B29: Project Administration

Sheet Config
A1: Configuration | B1: Value | C1: Description | D1: HubSpot Property
A2: Gdrvie + Deal Inputs
A3: Company Name | B3: Taoglas Strategy Engagement | C3: Client company name for proposals
A4: Google Folder | B4: https://drive.google.com/drive/folders/1Y6mdhZ8I_tVKSImaxGZFLoTrLMYJewxW | C4: Needs to be manually input for the time being, will be set by the Pipedream automation
A5: Deal Record ID | B5: 33928287798 | C5: HubSpot deal record ID, needs to be manually input for the time being, will be set by the Pipedream automation
A6: Last Sync to HubSpot | B6: 45918.287 | C6: The last time the story doc was sync'd to the HubSpot deal record
A8: Client Page
A9: Client Page URL | B9: https://script.google.com/macros/s/AKfycbyX-NJc38M7t92lgQFeLnpQ8A1C6EDBxb7wd7k__fQ9E_VNUhCjp9BQ8M6PJCelfrasgA/exec?sheetId=1mN36V8Y7tH-yGd842Pw1GdCs_a_A9_eGH_K5hNk4wW4 | C9: The URL of the page that will be shared in Trumpet | D9: customer_stories_client_url
A10: Last Client Page URL Generated | B10: 45917.484 | C10: The last time you created/updated a URL so we can understand deployment app versions
A11: Client Page Status | B11: Final Presentation | C11: Determines page status for the shared link
A12: Project ID | B12: ------ | C12: TBD on usage to facilitate project creation
A13: Solutions Architect | B13: Martin Rittenberry | C13: SA assigned to this project
A14: Request Scope Review | C14: Future-state functionality incoming
A15: Scope Reviewed | C15: Future-state functionality incoming
A17: NOW Project
A18: Hourly Project Rate | B18: 325 | C18: Standard hourly rate for most services | D18: project_hourly_rate
A19: Project Management Factor | B19: 0.2 | C19: Percentage markup for project management
A20: Project Management Content | B20: To support management and communication, a project manager and delivery lead will own all A8 tasks and clearly communicate needs. - Visibility to budget spend will be provided during the duration of the project - A8 will provide check-in agenda items and follow-ups - Taoglas to communicate to A8's shared inbox for easier collaboration and timely responses - Taoglas driven delay will result in additional PM time billed to manage timeline | C20: Description text for the PM section. editable by you.
A21: SA Expected Start Date | B21: 45936 | C21: Project start date
A22: Total Project Months | B22: 2 | C22: Expected project duration | D22: project_duration
A24: NEXT Support Retainer
A25: Post-Launch Hourly Rate | B25: 0 | C25: Post-launch rate, a zero here will hide the workstream/section | D25: retainer_hourly_rate
A26: Post-Launch Hours Per Month | B26: 0 | C26: Post-launch hours per month, a zero here will hide the workstream/section | D26: retainer_hours_per_month_sold
A27: Post-Launch # of Months | B27: 0 | C27: Post-launch months, a zero here will hide the workstream/section | D27: retainer_months_sold
A28: Post-Launch Support Content | B28: Hours dedicated to post go-live support. These hours can be used for anything HubSpot related (reporting, training, iterations, additional asks, etc.) | C28: Description text for the post-launch section
A31: Additional Notes + Considerations
A32: Additional Notes | B32: - The assumptions content in this scope is based on information and discovery during the sales evaluation and is subject to change during the project if additional challenges or barriers are discovered. - A8 is a Time & Materials agency, we will provide transparent budget tracking throughout the project and change orders will require approvals. - We interchange between A8 and Aptitude 8 in this document. | C32: Description text for below the investment summaries, but above the later phase workstreams

Sheet Calculations
D1: HubSpot Property
A2: Calculated Project Details
A3: Total Service Hours Hours | B3: =SUMIF(Input!A:A,"Now",Input!I:I) -> 176 | C3: Total amount of Input rows
A4: Total Project Management Hours | B4: =round(B3*Config!B19,0) -> 35 | C4: Based on PM % in Config Sheet
A5: Total Project Hours Sold | B5: =sum(B3:B4) -> 211 | C5: Service + PM | D5: project_hours_sold
A6: Total Retainer Hours Sold | B6: =Config!B26 * Config!B27 -> 0
A7: Total Engagement Hours Sold | B7: =sum(B5:B6) -> 211 | C7: This should match exactly to the investment block on the HTML Page | D7: sold_hours
A8: Deal Amount | B8: =(B5*Config!B18)+(B6*Config!B25) -> 68575 | C8: This should match exactly to the investment block on the HTML Page | D8: amount
A9: Expected End Date | B9: =EDATE(Config!B21, Config!B22) -> 45997
A10: Expected Project Hours/Month | B10: =roundup(B3/Config!B22,0) -> 88
A11: Linear Expected Project Hours/Week | B11: =roundup(B10/4.3,0) -> 21
A12: Peak Project Expected Hours/Week | B12: =B11*1.2 -> 25.2
A13: Low Project Expected Hours/Week | B13: =B11*0.5 -> 10.5
A14: Dev Work Percentage | B14: =C21 -> 0 | D14: dev_work_pct
A15: SE Work Percentage | B15: =C23 -> 0.20853081 | D15: se_work_pct
A18: Calculated Function Summary
B19: Sum of Hours | C19: Percent of
A20: Consulting | B20: =SUMIFS(Input!I:I,Input!K:K,"Consulting",Input!A:A,"Now") -> 15 | C20: =B20/B26 -> 0.071090047
A21: Development | B21: =SUMIFS(Input!I:I,Input!K:K,"Development",Input!A:A,"Now") -> 0 | C21: =B21/B26 -> 0
A22: Project Management | B22: =B4 -> 35 | C22: =B22/B26 -> 0.16587678
A23: Solutions Engineering | B23: =SUMIFS(Input!I:I,Input!K:K,"Solutions Engineering",Input!A:A,"Now") -> 44 | C23: =B23/B26 -> 0.20853081
A24: Strategy | B24: =SUMIFS(Input!I:I,Input!K:K,"Strategy",Input!A:A,"Now") -> 117 | C24: =B24/B26 -> 0.55450237
A26: Sum of Function-Based Hours | B26: =sum(B20:B24) -> 211 | C26: =sum(C20:C24) -> 1
A29: Calculated Ranges | B29: Low Hours | C29: High Hours
A30: Project Service Estimates: | B30: =SUMIF(Input!A:A,"Now",Input!G:G) -> 137 | C30: =SUMIF(Input!A:A,"Now",Input!H:H) -> 209
A31: Project Management: | B31: =round(B30*Config!B19,0) -> 27 | C31: =round(C30*Config!B19,0) -> 42
A32: Post-Project Support: | B32: =B6 -> 0 | C32: =B6 -> 0
A33: Hour Estimates: | B33: =SUM(B30:B32) -> 164 | C33: =SUM(C30:C32) -> 251
A34: Investment Ranges: | B34: =(sum(B30:B31)*Config!B18)+(B32*Config!B25) -> 53300 | C34: =(sum(C30:C31)*Config!B18)+(C32*Config!B25) -> 81575
A36: SOW Summarized Line Items
A37: =IFERROR(__xludf.DUMMYFUNCTION("VSTACK( QUERY(Input!A:I,""SELECT B, SUM(I), SUM(I)*""&Config!B18&"" WHERE B IS NOT NULL AND A = 'Now' GROUP BY B LABEL B 'Workstream', SUM(I) 'Total Hours', SUM(I)*""&Config!B18&"" 'Total Investment'"",1), {""Project Management"", ROUND(SUMPRODUCT(QUE"&"RY(Input!A:I,""SELECT SUM(I) WHERE B IS NOT NULL AND A = 'Now' GROUP BY B LABEL SUM(I) ''"",0))*Config!B19,0), ROUND(SUMPRODUCT(QUERY(Input!A:I,""SELECT SUM(I) WHERE B IS NOT NULL AND A = 'Now' GROUP BY B LABEL SUM(I) ''"",0))*Config!B19,0)*Config!B18}, "&" {""Post-Launch Support"", Config!B26*Config!B27, Config!B26*Config!B27*Config!B25} )"),"Workstream") -> Workstream | B37: =IFERROR(__xludf.DUMMYFUNCTION("""COMPUTED_VALUE"""),"Total Hours") -> Total Hours | C37: =IFERROR(__xludf.DUMMYFUNCTION("""COMPUTED_VALUE"""),"Total Investment") -> Total Investment
A38: =IFERROR(__xludf.DUMMYFUNCTION("""COMPUTED_VALUE"""),"Custom Integration Strategy + Technology Planning") -> Custom Integration Strategy + Technology Planning | B38: =IFERROR(__xludf.DUMMYFUNCTION("""COMPUTED_VALUE"""),36.0) -> 36 | C38: =IFERROR(__xludf.DUMMYFUNCTION("""COMPUTED_VALUE"""),11700.0) -> 11700
A39: =IFERROR(__xludf.DUMMYFUNCTION("""COMPUTED_VALUE"""),"Discovery Interviews + Workshops") -> Discovery Interviews + Workshops | B39: =IFERROR(__xludf.DUMMYFUNCTION("""COMPUTED_VALUE"""),57.0) -> 57 | C39: =IFERROR(__xludf.DUMMYFUNCTION("""COMPUTED_VALUE"""),18525.0) -> 18525
A40: =IFERROR(__xludf.DUMMYFUNCTION("""COMPUTED_VALUE"""),"Flex Hours") -> Flex Hours | B40: =IFERROR(__xludf.DUMMYFUNCTION("""COMPUTED_VALUE"""),15.0) -> 15 | C40: =IFERROR(__xludf.DUMMYFUNCTION("""COMPUTED_VALUE"""),4875.0) -> 4875
A41: =IFERROR(__xludf.DUMMYFUNCTION("""COMPUTED_VALUE"""),"Phase 1 Implementation Planning") -> Phase 1 Implementation Planning | B41: =IFERROR(__xludf.DUMMYFUNCTION("""COMPUTED_VALUE"""),19.0) -> 19 | C41: =IFERROR(__xludf.DUMMYFUNCTION("""COMPUTED_VALUE"""),6175.0) -> 6175
A42: =IFERROR(__xludf.DUMMYFUNCTION("""COMPUTED_VALUE"""),"Strategy Development + Design") -> Strategy Development + Design | B42: =IFERROR(__xludf.DUMMYFUNCTION("""COMPUTED_VALUE"""),49.0) -> 49 | C42: =IFERROR(__xludf.DUMMYFUNCTION("""COMPUTED_VALUE"""),15925.0) -> 15925
A43: =IFERROR(__xludf.DUMMYFUNCTION("""COMPUTED_VALUE"""),"Project Management") -> Project Management | B43: =IFERROR(__xludf.DUMMYFUNCTION("""COMPUTED_VALUE"""),35.0) -> 35 | C43: =IFERROR(__xludf.DUMMYFUNCTION("""COMPUTED_VALUE"""),11375.0) -> 11375
A44: =IFERROR(__xludf.DUMMYFUNCTION("""COMPUTED_VALUE"""),"Post-Launch Support") -> Post-Launch Support | B44: =IFERROR(__xludf.DUMMYFUNCTION("""COMPUTED_VALUE"""),0.0) -> 0 | C44: =IFERROR(__xludf.DUMMYFUNCTION("""COMPUTED_VALUE"""),0.0) -> 0

Sheet ASIS Sample
A1: Workstream | B1: Service_Title | C1: Customer_Story | D1: Suggested_Path | E1: Assumptions | F1: Estimated_Low_Hours | G1: Estimated_High_Hours
A2: Discovery + Requirements + Solutioning Workshops | B2: Process + Requirements Gathering Workshops | C2: ASIS needs strategic guidance to map current and future state processes across all tech stack dependent systems. | D2: A8 and ASIS to execute multiple workshops with stakeholder groups to document requirements and identify optimization opportunities. | E2: - All sessions recorded - ASIS project champion to support identifying key stakeholder groups - These sessions may be a hybrid of discovery and collaborative solutioning - A8 to document action items - A8 to collaborate on information intake from ICs and additional stakeholders (eg. Surveyed information, user stories) | F2: 16 | G2: 20
A3: Discovery + Requirements + Solutioning Workshops | B3: AMS Reverse Demos | C3: ASIS needs to demonstrate current processes and pain points within their current AMS. | D3: A8 and ASIS to conduct reverse demos, with ASIS resources leading the demo within current platforms. | E3: - A8 to review recorded sessions from previous engagement - May also include additional time for Magento and other platforms - ASIS to provide support from AMS industry experts to support evaluation - ASIS to identify pain points and inefficiencies - Both teams to catalog "must-have" vs "nice-to-have" functionality | F3: 6 | G3: 10
A4: Discovery + Requirements + Solutioning Workshops | B4: System Architecture Consulting + Strategy Workshops | C4: ASIS needs A8's expertise to evaluate current tech stack and design an optimal integration approach. | D4: A8 to understand and document current systems data flows and integration requirements to support creation of the future-state architecture plan. | E4: - Future deliverable will be a tech stack overview document with data flow diagrams - SSO Requirements include but are not limited to: - Needs to support SSO across all partner websites - Must be standards compliant using common web authentication methods: SAML, OAuth 2.0, OpenID - Identity provider could be part of the new member platform/AMS as long as it: - Is standards compliant - Doesn't have egregious costs - Doesn't limit future flexibility | F4: 8 | G4: 12
A5: Discovery + Requirements + Solutioning Workshops | B5: AMS + Tech Stack Requirement Documentation | C5: ASIS needs clear documentation of requirements for MVP and future phases. Along with clear requirements documented to support the RFP creation. | D5: A8 to create detailed requirements docs for applicable platforms. | E5: - A8 to document requirements, workflows, and system interactions - Tech stack visuals with integration dependencies noted - Visuals created on Lucid boards - Written documentation created in Google Docs and Sheets (exportable) | F5: 12 | G5: 16
A6: AMS Selection + RFP Support | B6: RFP Strategy Support + Consulting | C6: ASIS needs strategic guidance on AMS vendor selection and the RFP process. | D6: A8 to provide support evaluating AMS platforms, partners, and reviewing the RFP content. | E6: - A8 to remain strategic partner with a holistic tech stack and HubSpot-first strategy (we are not AMS leading experts) - A8 to review ASIS's RFP template and certification RFP example - A8 to partner with AMS expert consultants (Delcor, Effective DB, etc.) - Define evaluation criteria focusing on business outcomes vs features - A8 can support content editing on requirement sections, per the created documentation from discovery - Support RFP timeline planning aligned with budgeting cycle (and phased approach) | F6: 18 | G6: 20
A7: AMS Selection + RFP Support | B7: AMS Candidate Demos | C7: ASIS needs a strategic partner to support evaluation of AMS platforms to confirm requirements are met and aligned. | D7: A8 to support ASIS by actively attending AMS demos and key meetings. | E7: - A8 to receive support from AMS industry expert partners for vendor evaluation - All demos and meetings to be recorded - A8 to attend vendor demonstrations - Time is inclusive of internal meetings with ASIS to support dbriefs - ASIS leads coordination of demo scheduling for this phase | F7: 15 | G7: 20
A8: AMS Selection + RFP Support | B8: AMS Selection Process Support + Proposal Evaluation | C8: ASIS needs a structured approach to evaluate and select AMS vendor(s). | D8: A8 to provide consulting support on both the platform selection process and evaluating proposals to ensure ASIS's Phase 2 requirements are met. | E8: - A8 and contractor to support vendor shortlist recommendations with AMS expert partners - A8, AMS expert, and ASIS team to collaborate on decision criteria - A8 to support validation vendor alignment with MVP requirements - A8 to review technical evaluation of proposed solutions and integration capabilities - A8 to attend leadership presentations for system selection - A8 will not be involved with price negotiations and procurement | F8: 18 | G8: 20
A9: Implementation Planning | B9: Critical Process Mapping + Documentation | C9: ASIS needs detailed process flows documented for all key workflows and processes within their tech stack, AMS, and CRM. | D9: A8 to create swimlane diagrams showing system and user interactions where necessary. | E9: - This is an execution task defined by the Requirements & Solutioning deliverables - Process flows by team/function | F9: 12 | G9: 15
A10: Implementation Planning | B10: Data Migration Planning | C10: ASIS needs strategy for migrating data from legacy systems into new and existing systems for Phase 2. | D10: A8 to create a detailed migration plan including data cleanup mapping and validation approach. | E10: - Source system documentation - Data mapping documentation | F10: 8 | G10: 10
A11: Implementation Planning | B11: Training + Change Management Strategy | C11: ASIS needs a clear plan for user onboarding and adoption in Phase 2. | D11: Develop training approach and timeline aligned with implementation phases | E11: - Training modality recommendations - User group identification - Timeline planning | F11: 6 | G11: 8
A12: Implementation Planning | B12: Implementation Planning + Strategy | C12: ASIS needs a strategy for implementing their Phase 2 tech stack, and to avoid risk and lost materials in future phases. | D12: A8 to combine all resources and create a detailed implementation plan that aligns with proposed AMS responsibilities. | E12: - Inclusive of migration timeline(s), AMS onboarding, all user training, and required integrations - AMS selection and AMS partner SOWs must be signed or aligned between ASIS and A8 - A8 and ASIS to align on terminology (eg. MVP vs Phase 2 vs Phase 3) | F12: 10 | G12: 12
A13: Implementation Planning | B13: A8 Phase 2 SOW + Requirements | C13: ASIS needs a clear SOW and documented requirements for Phase 2 to ensure success of their AMS roll out. | D13: A8 to provide a detailed SOW and timeline estimate that aligns with all requirements and compliments the proposed AMS work. | E13: - SOW to include cost estimates along with assets documented above | F13: 10 | G13: 15
A14: Implementation Planning | B14: Leadership Presentation + Documentation | C14: ASIS needs support presenting the Phase 2 implementation plan and SOW to their executive leadership. | D14: A8 to support ASIS stakeholders with presentations and alignment calls to ensure all parties are in alignment before Phase 2 begins. | E14: - Presentation materials to include an executive deck, along with all resources documented above | F14: 8 | G14: 10
A15: Flex Hours | B15: Flex Hours | C15: These scoped hours will provide ASIS additional support for ad hoc requests that come up during the project. This budget could also be allocated for additional consulting, evaluation, or process documentation. | E15: - Inclusive of ad hoc requests, additional meetings, and additional project planning. | F15: 40 | G15: 40

Sheet Colibri Sample
A1: Workstream | B1: Service_Title | C1: Customer_Story | D1: Suggested_Path | E1: Assumptions | F1: Estimated_Low_Hours | G1: Estimated_High_Hours
A2: Discovery Interviews | B2: Internal A8 Exercise - Real Estate + Healthcare Overlay | C2: Colibri + A8 need immediate insights from existing A8 work to accelerate the project timeline and identify similarities (or differences) across ecosystems. | D2: A8 to conduct internal exercise and overlay Real Estate and Healthcare audit findings to identify standardization patterns, gaps, and context before stakeholder interviews. | E2: - Access to complete RE and HC audit documentation, such as process and system architecture maps, and internal A8 resources - Focus on journey standardization opportunities - Focus on marketing automation - Focus on foundational model for Crawl, Walk, Run, Fly - Focus on segmentation structure/strategy - Focus on metrics & KPIs - Cross-ecosystem comparison methodology documented | F2: 10 | G2: 14
A3: Discovery Interviews | B3: Cross-Ecosystem Stakeholder Interviews | C3: Colibri has 5 ecosystems with separate marketing approaches doing identical functions, requiring validation interviews to understand nuances beyond RE/HC. | D3: A8 to conduct interviews with marketing heads and key stakeholders across these Ecosystems: Sales, Service, Accounting, Financial Services, Healthcare, Real Estate, Teaching, and Valuation Property Services to validate baseline standards and capture unique requirements and determine which standards apply at the Colibri-wide level vs. ecosystem level. This will include exploration into our Sales & Service areas at an ecosystem level. | E3: - Assumes access to heads of marketing across all ecosystems. Limit to key leaders in Marketing, Sales, and Service per ecosystem. - Aptitude 8 will use existing documentation where possible. - Structured interviews based on existing RE/HC learnings - Focus on full lifecycle marketing, pain points, and standardization readiness - All sessions recorded and transcribed | F3: 22 | G3: 30
A4: Discovery Interviews | B4: Colibri Reporting + Analytics Interviews | C4: Colibri needs an understanding and alignment on their own corporate-level reporting requirements to inform their decision strategy. | D4: A8 to conduct reporting-based interviews to gain an understanding of the type of insights Colibri is attempting to make across all ecosystems. | E4: - Assumes access to heads of marketing and key players across all ecosystems along with executive leadership access/feedback - Reviews PowerBI, GA4, Matomo, and other platforms being utilized - All sessions recorded and transcribed | F4: 10 | G4: 15
A5: Current-state Process Mapping + User Stories | B5: Customer Journey Documentation - Ecosystem | C5: Colibri needs an understanding of current customer journeys so they can assess the level of sophistication and complexities across all brands. | D5: A8 to document the following marketing ops dependencies: Marketing customer journeys, Marketing automation workflows, Lead scoring mechanisms, Lifecycle stages (marketing-owned), Marketing technology stack (HubSpot, Salesforce Marketing Cloud, Eloqua), and Marketing processes and sales handoffs | E5: - Journey standardization based on successful Healthcare and Real Estate implementations - Journey templates account for ecosystem-specific requirements - Includes an understanding of the core lifecycle management functions | F5: 8 | G5: 12
A6: Current-state Process Mapping + User Stories | B6: Gap Analysis Across All Ecosystems | C6: Colibri needs comprehensive gap analysis across Healthcare, Real Estate, Financial Services, Accounting, VPS, and remaining ecosystems to identify standardization requirements. | D6: A8 to conduct detailed gap analysis comparing current state across all ecosystems against proposed baseline standards to identify areas requiring standardization vs. legitimate customization. | E6: - Completed Phase 1 inventory and interviews - Baseline standards framework from RE/HC overlay - Gap analysis methodology - Essential vs. standardizable variance identification - Resource requirement assessment for gap closure - Prioritization framework for implementation | F6: 20 | G6: 24
A7: Current-state Process Mapping + User Stories | B7: Enhanced Current-State Process Mapping + Ecosystem Standards Framework | C7: Building on existing RE/HC work, Colibri needs comprehensive process mapping that defines standardization at both the Colibri enterprise level and individual ecosystem level, with clear delineation of where differences are essential versus where they can be standardized. | D7: A8 to expand current-state mapping by blending existing ecosystem work with enterprise-level standardization framework, creating playbooks for crawl/walk/run/fly marketing operations maturity levels across all ecosystems. A8 will also distinguish which deliverables are enterprise standards vs. ecosystem-specific, including the rational behind the differences. | E7: - Standardization at the Colibri level AND the ecosystem level and call out where they're different - Playbooks for crawl, walk, run, fly marketing ops - Colibri leadership alignment on enterprise-level vs ecosystem-level standardization philosophy - Clear delineation between essential ecosystem differences vs standardizable processes including governance for cross-brand frequency caps, suppression logic, and multi-licensing handling - Technology-agnostic recommendations will support future platform migrations (SFMC or otherwise) - Current marketing technology implementations are accessible for audit and comparison | F7: 15 | G7: 18
A8: Marketing Ops Strategy Roadmap | B8: Comprehensive Marketing Strategy Document | C8: Colibri requires a unified marketing strategy document that consolidates current state assessment, marketing capability framework, and future-state operating model to serve as the foundation for their digital transformation and stakeholder alignment. | D8: A8 to develop comprehensive marketing strategy document including current state inventory, consolidated capability framework, future-state operating model, standardized customer journeys, lifecycle stages, lead scoring approach, and metrics measurement framework. | E8: - Summary of current state assessment and inventory of current state journeys and artifacts - Consolidated Marketing Capability Framework - Defined future-state marketing operating model. - Determine where standards apply at the Colibri-wide level vs. ecosystem level - Standardized customer journeys, lifecycle stages, and lead scoring approach. - Standardized Lifecycle and Lead Scoring Implementation Guide of Metrics and Measurement Framework - Define KPIs and success metrics and agree across all ecosystem leads - Define KPIs and success metrics and agree across all ecosystem leads | F8: 8 | G8: 10
A9: Marketing Ops Strategy Roadmap | B9: Colibri Marketing Automation & Operations Blueprint | C9: Colibri needs a technology-agnostic marketing operations blueprint that provides standardized journey templates, lifecycle communications plans, lead scoring frameworks, and governance structures that can be implemented across all ecosystems regardless of platform choice. | D9: A8 to create comprehensive marketing automation blueprint including standardized journey templates, lifecycle stage communication plans, lead scoring and automation framework, and marketing governance structure for sustainable operations. | E9: - Standardized journey templates - Communications Plan for Lifecycle stages - Lead scoring and automation framework - Marketing Governance | F9: 10 | G9: 12
A10: Workshops + Future Requirements Validation | B10: Ecosystem vs Enterprise Standardization Strategy Workshop | C10: Colibri needs to answer the first-order question: should standardization happen at ecosystem level or corporate/enterprise level across all of Colibri. | D10: A8 to facilitate strategic workshops with their findings and A8's recommendation based on the discovery and process mapping work in earlier phases. Colibri stakeholders to evaluate A8's recommendations and documented trade-offs to then align with A8 on the best path forward. A8 will explore and help determine which standards apply at the Colibri-wide level vs. ecosystem level including defining and documenting enterprise-level standards for data structure, naming conventions, and permissions. | E10: - Participation from Christa Chancellor, Prabhu Inbarajan, Yazir Mendez, and other marketing heads - Structured decision framework - Trade off analysis between ecosystem vs enterprise approaches - Business impact modeling for each approach - Decision documentation with rationale - Governance for cross-brand frequency caps, suppression logic, and multi-license handling. | F10: 10 | G10: 14
A11: Implementation Planning + Strategy Presentation | B11: Comprehensive Strategy Documentation & Executive Summary | C11: Based on the strategic decision, Colibri needs complete strategy documentation that serves as the north star for implementation, including executive summary for board and investor communications. | D11: A8 to create comprehensive strategy documentation with executive summary, high-level implementation plans, and supporting materials for internal and external stakeholder communication. | E11: - Executive-level summary for board presentations - Quick wins identification and prioritization - Strategy documentation for implementation teams - Supporting analysis and rationale documentation - Implementation frameworks - Success metrics and measurement tools - Change management guidance - Risk mitigation strategies documentation - Provide a high-level readout of Discovery & Interview Learnings a week after the last interview - Weekly checkpoints with Colibri - High-level deliverable review during week 5 to validate that the A8 Team is on track and make possible adjustments prior to stakeholder reviews | F11: 16 | G11: 24
A12: Implementation Planning + Strategy Presentation | B12: Leadership Presentation | C12: Colibri's project team needs support presenting the implementation plan and SOW to their executive leadership. | D12: A8 to present to Colibri leadership to ensure all parties are in alignment before the next implementation phase. | E12: - Presentation materials to include an executive deck, along with all resources documented above. - A8 to ensure strategic buy-in across marketing leads across all ecosystems, to provide a finalized product that has an agreed-upon framework. - A8 to present the implementation plan and SOW to Colibri's executive leadership. - A8 to ensure strategic buy-in across marketing leads across all ecosystems, to provide a finalized product that has an agreed-upon framework. A8 to support presenting the implementation plan and SOW to Colibri's executive leadership. | F12: 8 | G12: 10

Sheet Scratch
A3: Hide | B3: Strategy Development | C3: Current-State Process Mapping Across All GTM Teams | D3: Taoglas needs comprehensive documentation of existing processes across all go-to-market teams to identify standardization opportunities and process gaps. | E3: A8 to document current-state processes for Direct Sales Distribution M&I Marketing and Customer Service through stakeholder interviews and system walkthroughs. | F3: - Access to current systems and processes across all GTM teams - Subject matter experts available for comprehensive process walkthroughs - Process documentation created in Lucid/Miro for visual collaboration - Regional and channel-specific process variations documented | G3: 15 | H3: 22 | I3: =IF(AND(G3<>"",H3<>""),ROUNDUP(AVERAGE(G3:H3),0),"") -> 19 | J3: FALSE
A4: Hide | B4: Custom Integration Strategy + Technology Planning | C4: Cadre AI Initiative Coordination Meetings | D4: Taoglas needs ongoing coordination between A8 CRM optimization and Cadre AI initiatives to ensure alignment avoid conflicts and maximize synergies between concurrent projects. | E4: A8 to participate in regular coordination meetings with Cadre team and facilitate integration planning between CRM optimization and AI initiative workstreams. | F4: - Regular meeting cadence established with Cadre AI team - Joint planning sessions for data sharing and integration requirements - Timeline coordination to optimize resource utilization across initiatives - Conflict resolution and priority setting for overlapping requirements - Documentation of joint deliverables and shared success metrics | G4: 8 | H4: 15 | I4: =IF(AND(G4<>"",H4<>""),ROUNDUP(AVERAGE(G4:H4),0),"") -> 12 | J4: FALSE
A5: Hide | B5: Implementation Planning | C5: Data Migration & Integration Strategy | D5: Taoglas needs comprehensive strategy for optimizing data quality and enhancing integrations with Tacton AEB SAP while maintaining business continuity. | E5: A8 to create detailed data optimization plan including current integration enhancement mapping validation and quality improvement approach. | F5: - Current integration documentation and data flow mapping completed - Data quality assessment across HubSpot Tacton AEB and SAP systems - Integration enhancement specifications and testing approach defined - Business continuity and rollback procedures documented for critical integrations - Performance monitoring and optimization procedures established | G5: 15 | H5: 22 | I5: =IF(AND(G5<>"",H5<>""),ROUNDUP(AVERAGE(G5:H5),0),"") -> 19 | J5: FALSE
A6: Hide | B6: Strategy Development | C6: Tactical Quick Wins Implementation Roadmap | D6: Taoglas needs immediate tactical recommendations for quick wins in forecasting data entry reporting and net new company creation to demonstrate early value. | E6: A8 to create tactical implementation roadmap for identified quick wins with specific configuration steps and success metrics. | F6: - Quick win opportunities validated through discovery process - Forecasting and reporting requirements clearly documented - Company creation workflow optimization specifications defined - Implementation steps prioritized by complexity and business impact - Success metrics and measurement approach defined for each quick win | G6: 12 | H6: 16 | I6: =IF(AND(G6<>"",H6<>""),ROUNDUP(AVERAGE(G6:H6),0),"") -> 14 | J6: FALSE
