Workbook

Sheet Input
A1: Library_ID | B1: Workstream | C1: Service_Title | D1: Customer_Story | E1: Suggested_Path | F1: Assumptions | G1: Estimated_Low_Hours | H1: Estimated_High_Hours | I1: Contracted_Hours | J1: Display | K1: Requires_Clarification | L1: Function | M1: Potential_Variance | N1: Project_ID | O1: Internal_Notes | P1: Task_Link
B2: Requirements Gathering Workshops | C2: Requirements Gathering Workshops | D2: As a sales team, I need to participate in structured requirements workshops so we can define data modeling, sales, quoting, and reporting needs to support a scalable HubSpot architecture. | E2: 1. Conduct 4 workshops focused on data model, sales process, quoting, and reporting. 2. Document requirements into BPMN diagrams and user stories. | F2: - Key stakeholders will attend 4 workshops (sales, quoting, reporting, data modeling). - Workshops will be scheduled with adequate lead time to ensure full participation from sales leadership, finance, and operations. - Client will provide representative examples of Shopify, Amazon, and B2B orders to inform discovery. - Client will share current HubSpot dashboards, even if incomplete or inaccurate, to review usability gaps. - Workshops will focus on defining current vs. future state processes (not building solutions in real-time). - Output will include BPMN diagrams, user stories, and prioritized requirements by business need. - Client team will identify a decision-maker to approve workshop outputs and requirements. - Data quality constraints (e.g., duplicates, missing fields) will be documented but not remediated during workshops. | G2: 8 | H2: 14 | I2: =MEDIAN(G2:H2) -> 11 | J2: Now | K2: FALSE | L2: Consulting
B3: Solution Design & Validation | C3: Solution Validation | D3: As a sales team, we need to review and validate the proposed solution design so that we can confirm it meets our requirements before build. | E3: 1. Facilitate up to 2 validation sessions. 2. Present ERD, Process Map, UAT scenarios, Training Plan, Go-Live Plan, and Gantt Chart. . Incorporate feedback and adjust hours if necessary. | F3: - Up to 2 solution validation sessions will be scheduled within 10 business days of workshop completion. - Deliverables will include ERD, process maps, UAT scenarios, training plan, go-live plan, and high-level Gantt. - Client will provide timely feedback (within 3–5 business days) on all deliverables to stay on schedule. - Any requested changes outside defined requirements may increase hours or require a formal change order. - Validation will confirm alignment with sales adoption goals and B2B scalability targets. - Technical diagrams (ERD, TRD) will reflect current known integrations (HubSpot & Netsuite). - Client acknowledges that feedback should come consolidated from key stakeholders to avoid scope creep. - Approval of the validated solution design will serve as the basis for build and implementation. | G3: 8 | H3: 14 | I3: =MEDIAN(G3:H3) -> 11 | J3: Now | K3: FALSE | L3: Consulting
B4: Sales Implementation | C4: Rebuild Data Model | D4: As a sales team, we need our HubSpot data model rebuilt with commission, LTV, partner/customer associations, multi-location clients, and product price books so we can report and operate effectively. | E4: 1. Define calculated properties for commission and LTV. 2. Configure association labels (Partners vs Customers). 3. Create parent/child company relationships. 4. Implement product structure with 3 price books (MSRP, 25% off, 50% off). | F4: - Calculated properties (commission, LTV) will be limited to logic defined during requirements. - Association labels (partners, customers) will be aligned to Incrediwear’s B2B structure. - Parent-child company relationships will reflect multi-location clients and international distributors. - Product structure will include up to 3 price books (MSRP, 25%, 50%). - Data sources for backfill (NetSuite, Shopify, Amazon) will be accessible for mapping and validation. - Client will provide subject matter experts for product/pricing validation. - Data migration will be limited to records defined in scope; historical activity is excluded. | G4: 6 | H4: 8 | I4: =MEDIAN(G4:H4) -> 7 | J4: Now | K4: FALSE | L4: Consulting
B5: Sales Implementation | C5: Record Customization | D5: As a sales team, we need record layouts customized by business type so that each team has the relevant properties and views for their process. | E5: Aptitude 8 should customize 6 layouts: Contacts, Companies (4 business types), Deals. | F5: - 6 layouts will be customized (Contacts, Deals, and 4 Company record types: Retail, Medical, Teams, International). - Each layout will include only fields relevant to that business type. - Dependent properties will be configured based on data gathered in workshops. - Layouts will remain within HubSpot’s out-of-the-box customization limits (no coded UI). - Users will be assigned correct default views by role/team. - Client will confirm naming conventions for business types to avoid ambiguity. - Record customizations will not include workflow automation (handled separately). - Validation of layouts will occur with sales leadership before rollout. | G5: 4 | H5: 7 | I5: =MEDIAN(G5:H5) -> 5.5 | J5: Now | K5: FALSE | L5: Consulting
B6: Sales Implementation | C6: Backfill New Parent-Child Relationship Structure | D6: As a sales team, we need to migrate existing records into the new HubSpot data structure so that our operations can continue without disruption. | E6: Aptitude 8 should export the relevant records from HubSpot so they can transform the data in spreadsheet, specifically, apply the correct parent-child relationships to companies. Once transformation is complete, import the relationships into HubSpot. | F6: - Transformation of data will be performed in spreadsheet format, supplied by Aptitude 8 for client review. - Correct contact and deal associations must already exist or be clearly identifiable in exported data. - No historical activities, notes, or tasks will be remapped during backfill. - Total record counts are ~541 deals, ~4,800 companies, and ~407,000 contacts. - Client will provide validation of test imports before full backfill execution. - Backfill will not address duplicate records beyond parent-child relationships. - Client acknowledges that backfill may expose additional data quality issues requiring future cleanup. | G6: 15 | H6: 30 | I6: =MEDIAN(G6:H6) -> 22.5 | J6: Now | K6: FALSE | L6: Consulting
B7: Sales Implementation | C7: Optimize Sales Pipeline | D7: As a sales team, we need to rebuild our B2B pipeline with clear forecasting and criteria so that deals are consistently managed, while keeping eCom pipeline updates minimal. | E7: Aptitude 8 should update pipeline stages, required fields, pipeline rules, and other pipeline specific settings like deal tags. | F7: - Only the B2B pipeline will be updated; eCommerce pipelines will remain largely unchanged (minus minor updates related to the Netsuite integration). - Pipeline stage definitions will be aligned to agreed sales process maps from workshops. - Required fields for stage progression will be finalized during design validation. - Forecasting logic will be basic. - Client will confirm territory definitions for roll-up reporting. - No additional pipelines will be created unless explicitly added via change order. - Pipeline rules will be configured with HubSpot’s out-of-the-box functionality. - Validation will occur with sales managers before rollout. | G7: 4 | H7: 8 | I7: =MEDIAN(G7:H7) -> 6 | J7: Now | K7: FALSE | L7: Consulting
B8: Sales Implementation | C8: Customize Sales Workspace | D8: As a sales rep, I need tailored HubSpot workspace views for tasks, deals, and leads so that I can manage my pipeline efficiently. | E8: 1. Configure custom workspace views for tasks, deal management, and lead management. 2. Validate with sales leadership. | F8: - Custom workspaces will be limited to 3 areas: tasks, deals, and leads. - Views will be based on fields and filters defined during workshops. - Sales leadership will validate workspace configurations before rollout. - No custom-coded UI or third-party add-ons are included. - Client will provide clarity on priority fields for each workspace. - Workspaces will be configured for role-based adoption (rep vs manager). - Validation will occur with a sample group of users. - Workspaces will not include marketing or service hub features outside sales scope. | G8: 1 | H8: 3 | I8: =MEDIAN(G8:H8) -> 2 | J8: Now | K8: FALSE | L8: Consulting
B9: Sales Implementation | C9: Implement Custom Lead/Engagement Scoring | D9: As a sales team, we need basic lead and engagement scoring so that we can prioritize opportunities and reps are motivated to focus on high-value deals. | E9: 1. Configure deal tags (5). 2. Create engagement scoring model (basic to moderate complexity). 3. Launch v1 scoring for initial use. | F9: - Engagement scoring will be limited to a basic-to-moderate complexity model. - Initial scoring will include up to 5 deal tags. - Model is intended as v1; further refinement may be part of future phases. - Data available for scoring (activities, lifecycle stage, product interest) must already exist in HubSpot. - Client will provide input on priority activities to drive scoring (e.g., calls, emails, meetings). - Validation will occur with sales leadership before rollout. - Engagement scores will be visible in reports and record views but not tied to automation beyond scope. | G9: 4 | H9: 7 | I9: =MEDIAN(G9:H9) -> 5.5 | J9: Now | K9: FALSE | L9: Consulting
B10: Sales Implementation | C10: Implement Quote Template | D10: As a sales team, we need a basic quote template so that we can generate and send quotes directly from HubSpot. | E10: 1. Configure OOTB legacy quote template. 2. Test for formatting and accuracy. | F10: - Quote template will use HubSpot’s out-of-the-box legacy quote functionality. - No custom branding beyond standard template fields is included. (This can be done by the Incrediwear team) - No approval workflows or e-signature integrations are included. - Formatting and testing will be limited to one template. - Client will provide company logo and required fields for quote. - Taxes, shipping, and discounts must be handled by HubSpot’s native capabilities. - No external commerce tools (e.g., CommerceHub) are required. - Client will validate template before rollout. | G10: 3 | H10: 5 | I10: =MEDIAN(G10:H10) -> 4 | J10: Now | K10: FALSE | L10: Consulting
B11: Sales Implementation | C11: Sales Automations | D11: As a sales team, we need automation for territory assignment, communications, and CRM updates so that manual processes are reduced and efficiency increases. | E11: 1. Automate territory assignments. 2. Build workflows for automated comms. 3. Create workflows to automate CRM updates (e.g., property updates, deal stage progression). | F11: - Automation will be limited to out-of-the-box HubSpot workflows. - Territory assignment rules will be defined and approved by client. - Automated communications will be limited to email sequences within HubSpot. - Automations will focus on reducing manual/administrative tasks. - Client will provide test scenarios for validation. - UAT will be required before rollout. - Any advanced automation (e.g., AI routing, custom code) is outside scope. | G11: 5 | H11: 7 | I11: =MEDIAN(G11:H11) -> 6 | J11: Now | K11: FALSE | L11: Consulting
B12: Sales Implementation | C12: Sales Reports & Dashboards | D12: As sales leadership, we need reports and dashboards to track performance, pipeline, and product sales so that we can manage effectively. | E12: 1. Configure OOTB reports with slight customizations. 2. Build custom roll-up report: distributor → territory rep → manager. 3. Create product/line item and goal reports. | F12: - Most reports will be built using HubSpot’s out-of-the-box reporting tools. - Custom roll-up report (distributor → territory rep → manager) will be the only true custom build. - Product/line item reporting will rely on clean product structure implemented in data model rebuild. - Goal reporting will be configured for B2B pipeline only. - Dashboards will be role-based (rep, manager, leadership). - Client will provide key KPIs for dashboard design. - Reports will be limited to HubSpot data; no external BI tools included. - Reports will be validated in UAT before go-live. | G12: 7 | H12: 10 | I12: =MEDIAN(G12:H12) -> 8.5 | J12: Now | K12: FALSE | L12: Consulting
B13: Solution Design & Validation | C13: Netsuite Technical Requirements Document | D13: As a sales team, we need a documented Technical Requirements Document for the NetSuite integration so that development can proceed against a clear blueprint. | E13: 1. Conduct integration discovery workshops. 2. Map requirements for objects, triggers, sync frequency. 3. Produce TRD including data flows, dependencies, and integration approach. | F13: - TRD will include ERD, data mapping, triggers, dependencies, and sync frequency. - Discovery workshops will cover object mapping, field mapping, and sync logic for Contacts, Companies, Deals, and Products. - Client stakeholders (finance, operations, sales) will attend sessions to confirm requirements. - Client will provide sample orders (Shopify, Amazon, B2B) to confirm required fields. - Payment status requirements (Paid/Partial/Unpaid + date) will be documented in TRD. - Any changes to integration scope after TRD approval will require a change order. - Client will validate TRD deliverables within 5 business days to maintain timeline. - TRD will serve as the blueprint for integration build and cannot be bypassed. | G13: 15 | H13: 25 | I13: =MEDIAN(G13:H13) -> 20 | J13: Now | K13: FALSE
B14: Netsuite Integration | C14: Implement Netsuite Integration | D14: As a sales team, we need a custom bi-directional integration between NetSuite and HubSpot so that sales, finance, and operations can share consistent data. | E14: 1. Sync Contacts, Companies, Deals, and Products bi-directionally. 2. Include payment status (Paid/Partial/Unpaid + date) on deals instead of invoices. 3. Build integration on AWS with no middleware. 4. Validate sync logic and error handling. | F14: - Objects in scope: Contacts, Companies, Deals, Products. - Invoices are excluded; only payment status (Paid/Partial/Unpaid) and payment date will sync. - Integration will be custom built on AWS (no middleware such as Dell Boomi, Celigo, or DataSync). - Bi-directional sync logic will be confirmed in TRD before build. - Integration will include error handling and logging to surface sync failures. - NetSuite API credentials and sandbox access will be provided by client. - Integration is limited to 4 objects; additional objects will require a change order. - Client IT team will support initial connectivity testing between NetSuite and AWS. | G14: 42 | H14: 70 | I14: =MEDIAN(G14:H14) -> 56 | J14: Now | K14: FALSE | L14: Development
B15: Netsuite Integration | C15: Netsuite Integration User Acceptance Testing | D15: As a sales and operations team, we need to test and validate the NetSuite integration so that it functions as intended before launch. | E15: 1. Create UAT plan with test cases. 2. Guide client through test execution. 3. Track issues in ClickUp, resolve, and regression test. | F15: - UAT will be limited to NetSuite integration (Contacts, Companies, Deals, Products). - UAT plan will include test cases for new record creation, updates, deletes, and error handling. - Client resources will execute UAT with guidance from Aptitude 8. - Up to 2 rounds of UAT feedback/defect resolution are included. - Defects outside agreed integration logic (e.g., data quality issues in source system) are out of scope. - Regression testing will occur after each round of fixes. - Client will provide a consolidated list of UAT testers and feedback owners. - UAT must be signed off before integration moves to production. | G15: 8 | H15: 12 | I15: =MEDIAN(G15:H15) -> 10 | J15: Now | K15: FALSE | L15: Development
B16: Launch | C16: Hypercare | D16: Incrediwear needs dedicated support immediately post launch to ensure a smooth transition to production and to address any bugs that come up during this post-launch period. | E16: Concentrated attention is given to issues/bugs that arise during this period as a result of the launch Client emails take top priority during this period Client meetings as needed (daily, every other day, twice per week, etc.) Additional team trainings or office hours, as needed and as time allows (otherwise this can be provided in the NEXT retainer) | F16: - This hypercare period is for 2 weeks (10 business days) post-launch - Hypercare support is only available during regular business hours on regular working days (i.e. no holidays or weekends) - Any unused Hypercare hours can be applied to the first month of the NEXT retainer - Hypercare hours may be applied to any issues, bugs, or questions that relate to the launch, but any new functionality requests will be backlogged for the NEXT retainer - Any hours needed for bug fixes beyond the scoped Hypercare hours will be billed as overage hours | G16: 10 | H16: 20 | I16: =MEDIAN(G16:H16) -> 15 | J16: Now | K16: FALSE
B17: Training & Documentation | C17: Sales Team Training | D17: As a sales and leadership team, we need targeted HubSpot training so that we can adopt the system effectively and maximize reporting value. | E17: 1. Deliver 2 training sessions for sales users. 2. Deliver 1 training session for leadership/admin on reporting & analytics. 3. Provide recordings and basic materials. | F17: - Up to 3 training sessions included (2 for sales users, 1 for leadership/admin). - Each session will be up to 60 minutes and delivered virtually. - Sessions will be recorded and shared with client for future reference. - Training content will cover features implemented in this project only. - Leadership/admin training will focus on reporting, dashboards, and management workflows. - Sales training will focus on pipeline management, tasks, and daily usage. - Client will ensure attendance of target users during training sessions. - Training will not cover advanced HubSpot features outside defined scope (e.g., Marketing Hub, Service Hub). | G17: 6 | H17: 10 | I17: =MEDIAN(G17:H17) -> 8 | J17: Now | K17: FALSE | L17: Consulting
B18: Training & Documentation | C18: Integration Documentation & Handoff | D18: As a technical team, we need documentation of the integration so that we can maintain and support it after go-live. | E18: 1. Produce integration documentation (data flows, dependencies, error handling). 2. Provide handoff session with client technical team. | F18: - Documentation will cover data flows, dependencies, error handling, and sync logic for in-scope integration. - One handoff session (up to 60 minutes) with client’s technical team is included. - Documentation will reflect final build only; changes post-handoff are not included. - Client technical team must have baseline NetSuite/HubSpot knowledge to understand handoff. - Error resolution instructions will be included but ongoing support is out of scope. - Documentation will not include third-party systems not involved in the integration. - Client is responsible for maintaining documentation after project handoff. | G18: 8 | H18: 12 | I18: =MEDIAN(G18:H18) -> 10 | J18: Now | K18: FALSE | L18: Consulting
B19: Training & Documentation | C19: HS Implementation Documentation | D19: As a client team, we need HubSpot implementation documentation so that we have reference materials for ongoing operations and new hire onboarding. | E19: 1. Create documentation for implemented HubSpot features. 2. Include process workflows, system instructions, and troubleshooting. | F19: - Documentation will cover HubSpot features implemented in this project (pipelines, layouts, automations, reports). - Documentation will be finalized after implementation and validated with client. - Future updates to documentation after project completion are not included in scope, but can be made available in Post Launch Support. | G19: 6 | H19: 12 | I19: =MEDIAN(G19:H19) -> 9 | J19: Now | K19: FALSE | L19: Consulting
B20: Post Launch Support | C20: Post Launch Support | D20: As a leadership team, we require additonal support post-launch in order to complete any remaining action items, follow-ups, or wish list items that have resulted from the Phase 1 workstreams. | E20: This retainer will build directly on the Phase 1 foundation while introducing new functionality that drives pipeline growth, campaign execution, and end-to-end visibility. | F20: Hours dedicated to post go-live support. These hours can be used for anything HubSpot related (reporting, training, iterations, additional asks, etc.) | G20: 30 | H20: 30 | I20: =IF(AND(G20<>"",H20<>""),ROUNDUP(AVERAGE(G20:H20),0),"") -> 30 | J20: Later | K20: FALSE
I21: =IF(AND(G21<>"",H21<>""),ROUNDUP(AVERAGE(G21:H21),0),"") | K21: FALSE
I22: =IF(AND(G22<>"",H22<>""),ROUNDUP(AVERAGE(G22:H22),0),"") | K22: FALSE
I23: =IF(AND(G23<>"",H23<>""),ROUNDUP(AVERAGE(G23:H23),0),"") | K23: FALSE
I24: =IF(AND(G24<>"",H24<>""),ROUNDUP(AVERAGE(G24:H24),0),"") | K24: FALSE
I25: =IF(AND(G25<>"",H25<>""),ROUNDUP(AVERAGE(G25:H25),0),"") | K25: FALSE
I26: =IF(AND(G26<>"",H26<>""),ROUNDUP(AVERAGE(G26:H26),0),"") | K26: FALSE
I27: =IF(AND(G27<>"",H27<>""),ROUNDUP(AVERAGE(G27:H27),0),"") | K27: FALSE
I28: =IF(AND(G28<>"",H28<>""),ROUNDUP(AVERAGE(G28:H28),0),"") | K28: FALSE
I29: =IF(AND(G29<>"",H29<>""),ROUNDUP(AVERAGE(G29:H29),0),"") | K29: FALSE
I30: =IF(AND(G30<>"",H30<>""),ROUNDUP(AVERAGE(G30:H30),0),"") | K30: FALSE
I31: =IF(AND(G31<>"",H31<>""),ROUNDUP(AVERAGE(G31:H31),0),"") | K31: FALSE
I32: =IF(AND(G32<>"",H32<>""),ROUNDUP(AVERAGE(G32:H32),0),"") | K32: FALSE
... I140: =IF(AND(G140<>"",H140<>""),ROUNDUP(AVERAGE(G140:H140),0),"") | K140: FALSE
K141: FALSE
K142: FALSE

Sheet ClickUp Import
A1: Task Type | B1: Task Name | C1: Description Content | D1: High Hours Estimate | E1: Contracted Hours
A2: Workstream | B2: Launch
A3: Customer Story | B3: Hypercare | C3: Incrediwear needs dedicated support immediately post launch to ensure a smooth transition to production and to address any bugs that come up during this post-launch period. Concentrated attention is given to issues/bugs that arise during this period as a result of the launch Client emails take top priority during this period Client meetings as needed (daily, every other day, twice per week, etc.) Additional team trainings or office hours, as needed and as time allows (otherwise this can be provided in the NEXT retainer) - This hypercare period is for 2 weeks (10 business days) post-launch - Hypercare support is only available during regular business hours on regular working days (i.e. no holidays or weekends) - Any unused Hypercare hours can be applied to the first month of the NEXT retainer - Hypercare hours may be applied to any issues, bugs, or questions that relate to the launch, but any new functionality requests will be backlogged for the NEXT retainer - Any hours needed for bug fixes beyond the scoped Hypercare hours will be billed as overage hours | D3: 20 | E3: 15
A4: Workstream | B4: Netsuite Integration
A5: Customer Story | B5: Implement Netsuite Integration | C5: As a sales team, we need a custom bi-directional integration between NetSuite and HubSpot so that sales, finance, and operations can share consistent data. 1. Sync Contacts, Companies, Deals, and Products bi-directionally. 2. Include payment status (Paid/Partial/Unpaid + date) on deals instead of invoices. 3. Build integration on AWS with no middleware. 4. Validate sync logic and error handling. - Objects in scope: Contacts, Companies, Deals, Products. - Invoices are excluded; only payment status (Paid/Partial/Unpaid) and payment date will sync. - Integration will be custom built on AWS (no middleware such as Dell Boomi, Celigo, or DataSync). - Bi-directional sync logic will be confirmed in TRD before build. - Integration will include error handling and logging to surface sync failures. - NetSuite API credentials and sandbox access will be provided by client. - Integration is limited to 4 objects; additional objects will require a change order. - Client IT team will support initial connectivity testing between NetSuite and AWS. | D5: 70 | E5: 56
A6: Customer Story | B6: Netsuite Integration User Acceptance Testing | C6: As a sales and operations team, we need to test and validate the NetSuite integration so that it functions as intended before launch. 1. Create UAT plan with test cases. 2. Guide client through test execution. 3. Track issues in ClickUp, resolve, and regression test. - UAT will be limited to NetSuite integration (Contacts, Companies, Deals, Products). - UAT plan will include test cases for new record creation, updates, deletes, and error handling. - Client resources will execute UAT with guidance from Aptitude 8. - Up to 2 rounds of UAT feedback/defect resolution are included. - Defects outside agreed integration logic (e.g., data quality issues in source system) are out of scope. - Regression testing will occur after each round of fixes. - Client will provide a consolidated list of UAT testers and feedback owners. - UAT must be signed off before integration moves to production. | D6: 12 | E6: 10
A7: Workstream | B7: Requirements Gathering Workshops
A8: Customer Story | B8: Requirements Gathering Workshops | C8: As a sales team, I need to participate in structured requirements workshops so we can define data modeling, sales, quoting, and reporting needs to support a scalable HubSpot architecture. 1. Conduct 4 workshops focused on data model, sales process, quoting, and reporting. 2. Document requirements into BPMN diagrams and user stories. - Key stakeholders will attend 4 workshops (sales, quoting, reporting, data modeling). - Workshops will be scheduled with adequate lead time to ensure full participation from sales leadership, finance, and operations. - Client will provide representative examples of Shopify, Amazon, and B2B orders to inform discovery. - Client will share current HubSpot dashboards, even if incomplete or inaccurate, to review usability gaps. - Workshops will focus on defining current vs. future state processes (not building solutions in real-time). - Output will include BPMN diagrams, user stories, and prioritized requirements by business need. - Client team will identify a decision-maker to approve workshop outputs and requirements. - Data quality constraints (e.g., duplicates, missing fields) will be documented but not remediated during workshops. | D8: 14 | E8: 11
A9: Workstream | B9: Sales Implementation
A10: Customer Story | B10: Rebuild Data Model | C10: As a sales team, we need our HubSpot data model rebuilt with commission, LTV, partner/customer associations, multi-location clients, and product price books so we can report and operate effectively. 1. Define calculated properties for commission and LTV. 2. Configure association labels (Partners vs Customers). 3. Create parent/child company relationships. 4. Implement product structure with 3 price books (MSRP, 25% off, 50% off). - Calculated properties (commission, LTV) will be limited to logic defined during requirements. - Association labels (partners, customers) will be aligned to Incrediwear’s B2B structure. - Parent-child company relationships will reflect multi-location clients and international distributors. - Product structure will include up to 3 price books (MSRP, 25%, 50%). - Data sources for backfill (NetSuite, Shopify, Amazon) will be accessible for mapping and validation. - Client will provide subject matter experts for product/pricing validation. - Data migration will be limited to records defined in scope; historical activity is excluded. | D10: 8 | E10: 7
A11: Customer Story | B11: Record Customization | C11: As a sales team, we need record layouts customized by business type so that each team has the relevant properties and views for their process. Aptitude 8 should customize 6 layouts: Contacts, Companies (4 business types), Deals. - 6 layouts will be customized (Contacts, Deals, and 4 Company record types: Retail, Medical, Teams, International). - Each layout will include only fields relevant to that business type. - Dependent properties will be configured based on data gathered in workshops. - Layouts will remain within HubSpot’s out-of-the-box customization limits (no coded UI). - Users will be assigned correct default views by role/team. - Client will confirm naming conventions for business types to avoid ambiguity. - Record customizations will not include workflow automation (handled separately). - Validation of layouts will occur with sales leadership before rollout. | D11: 7 | E11: 5.5
A12: Customer Story | B12: Backfill New Parent-Child Relationship Structure | C12: As a sales team, we need to migrate existing records into the new HubSpot data structure so that our operations can continue without disruption. Aptitude 8 should export the relevant records from HubSpot so they can transform the data in spreadsheet, specifically, apply the correct parent-child relationships to companies. Once transformation is complete, import the relationships into HubSpot. - Transformation of data will be performed in spreadsheet format, supplied by Aptitude 8 for client review. - Correct contact and deal associations must already exist or be clearly identifiable in exported data. - No historical activities, notes, or tasks will be remapped during backfill. - Total record counts are ~541 deals, ~4,800 companies, and ~407,000 contacts. - Client will provide validation of test imports before full backfill execution. - Backfill will not address duplicate records beyond parent-child relationships. - Client acknowledges that backfill may expose additional data quality issues requiring future cleanup. | D12: 30 | E12: 22.5
A13: Customer Story | B13: Optimize Sales Pipeline | C13: As a sales team, we need to rebuild our B2B pipeline with clear forecasting and criteria so that deals are consistently managed, while keeping eCom pipeline updates minimal. Aptitude 8 should update pipeline stages, required fields, pipeline rules, and other pipeline specific settings like deal tags. - Only the B2B pipeline will be updated; eCommerce pipelines will remain largely unchanged (minus minor updates related to the Netsuite integration). - Pipeline stage definitions will be aligned to agreed sales process maps from workshops. - Required fields for stage progression will be finalized during design validation. - Forecasting logic will be basic. - Client will confirm territory definitions for roll-up reporting. - No additional pipelines will be created unless explicitly added via change order. - Pipeline rules will be configured with HubSpot’s out-of-the-box functionality. - Validation will occur with sales managers before rollout. | D13: 8 | E13: 6
A14: Customer Story | B14: Customize Sales Workspace | C14: As a sales rep, I need tailored HubSpot workspace views for tasks, deals, and leads so that I can manage my pipeline efficiently. 1. Configure custom workspace views for tasks, deal management, and lead management. 2. Validate with sales leadership. - Custom workspaces will be limited to 3 areas: tasks, deals, and leads. - Views will be based on fields and filters defined during workshops. - Sales leadership will validate workspace configurations before rollout. - No custom-coded UI or third-party add-ons are included. - Client will provide clarity on priority fields for each workspace. - Workspaces will be configured for role-based adoption (rep vs manager). - Validation will occur with a sample group of users. - Workspaces will not include marketing or service hub features outside sales scope. | D14: 3 | E14: 2
A15: Customer Story | B15: Implement Custom Lead/Engagement Scoring | C15: As a sales team, we need basic lead and engagement scoring so that we can prioritize opportunities and reps are motivated to focus on high-value deals. 1. Configure deal tags (5). 2. Create engagement scoring model (basic to moderate complexity). 3. Launch v1 scoring for initial use. - Engagement scoring will be limited to a basic-to-moderate complexity model. - Initial scoring will include up to 5 deal tags. - Model is intended as v1; further refinement may be part of future phases. - Data available for scoring (activities, lifecycle stage, product interest) must already exist in HubSpot. - Client will provide input on priority activities to drive scoring (e.g., calls, emails, meetings). - Validation will occur with sales leadership before rollout. - Engagement scores will be visible in reports and record views but not tied to automation beyond scope. | D15: 7 | E15: 5.5
A16: Customer Story | B16: Implement Quote Template | C16: As a sales team, we need a basic quote template so that we can generate and send quotes directly from HubSpot. 1. Configure OOTB legacy quote template. 2. Test for formatting and accuracy. - Quote template will use HubSpot’s out-of-the-box legacy quote functionality. - No custom branding beyond standard template fields is included. (This can be done by the Incrediwear team) - No approval workflows or e-signature integrations are included. - Formatting and testing will be limited to one template. - Client will provide company logo and required fields for quote. - Taxes, shipping, and discounts must be handled by HubSpot’s native capabilities. - No external commerce tools (e.g., CommerceHub) are required. - Client will validate template before rollout. | D16: 5 | E16: 4
A17: Customer Story | B17: Sales Automations | C17: As a sales team, we need automation for territory assignment, communications, and CRM updates so that manual processes are reduced and efficiency increases. 1. Automate territory assignments. 2. Build workflows for automated comms. 3. Create workflows to automate CRM updates (e.g., property updates, deal stage progression). - Automation will be limited to out-of-the-box HubSpot workflows. - Territory assignment rules will be defined and approved by client. - Automated communications will be limited to email sequences within HubSpot. - Automations will focus on reducing manual/administrative tasks. - Client will provide test scenarios for validation. - UAT will be required before rollout. - Any advanced automation (e.g., AI routing, custom code) is outside scope. | D17: 7 | E17: 6
A18: Customer Story | B18: Sales Reports & Dashboards | C18: As sales leadership, we need reports and dashboards to track performance, pipeline, and product sales so that we can manage effectively. 1. Configure OOTB reports with slight customizations. 2. Build custom roll-up report: distributor → territory rep → manager. 3. Create product/line item and goal reports. - Most reports will be built using HubSpot’s out-of-the-box reporting tools. - Custom roll-up report (distributor → territory rep → manager) will be the only true custom build. - Product/line item reporting will rely on clean product structure implemented in data model rebuild. - Goal reporting will be configured for B2B pipeline only. - Dashboards will be role-based (rep, manager, leadership). - Client will provide key KPIs for dashboard design. - Reports will be limited to HubSpot data; no external BI tools included. - Reports will be validated in UAT before go-live. | D18: 10 | E18: 8.5
A19: Workstream | B19: Solution Design & Validation
A20: Customer Story | B20: Solution Validation | C20: As a sales team, we need to review and validate the proposed solution design so that we can confirm it meets our requirements before build. 1. Facilitate up to 2 validation sessions. 2. Present ERD, Process Map, UAT scenarios, Training Plan, Go-Live Plan, and Gantt Chart. . Incorporate feedback and adjust hours if necessary. - Up to 2 solution validation sessions will be scheduled within 10 business days of workshop completion. - Deliverables will include ERD, process maps, UAT scenarios, training plan, go-live plan, and high-level Gantt. - Client will provide timely feedback (within 3–5 business days) on all deliverables to stay on schedule. - Any requested changes outside defined requirements may increase hours or require a formal change order. - Validation will confirm alignment with sales adoption goals and B2B scalability targets. - Technical diagrams (ERD, TRD) will reflect current known integrations (HubSpot & Netsuite). - Client acknowledges that feedback should come consolidated from key stakeholders to avoid scope creep. - Approval of the validated solution design will serve as the basis for build and implementation. | D20: 14 | E20: 11
A21: Customer Story | B21: Netsuite Technical Requirements Document | C21: As a sales team, we need a documented Technical Requirements Document for the NetSuite integration so that development can proceed against a clear blueprint. 1. Conduct integration discovery workshops. 2. Map requirements for objects, triggers, sync frequency. 3. Produce TRD including data flows, dependencies, and integration approach. - TRD will include ERD, data mapping, triggers, dependencies, and sync frequency. - Discovery workshops will cover object mapping, field mapping, and sync logic for Contacts, Companies, Deals, and Products. - Client stakeholders (finance, operations, sales) will attend sessions to confirm requirements. - Client will provide sample orders (Shopify, Amazon, B2B) to confirm required fields. - Payment status requirements (Paid/Partial/Unpaid + date) will be documented in TRD. - Any changes to integration scope after TRD approval will require a change order. - Client will validate TRD deliverables within 5 business days to maintain timeline. - TRD will serve as the blueprint for integration build and cannot be bypassed. | D21: 25 | E21: 20
A22: Workstream | B22: Training & Documentation
A23: Customer Story | B23: Sales Team Training | C23: As a sales and leadership team, we need targeted HubSpot training so that we can adopt the system effectively and maximize reporting value. 1. Deliver 2 training sessions for sales users. 2. Deliver 1 training session for leadership/admin on reporting & analytics. 3. Provide recordings and basic materials. - Up to 3 training sessions included (2 for sales users, 1 for leadership/admin). - Each session will be up to 60 minutes and delivered virtually. - Sessions will be recorded and shared with client for future reference. - Training content will cover features implemented in this project only. - Leadership/admin training will focus on reporting, dashboards, and management workflows. - Sales training will focus on pipeline management, tasks, and daily usage. - Client will ensure attendance of target users during training sessions. - Training will not cover advanced HubSpot features outside defined scope (e.g., Marketing Hub, Service Hub). | D23: 10 | E23: 8
A24: Customer Story | B24: Integration Documentation & Handoff | C24: As a technical team, we need documentation of the integration so that we can maintain and support it after go-live. 1. Produce integration documentation (data flows, dependencies, error handling). 2. Provide handoff session with client technical team. - Documentation will cover data flows, dependencies, error handling, and sync logic for in-scope integration. - One handoff session (up to 60 minutes) with client’s technical team is included. - Documentation will reflect final build only; changes post-handoff are not included. - Client technical team must have baseline NetSuite/HubSpot knowledge to understand handoff. - Error resolution instructions will be included but ongoing support is out of scope. - Documentation will not include third-party systems not involved in the integration. - Client is responsible for maintaining documentation after project handoff. | D24: 12 | E24: 10
A25: Customer Story | B25: HS Implementation Documentation | C25: As a client team, we need HubSpot implementation documentation so that we have reference materials for ongoing operations and new hire onboarding. 1. Create documentation for implemented HubSpot features. 2. Include process workflows, system instructions, and troubleshooting. - Documentation will cover HubSpot features implemented in this project (pipelines, layouts, automations, reports). - Documentation will be finalized after implementation and validated with client. - Future updates to documentation after project completion are not included in scope, but can be made available in Post Launch Support. | D25: 12 | E25: 9
A26: Workstream | B26: Project Management | E26: 54
A27: Customer Story | B27: Project Kickoff, Onboarding, and Closeout
A28: Customer Story | B28: Recurring Project Check-ins
A29: Customer Story | B29: Project Administration

Sheet Config
A1: Configuration | B1: Value | C1: Description | D1: HubSpot Property
A2: Gdrvie + Deal Inputs
A3: Company Name | B3: Incrediwear | C3: Incrediwear
A4: Google Folder | B4: https://drive.google.com/drive/folders/1XzMUJqXYEOfxmFGCABM9XytqEefe7wVl | C4: Needs to be manually input for the time being, will be set by the Pipedream automation
A5: Deal Record ID | B5: 42441743998 | C5: HubSpot deal record ID, needs to be manually input for the time being, will be set by the Pipedream automation
A6: Last Sync to HubSpot | B6: 45915.518 | C6: The last time the story doc was sync'd to the HubSpot deal record
A8: Client Page
A9: Client Page URL | B9: https://script.google.com/macros/s/AKfycbz2eeS8jxpfqsYtUK0ifft79YBvSP9jk6hsLKhKjMJxYfwM90lLtgn38X4cQy1W6bsDKA/exec?sheetId=1ihKNXGMy80pvkWBAy3Si3EJ-txE1khGe8f6NaIOT3To | C9: The URL of the page that will be shared in Trumpet | D9: customer_stories_client_url
A10: Last Client Page URL Generated | B10: 45915.46 | C10: The last time you created/updated a URL so we can understand deployment app versions
A11: Client Page Status | B11: Final Presentation | C11: Determines page status for the shared link
A12: Project ID | B12: ------ | C12: TBD on usage to facilitate project creation
A13: Solutions Architect | B13: Matt Cannizo | C13: SA assigned to this project
A14: Request Scope Review | C14: Future-state functionality incoming
A15: Scope Reviewed | B15: Yes | C15: Future-state functionality incoming
A17: NOW Project
A18: Hourly Project Rate | B18: 245 | C18: Standard hourly rate for most services | D18: project_hourly_rate
A19: Project Management Factor | B19: 0.25 | C19: Percentage markup for project management
A20: Project Management Content | B20: To support management and communication, a project manager and delivery lead will own all A8 tasks and clearly communicate needs. - Visibility to budget spend will be provided during the duration of the project - A8 will provide check-in agenda items and follow-ups - Incrediwear to communicate to A8's shared inbox for easier collaboration and timely responses - Incrediwear driven delay will result in additional PM time billed to manage timeline | C20: Description text for the PM section. editable by you.
A21: SA Expected Start Date | B21: 45909 | C21: Project start date
A22: Total Project Months | B22: 4 | C22: Expected project duration | D22: project_duration
A24: NEXT Support Retainer
A25: Post-Launch Hourly Rate | B25: 220 | C25: Post-launch rate, a zero here will hide the workstream/section | D25: retainer_hourly_rate
A26: Post-Launch Hours Per Month | B26: 0 | C26: Post-launch hours per month, a zero here will hide the workstream/section | D26: retainer_hours_per_month_sold
A27: Post-Launch # of Months | B27: 0 | C27: Post-launch months, a zero here will hide the workstream/section | D27: retainer_months_sold
A28: Post-Launch Support Content | B28: A 3-month post-launch support retainer will ensure stability and adoption of the Phase 1 sales implementation. This retainer provides dedicated resources to resolve issues, fine-tune workflows, and support user adoption. Following this period, we will be positioned to begin Phase 2, which will focus on marketing implementation, optimizing D2C channels, and continuing to expand on the foundation built in Phase 1. | C28: Description text for the post-launch section
A31: Additional Notes + Considerations
A32: Additional Notes | B32: - The assumptions content in this scope is based on information and discovery during the sales evaluation and is subject to change during the project if additional challenges or barriers are discovered. - A8 is a Time & Materials agency, we will provide transparent budget tracking throughout the project and change orders will require approvals. - We interchange between A8 and Aptitude 8 in this document. | C32: Description text for below the investment summaries, but above the later phase workstreams

Sheet Calculations
D1: HubSpot Property
A2: Calculated Project Details
A3: Total Service Hours Hours | B3: =SUMIF(Input!J:J,"Now",Input!I:I) -> 217 | C3: Total amount of Input rows
A4: Total Project Management Hours | B4: =round(B3*Config!B19,0) -> 54 | C4: Based on PM % in Config Sheet
A5: Total Project Hours Sold | B5: =sum(B3:B4) -> 271 | C5: Service + PM | D5: project_hours_sold
A6: Total Retainer Hours Sold | B6: =Config!B26 * Config!B27 -> 0
A7: Total Engagement Hours Sold | B7: =sum(B5:B6) -> 271 | C7: This should match exactly to the investment block on the HTML Page | D7: sold_hours
A8: Deal Amount | B8: =(B5*Config!B18)+(B6*Config!B25) -> 66395 | C8: This should match exactly to the investment block on the HTML Page | D8: amount
A9: Expected End Date | B9: =EDATE(Config!B21, Config!B22) -> 46031
A10: Expected Project Hours/Month | B10: =roundup(B3/Config!B22,0) -> 55
A11: Linear Expected Project Hours/Week | B11: =roundup(B10/4.3,0) -> 13
A12: Peak Project Expected Hours/Week | B12: =B11*1.2 -> 15.6
A13: Low Project Expected Hours/Week | B13: =B11*0.5 -> 6.5
A14: Dev Work Percentage | B14: =C21 -> 0.27966102 | D14: dev_work_pct
A15: SE Work Percentage | B15: =C23 -> 0 | D15: se_work_pct
A18: Calculated Function Summary
B19: Sum of Hours | C19: Percent of
A20: Consulting | B20: =SUMIFS(Input!I:I,Input!L:L,"Consulting",Input!J:J,"Now") -> 116 | C20: =B20/B26 -> 0.49152542
A21: Development | B21: =SUMIFS(Input!I:I,Input!L:L,"Development",Input!J:J,"Now") -> 66 | C21: =B21/B26 -> 0.27966102
A22: Project Management | B22: =B4 -> 54 | C22: =B22/B26 -> 0.22881356
A23: Solutions Engineering | B23: =SUMIFS(Input!I:I,Input!L:L,"Solutions Engineering",Input!J:J,"Now") -> 0 | C23: =B23/B26 -> 0
A24: Strategy | B24: =SUMIFS(Input!I:I,Input!L:L,"Strategy",Input!J:J,"Now") -> 0 | C24: =B24/B26 -> 0
A26: Sum of Function-Based Hours | B26: =sum(B20:B24) -> 236 | C26: =sum(C20:C24) -> 1
A29: Calculated Ranges | B29: Low Hours | C29: High Hours
A30: Project Service Estimates: | B30: =SUMIF(Input!J:J,"Now",Input!G:G) -> 160 | C30: =SUMIF(Input!J:J,"Now",Input!H:H) -> 274
A31: Project Management: | B31: =round(B30*Config!B19,0) -> 40 | C31: =round(C30*Config!B19,0) -> 69
A32: Post-Project Support: | B32: =B6 -> 0 | C32: =B6 -> 0
A33: Hour Estimates: | B33: =SUM(B30:B32) -> 200 | C33: =SUM(C30:C32) -> 343
A34: Investment Ranges: | B34: =(sum(B30:B31)*Config!B18)+(B32*Config!B25) -> 49000 | C34: =(sum(C30:C31)*Config!B18)+(C32*Config!B25) -> 84035
A36: SOW Summarized Line Items
A37: =IFERROR(__xludf.DUMMYFUNCTION("VSTACK( QUERY(Input!B:J,""SELECT B, SUM(I), SUM(I)*""&Config!B18&"" WHERE B IS NOT NULL AND J = 'Now' GROUP BY B LABEL B 'Workstream', SUM(I) 'Total Hours', SUM(I)*""&Config!B18&"" 'Total Investment'"",1), {""Project Management"", ROUND(SUMPRODUCT(QUE"&"RY(Input!B:J,""SELECT SUM(I) WHERE B IS NOT NULL AND J = 'Now' GROUP BY B LABEL SUM(I) ''"",0))*Config!B19,0), ROUND(SUMPRODUCT(QUERY(Input!B:J,""SELECT SUM(I) WHERE B IS NOT NULL AND J = 'Now' GROUP BY B LABEL SUM(I) ''"",0))*Config!B19,0)*Config!B18}, "&" {""Post-Launch Support"", Config!B26*Config!B27, Config!B26*Config!B27*Config!B25} )"),"Workstream") -> Workstream | B37: =IFERROR(__xludf.DUMMYFUNCTION("""COMPUTED_VALUE"""),"Total Hours") -> Total Hours | C37: =IFERROR(__xludf.DUMMYFUNCTION("""COMPUTED_VALUE"""),"Total Investment") -> Total Investment
A38: =IFERROR(__xludf.DUMMYFUNCTION("""COMPUTED_VALUE"""),"Launch") -> Launch | B38: =IFERROR(__xludf.DUMMYFUNCTION("""COMPUTED_VALUE"""),15.0) -> 15 | C38: =IFERROR(__xludf.DUMMYFUNCTION("""COMPUTED_VALUE"""),3675.0) -> 3675
A39: =IFERROR(__xludf.DUMMYFUNCTION("""COMPUTED_VALUE"""),"Netsuite Integration") -> Netsuite Integration | B39: =IFERROR(__xludf.DUMMYFUNCTION("""COMPUTED_VALUE"""),66.0) -> 66 | C39: =IFERROR(__xludf.DUMMYFUNCTION("""COMPUTED_VALUE"""),16170.0) -> 16170
A40: =IFERROR(__xludf.DUMMYFUNCTION("""COMPUTED_VALUE"""),"Requirements Gathering Workshops ") -> Requirements Gathering Workshops | B40: =IFERROR(__xludf.DUMMYFUNCTION("""COMPUTED_VALUE"""),11.0) -> 11 | C40: =IFERROR(__xludf.DUMMYFUNCTION("""COMPUTED_VALUE"""),2695.0) -> 2695
A41: =IFERROR(__xludf.DUMMYFUNCTION("""COMPUTED_VALUE"""),"Sales Implementation") -> Sales Implementation | B41: =IFERROR(__xludf.DUMMYFUNCTION("""COMPUTED_VALUE"""),67.0) -> 67 | C41: =IFERROR(__xludf.DUMMYFUNCTION("""COMPUTED_VALUE"""),16415.0) -> 16415
A42: =IFERROR(__xludf.DUMMYFUNCTION("""COMPUTED_VALUE"""),"Solution Design & Validation") -> Solution Design & Validation | B42: =IFERROR(__xludf.DUMMYFUNCTION("""COMPUTED_VALUE"""),31.0) -> 31 | C42: =IFERROR(__xludf.DUMMYFUNCTION("""COMPUTED_VALUE"""),7595.0) -> 7595
A43: =IFERROR(__xludf.DUMMYFUNCTION("""COMPUTED_VALUE"""),"Training & Documentation") -> Training & Documentation | B43: =IFERROR(__xludf.DUMMYFUNCTION("""COMPUTED_VALUE"""),27.0) -> 27 | C43: =IFERROR(__xludf.DUMMYFUNCTION("""COMPUTED_VALUE"""),6615.0) -> 6615
A44: =IFERROR(__xludf.DUMMYFUNCTION("""COMPUTED_VALUE"""),"Project Management") -> Project Management | B44: =IFERROR(__xludf.DUMMYFUNCTION("""COMPUTED_VALUE"""),54.0) -> 54 | C44: =IFERROR(__xludf.DUMMYFUNCTION("""COMPUTED_VALUE"""),13230.0) -> 13230
A45: =IFERROR(__xludf.DUMMYFUNCTION("""COMPUTED_VALUE"""),"Post-Launch Support") -> Post-Launch Support | B45: =IFERROR(__xludf.DUMMYFUNCTION("""COMPUTED_VALUE"""),0.0) -> 0 | C45: =IFERROR(__xludf.DUMMYFUNCTION("""COMPUTED_VALUE"""),0.0) -> 0
