Workbook

Sheet Overview
C1: NTT Data
B2: Service | C2: Customer Story | D2: Suggested Path | E2: Assumptions | F2: Estimated Low Hours | G2: Estimated High Hours | H2: Potential Variance | I2: Function | J2: POC
A4: • | B4: Data Improvements | F4: =IFERROR(__xludf.DUMMYFUNCTION("ROUNDUP( ( SUM( INDIRECT( ""F""&(ROW()+1)&"":F""& IFERROR( INDEX( FILTER( ROW(A:A), REGEXMATCH(A:A, ""^[•◆■※⊳]""), ROW(A:A) > ROW() ), 1 "&" )-1, 999 ) ) )+ SUM( INDIRECT( ""G""&(ROW()+1)&"":G""& IFERROR( INDEX( FILTER( ROW(A:A), REGEXMATCH(A:A, ""^[•◆■※⊳]""), ROW(A:A) "&"> ROW() ), 1 )-1, 999 ) ) ) )/2 )"),25.0) -> 25 | H4: Standard
B5: Deduplicate Contacts | C5: NTT Data needs contact records deduplicated across the CRM so campaigns aren’t misattributed and customer experience is not degraded by redundant outreach. | D5: Evaluate the volume and causes of duplicate records, especially across integrations. Deploy deduplication rules and tools (e.g. via HubSpot, Insycle, or Operations Hub) with support for automation where possible. | E5: - Aptitude 8 assumes there are at least 10,000 contact duplicates to be addressed and will resolve all 10,000 - Some duplicates stem from misaligned integrations or import logic, Aptitude 8 will diagnose and make clear recommendations on how to prevent that from happening after the transformation - Cross-object deduplication (contacts + companies) may be required. - Aptitude 8 assumes code will be written to programmatically solve for the current dupes and potentially manage dupes created from the integration until it's fixed - The cleanup will require NTT Data to review large datasets in order to maintain a high level of accuracy | F5: 15 | G5: 20 | I5: Consulting
B6: Property Cleanup | C6: NTT Data needs a simplified and organized set of properties so internal teams can use and report on CRM data without confusion or redundancy. | D6: Audit existing properties, archive unused ones, consolidate duplicates, and re-architect property groups with updated descriptions and clear usage guidelines. | E6: - Up to 300 properties will be reviewed. - Redundant fields and legacy campaign properties are common. - Requires input from NTT Data before proceeding | F6: 5 | G6: 10 | I6: Consulting
A8: • | B8: Marketing Optimization | F8: =IFERROR(__xludf.DUMMYFUNCTION("ROUNDUP( ( SUM( INDIRECT( ""F""&(ROW()+1)&"":F""& IFERROR( INDEX( FILTER( ROW(A:A), REGEXMATCH(A:A, ""^[•◆■※⊳]""), ROW(A:A) > ROW() ), 1 "&" )-1, 999 ) ) )+ SUM( INDIRECT( ""G""&(ROW()+1)&"":G""& IFERROR( INDEX( FILTER( ROW(A:A), REGEXMATCH(A:A, ""^[•◆■※⊳]""), ROW(A:A) "&"> ROW() ), 1 )-1, 999 ) ) ) )/2 )"),79.0) -> 79 | H8: Standard
B9: Marketing Contact Status Fix | C9: NTT Data needs the marketing contact status field working properly so that we can control billing, avoid unnecessary charges, and safely send campaigns. | D9: Audit current marketing contact logic, evaluate how contacts are set/unset via workflows or integrations, and implement a fix to preserve compliance with HubSpot billing rules. | E9: - HubSpot Support might be required to help diagnose and solve the issue - Aptitude 8 will provide a summary of the issue and recommend a path forward - Aptitude 8 will implement the fix - Up to 10 hours | F9: 8 | G9: 12 | I9: Consulting
B10: Marketing Asset Naming Convention Standardization | C10: NTT Data needs consistent naming across HubSpot assets so I can quickly locate, reuse, and report on marketing materials. | D10: Define naming conventions for emails, forms, lists, landing pages, workflows, and campaigns. Train users and apply retroactive naming updates to existing assets. | E10: - No naming standards currently in place. - Standardization improves performance tracking and team onboarding. - Some manual effort will be required for legacy assets. | F10: 3 | G10: 5 | I10: Consulting
B11: Implement Marketing Attribution Program | C11: NTT Data needs a functioning attribution model so we can understand which campaigns and touchpoints contribute to pipeline creation. | D11: Gather requirements from Marketing and Sales, define a multi-touch attribution approach, implement HubSpot’s attribution features, and validate with test cohorts. | E11: - Aptitude 8 will gather requirements, recommend appropriate path forward, and implement an MVP attribution program. - May require standardizing UTM usage. - Attribution reporting configuration will follow model design. - Accurate cross-object visibility is required (e.g. contacts → deals). - Up to 25 hours | F11: 20 | G11: 30 | I11: Consulting
B12: Workflow Cleanup | C12: NTT Data needs broken and redundant workflows fixed or archived so automations don’t interfere with performance or create confusion. | D12: Audit all workflows for errors, redundancy, or inactivity. Clean up or rewrite up to 40 workflows with high business impact. | E12: - 40 workflows targeted for deep review and cleanup. - Workflow issues may impact email sends, lead scoring, or MQL routing. - Aligns with broader automation health initiatives in audit. | F12: 20 | G12: 40 | I12: Consulting
B13: Create ROI Reports & Dashboards | C13: NTT Data needs ROI reporting to evaluate how events and content drive pipeline so we can optimize marketing investment. | D13: Deliver 5 reports and 2 dashboards that attribute influenced revenue to key assets across webinars, field events, and content. | E13: - Aptitude 8 will create up to 5 custom reports, up to 5 customized out-of-the-box reports and 2 dashboards - Up to 10 hours | F13: 8 | G13: 12 | I13: Consulting
A15: • | B15: Sales Process Optimization | F15: =IFERROR(__xludf.DUMMYFUNCTION("ROUNDUP( ( SUM( INDIRECT( ""F""&(ROW()+1)&"":F""& IFERROR( INDEX( FILTER( ROW(A:A), REGEXMATCH(A:A, ""^[•◆■※⊳]""), ROW(A:A) > ROW() ), 1 "&" )-1, 999 ) ) )+ SUM( INDIRECT( ""G""&(ROW()+1)&"":G""& IFERROR( INDEX( FILTER( ROW(A:A), REGEXMATCH(A:A, ""^[•◆■※⊳]""), ROW(A:A) "&"> ROW() ), 1 )-1, 999 ) ) ) )/2 )"),16.0) -> 16 | H15: Standard
B16: Reflect Sales Process in HubSpot | C16: NTT Data needs the post-SQL sales process represented accurately in HubSpot so we can track pipeline stages and align with downstream systems. | D16: Update deal stages and pipelines to reflect current GTM motions. Create custom properties to track progress and ensure visibility into C4C activity. | E16: - Integration with C4C may require iframe of an external dashboard in HubSpot. - Pipeline and property changes should align with forecasting structure. - Timing may depend on completion of integration fixes. | F16: 4 | G16: 8 | I16: Consulting
B17: Create New SDR Reports & Dashboards | C17: NTT Data needs reporting aligned to the updated data model so I can evaluate SDR performance and track key funnel metrics. | D17: Build 5 custom reports and 2 dashboards for SDR activity, conversion, and follow-up speed based on updated object relationships. | E17: - Aptitude 8 will create up to 5 custom reports, up to 5 customized out-of-the-box reports and 2 dashboards - Up to 10 hours | F17: 8 | G17: 12 | I17: Consulting
A19: • | B19: HubSpot AI Agents & Enrichments | F19: =IFERROR(__xludf.DUMMYFUNCTION("ROUNDUP( ( SUM( INDIRECT( ""F""&(ROW()+1)&"":F""& IFERROR( INDEX( FILTER( ROW(A:A), REGEXMATCH(A:A, ""^[•◆■※⊳]""), ROW(A:A) > ROW() ), 1 "&" )-1, 999 ) ) )+ SUM( INDIRECT( ""G""&(ROW()+1)&"":G""& IFERROR( INDEX( FILTER( ROW(A:A), REGEXMATCH(A:A, ""^[•◆■※⊳]""), ROW(A:A) "&"> ROW() ), 1 )-1, 999 ) ) ) )/2 )"),32.0) -> 32 | H19: Standard
B20: Create Prospecting Agent | C20: As a marketing leader, I need to automate the qualification of leads so that my team can focus their time on the highest-potential opportunities and reduce time spent researching unqualified prospects. | D20: - Conduct a discovery session to understand current qualification criteria (e.g., industry, company size, buyer role) and sales team workflows - Define and configure Selling Profiles in HubSpot with your key qualification signals (website, ICP traits, pain points) - Activate the Prospecting Agent in semi-autonomous mode to review AI-generated qualification summaries before contact is enriched or enrolled - Integrate the Prospecting Agent into the SDR or BDR workflow via list enrollment or CRM automation | E20: - Sales Hub Pro or Enterprise license with Prospecting Agent (Beta) enabled - Inbound or outbound contacts are available in CRM with minimal enrichment - Qualification criteria are clearly defined and documented by sales leadership - Website URLs are available or discoverable by HubSpot for research - Up to 3 selling profiles configured during implementation phase - Sales team has capacity to participate in pilot and provide feedback | F20: 12 | G20: 18 | I20: Consulting
B21: Implement Content Agent | C21: As a marketing leader, I need to scale content production without sacrificing brand quality, so that my team can meet growing demands across web, email, and social channels while staying aligned with our voice and customer segments. | D21: - Conduct a discovery session to understand the current content operations, workflows, and asset types in use (blog, landing pages, case studies, etc.) - Configure the Content Hub’s brand voice, tone, and audience parameters - Upload and tag a set of reference materials (PDFs, blogs, case studies, etc.) for training | E21: - Client has Content Hub Pro or Enterprise license with access to AI Agent functionality - Reference content and brand guidelines will be made available early in the engagement - CRM data is reasonably structured (e.g., contacts with lifecycle stages, personas, etc.) | F21: 8 | G21: 10 | I21: Consulting
B22: Implement Breeze Enrichment | C22: As a marketing leader, I want to enrich contact and company records, identify high-intent buyers, and shorten forms so that my teams can personalize outreach, improve conversion rates, and focus on leads that matter most. | D22: - Conduct a discovery session to understand current CRM data gaps, form strategy, and how sales teams identify buying signals - Review existing form strategy and identify high-traffic forms to apply form shortening and pre-fill logic - Configure Breeze Intelligence settings for: • Automatic enrichment for new records • On-demand enrichment for existing lists and views • Buyer intent signals with thresholds by visit count, page views, or industries - Activate the Buyer Intent CRM card for relevant user roles (BDRs, AEs, AMs) and define how to take action on signals (e.g. enroll in sequences, alert reps) - Pilot enrichment workflows and validate property population accuracy | E22: - HubSpot CRM includes contact/company records with emails and/or domains available for enrichment - Buyer intent is based on HubSpot-tracked website traffic (tracking code must be installed and active) - Target markets can be clearly defined (by industry, region, company size, etc.) - Form shortening is only applied to forms using HubSpot native forms - Users accessing intent data via CRM card have appropriate permissions - Up to 3 enrichment configurations and 2 form shortening use cases are included in this scope | F22: 5 | G22: 10 | I22: Consulting
A24: • | B24: Systems Integration | F24: =IFERROR(__xludf.DUMMYFUNCTION("ROUNDUP( ( SUM( INDIRECT( ""F""&(ROW()+1)&"":F""& IFERROR( INDEX( FILTER( ROW(A:A), REGEXMATCH(A:A, ""^[•◆■※⊳]""), ROW(A:A) > ROW() ), 1 "&" )-1, 999 ) ) )+ SUM( INDIRECT( ""G""&(ROW()+1)&"":G""& IFERROR( INDEX( FILTER( ROW(A:A), REGEXMATCH(A:A, ""^[•◆■※⊳]""), ROW(A:A) "&"> ROW() ), 1 )-1, 999 ) ) ) )/2 )"),112.0) -> 112 | H24: High
B25: Sendoso Gifting Analytics | C25: NTT Data needs to report on the impact of gifting initiatives via the Sendoso platform | D25: Design a solution for acquiring the Sendoso information and bringing it into HubSpot to enable campaign tracking for Gifting Initiatives | E25: - This is a one direction integration: Sendoso to HubSpot - Sendoso Sends will map to Custom Events in HubSpot to be used in lists, automation, and reporting in HubSpot - Aptitude 8 assumes this endpoint gives NTT Data the send information they need in HubSpot: https://developer.sendoso.com/rest-api/reference/sends/get-sends - Pipedream or an equivalent middleware must be purchased in order to manage the Sendoso --> HubSpot sync | F25: 35 | G25: 50 | I25: Solutions Engineering
B26: ZoomInfo Enrichment | C26: NTT Data needs ZoomInfo's connection reconfigured to properly enrich contacts and companies within HubSpot | D26: Review current integration, design a new set of integration and enrichment rules based on requirements, and re-configure the current ZoomInfo connector. | E26: - Aptitude 8 will create an MVP set of enrichment rules for ZoomInfo based on the specified needs. - Aptitude 8 will reconfigure the ZoomInfo connector only with no custom connectivity build | F26: 3 | G26: 5 | I26: Consulting
B27: C4C Integration Solution Engineering | C27: NTT Data needs a redesigned C4C integration so that HubSpot has visibility into post-SQL performance. | D27: Collaborate with a Solution Engineer to design an integration that syncs C4C outcomes, stage movement, and key fields into HubSpot. | E27: - Aptitude 8 will need a technical audit of the integration to determine what changes need to be made based off the marketing team's requirements - Requires participation from HQ IT or system owners. - Design contingent on HQ integration approval. - May require custom middleware or field mapping. - Aligns with HubSpot pipeline structure. | F27: 25 | G27: 35 | I27: Solutions Engineering
B28: C4C Integration Implementation Support | C28: NTT Data needs advisory support during C4C integration buildout so I can ensure the implementation matches design. | D28: Provide implementation oversight, QA, and strategy validation for C4C integration deployment. | E28: - NTT DATA is responsible for build. - Aptitude 8 provides advisory support only | F28: 30 | G28: 40 | I28: Development
A30: • | B30: Training & Documentation: Enable team success | F30: =IFERROR(__xludf.DUMMYFUNCTION("ROUNDUP( ( SUM( INDIRECT( ""F""&(ROW()+1)&"":F""& IFERROR( INDEX( FILTER( ROW(A:A), REGEXMATCH(A:A, ""^[•◆■※⊳]""), ROW(A:A) > ROW() ), 1 "&" )-1, 999 ) ) )+ SUM( INDIRECT( ""G""&(ROW()+1)&"":G""& IFERROR( INDEX( FILTER( ROW(A:A), REGEXMATCH(A:A, ""^[•◆■※⊳]""), ROW(A:A) "&"> ROW() ), 1 )-1, 999 ) ) ) )/2 )"),30.0) -> 30 | H30: Low
B31: Provide End-User Training | C31: NTT Data needs their support team to understand how to effectively use HubSpot Service Hub features to provide excellent customer service. | D31: Aptitude 8 will provide role-specific training sessions covering core functionality, service workflows, and HubSpot best practices. | E31: - Up to 3 virtual training sessions - Role-based curriculum - Session recordings provided - Basic training materials | F31: 8 | G31: 15 | I31: Consulting
B32: Create Training Documentation | C32: NTT Data needs reference materials to support ongoing training and new hire onboarding for their service teams. | D32: Aptitude 8 will create comprehensive documentation including process guides, system instructions, and troubleshooting resources. | E32: - Custom documentation for implemented features - Process workflows with visuals - System administration guidelines - Up to 3 role-specific guides | F32: 8 | G32: 12 | I32: Consulting
B33: Deliver Admin Training | C33: [Company] needs internal administrators to understand how to maintain and evolve their Service Hub implementation. | D33: Aptitude 8 will provide specialized training for HubSpot administrators on configuration, maintenance, and expansion of service capabilities. | E33: - Up to 2 admin training sessions - System management focus - Customization capabilities - Troubleshooting procedures | F33: 6 | G33: 10 | I33: Consulting
A35: ◆ | B35: Project Management + Strategy: Support this phase with transparency and regular progress reports | F35: =IFERROR(__xludf.DUMMYFUNCTION("ROUNDUP( ( SUM( FILTER( INDIRECT(""F4:F"" & ROW()-1), LEFT(INDIRECT(""A4:A"" & ROW()-1),1)=""•"" ) ) ) * Details!C12 )"),59.0) -> 59 | I35: Project Management
B36: Project Kickoff, Onboarding, and Closeout | C36: NTT Data needs a partner to support managing the HubSpot and consulting project, ensuring deadlines are clear and met. | D36: To support management and communication, a project manager and delivery lead will own all A8 tasks and clearly communicate needs to NTT Data. | E36: - Visibility to budget spend will be provided during the duration of the project - A8 will provide check-in agenda items and follow-ups - NTT Data to communicate to A8's shared inbox for easier collaboration and timely responses
B37: Recurring Project Check-ins
B38: Project Administration
A40: ■ | B40: NEXT Post-Launch Support | F40: =Details!C18*Details!C19 -> 180
B41: NEXT Post-Launch Support | C41: Hours dedicated to post go-live support. These hours can be used for anything HubSpot related (reporting, training, iterations, additional asks, etc.) | F41: Hours/Month: | G41: =Details!C18 -> 30
F42: # of Months: | G42: =Details!C19 -> 6
A45: ※ | E45: Total Estimated Engagement Hours: | F45: =SUMIFS(F:F, A:A, "*•*") + SUMIFS(F:F, A:A, "*◆*") + SUMIFS(F:F, A:A, "*■*") -> 533 | H45: Low Hour Estimate: | I45: {=INDIRECT("Details!G26")} -> 457.2
H46: High Hour Estimate: | I46: {=INDIRECT("Details!H26")} -> 604.8
A47: ⚑ | E47: Total Estimated Investment: | F47: =IFERROR(__xludf.DUMMYFUNCTION("ARRAYFORMULA( SUM( IF( REGEXMATCH(INDIRECT(""A4:A"" & MATCH(""※"",A:A,0)-1), ""^[•◆■]""), INDIRECT(""F4:F"" & MATCH(""※"",A:A,0)-1) * IF( REGEXMATCH(INDIRECT(""A4:A"" & MATCH(""※"",A:A,0)-1), ""^[•◆]""), Details!$C"&"$11, IF( REGEXMATCH(INDIRECT(""A4:A"" & MATCH(""※"",A:A,0)-1), ""^■""), Details!$C$17, 0 ) ), 0 ) ) )"),126085.0) -> 126085
A49: © | B49: 2025 Aptitude 8

Sheet Change Order Strike C4C
C1: NTT Data
B2: Service | C2: Customer Story | D2: Suggested Path | E2: Assumptions | F2: Estimated Low Hours | G2: Estimated High Hours | H2: Potential Variance | I2: Function | J2: POC
A4: • | B4: Data Improvements | F4: =IFERROR(__xludf.DUMMYFUNCTION("ROUNDUP( ( SUM( INDIRECT( ""F""&(ROW()+1)&"":F""& IFERROR( INDEX( FILTER( ROW(A:A), REGEXMATCH(A:A, ""^[•◆■※⊳]""), ROW(A:A) > ROW() ), 1 "&" )-1, 999 ) ) )+ SUM( INDIRECT( ""G""&(ROW()+1)&"":G""& IFERROR( INDEX( FILTER( ROW(A:A), REGEXMATCH(A:A, ""^[•◆■※⊳]""), ROW(A:A) "&"> ROW() ), 1 )-1, 999 ) ) ) )/2 )"),25.0) -> 25 | H4: Standard
B5: Deduplicate Contacts | C5: NTT Data needs contact records deduplicated across the CRM so campaigns aren’t misattributed and customer experience is not degraded by redundant outreach. | D5: Evaluate the volume and causes of duplicate records, especially across integrations. Deploy deduplication rules and tools (e.g. via HubSpot, Insycle, or Operations Hub) with support for automation where possible. | E5: - Aptitude 8 assumes there are at least 10,000 contact duplicates to be addressed and will resolve all 10,000 - Some duplicates stem from misaligned integrations or import logic, Aptitude 8 will diagnose and make clear recommendations on how to prevent that from happening after the transformation - Cross-object deduplication (contacts + companies) may be required. - Aptitude 8 assumes code will be written to programmatically solve for the current dupes and potentially manage dupes created from the integration until it's fixed - The cleanup will require NTT Data to review large datasets in order to maintain a high level of accuracy | F5: 15 | G5: 20 | I5: Consulting
B6: Property Cleanup | C6: NTT Data needs a simplified and organized set of properties so internal teams can use and report on CRM data without confusion or redundancy. | D6: Audit existing properties, archive unused ones, consolidate duplicates, and re-architect property groups with updated descriptions and clear usage guidelines. | E6: - Up to 300 properties will be reviewed. - Redundant fields and legacy campaign properties are common. - Requires input from NTT Data before proceeding | F6: 5 | G6: 10 | I6: Consulting
A8: • | B8: Marketing Optimization | F8: =IFERROR(__xludf.DUMMYFUNCTION("ROUNDUP( ( SUM( INDIRECT( ""F""&(ROW()+1)&"":F""& IFERROR( INDEX( FILTER( ROW(A:A), REGEXMATCH(A:A, ""^[•◆■※⊳]""), ROW(A:A) > ROW() ), 1 "&" )-1, 999 ) ) )+ SUM( INDIRECT( ""G""&(ROW()+1)&"":G""& IFERROR( INDEX( FILTER( ROW(A:A), REGEXMATCH(A:A, ""^[•◆■※⊳]""), ROW(A:A) "&"> ROW() ), 1 )-1, 999 ) ) ) )/2 )"),79.0) -> 79 | H8: Standard
B9: Marketing Contact Status Fix | C9: NTT Data needs the marketing contact status field working properly so that we can control billing, avoid unnecessary charges, and safely send campaigns. | D9: Audit current marketing contact logic, evaluate how contacts are set/unset via workflows or integrations, and implement a fix to preserve compliance with HubSpot billing rules. | E9: - HubSpot Support might be required to help diagnose and solve the issue - Aptitude 8 will provide a summary of the issue and recommend a path forward - Aptitude 8 will implement the fix - Up to 10 hours | F9: 8 | G9: 12 | I9: Consulting
B10: Marketing Asset Naming Convention Standardization | C10: NTT Data needs consistent naming across HubSpot assets so I can quickly locate, reuse, and report on marketing materials. | D10: Define naming conventions for emails, forms, lists, landing pages, workflows, and campaigns. Train users and apply retroactive naming updates to existing assets. | E10: - No naming standards currently in place. - Standardization improves performance tracking and team onboarding. - Some manual effort will be required for legacy assets. | F10: 3 | G10: 5 | I10: Consulting
B11: Implement Marketing Attribution Program | C11: NTT Data needs a functioning attribution model so we can understand which campaigns and touchpoints contribute to pipeline creation. | D11: Gather requirements from Marketing and Sales, define a multi-touch attribution approach, implement HubSpot’s attribution features, and validate with test cohorts. | E11: - Aptitude 8 will gather requirements, recommend appropriate path forward, and implement an MVP attribution program. - May require standardizing UTM usage. - Attribution reporting configuration will follow model design. - Accurate cross-object visibility is required (e.g. contacts → deals). - Up to 25 hours | F11: 20 | G11: 30 | I11: Consulting
B12: Workflow Cleanup | C12: NTT Data needs broken and redundant workflows fixed or archived so automations don’t interfere with performance or create confusion. | D12: Audit all workflows for errors, redundancy, or inactivity. Clean up or rewrite up to 40 workflows with high business impact. | E12: - 40 workflows targeted for deep review and cleanup. - Workflow issues may impact email sends, lead scoring, or MQL routing. - Aligns with broader automation health initiatives in audit. | F12: 20 | G12: 40 | I12: Consulting
B13: Create ROI Reports & Dashboards | C13: NTT Data needs ROI reporting to evaluate how events and content drive pipeline so we can optimize marketing investment. | D13: Deliver 5 reports and 2 dashboards that attribute influenced revenue to key assets across webinars, field events, and content. | E13: - Aptitude 8 will create up to 5 custom reports, up to 5 customized out-of-the-box reports and 2 dashboards - Up to 10 hours | F13: 8 | G13: 12 | I13: Consulting
A15: • | B15: Sales Process Optimization | F15: =IFERROR(__xludf.DUMMYFUNCTION("ROUNDUP( ( SUM( INDIRECT( ""F""&(ROW()+1)&"":F""& IFERROR( INDEX( FILTER( ROW(A:A), REGEXMATCH(A:A, ""^[•◆■※⊳]""), ROW(A:A) > ROW() ), 1 "&" )-1, 999 ) ) )+ SUM( INDIRECT( ""G""&(ROW()+1)&"":G""& IFERROR( INDEX( FILTER( ROW(A:A), REGEXMATCH(A:A, ""^[•◆■※⊳]""), ROW(A:A) "&"> ROW() ), 1 )-1, 999 ) ) ) )/2 )"),16.0) -> 16 | H15: Standard
B16: Reflect Sales Process in HubSpot | C16: NTT Data needs the post-SQL sales process represented accurately in HubSpot so we can track pipeline stages and align with downstream systems. | D16: Update deal stages and pipelines to reflect current GTM motions. Create custom properties to track progress and ensure visibility into C4C activity. | E16: - Integration with C4C may require iframe of an external dashboard in HubSpot. - Pipeline and property changes should align with forecasting structure. - Timing may depend on completion of integration fixes. | F16: 4 | G16: 8 | I16: Consulting
B17: Create New SDR Reports & Dashboards | C17: NTT Data needs reporting aligned to the updated data model so I can evaluate SDR performance and track key funnel metrics. | D17: Build 5 custom reports and 2 dashboards for SDR activity, conversion, and follow-up speed based on updated object relationships. | E17: - Aptitude 8 will create up to 5 custom reports, up to 5 customized out-of-the-box reports and 2 dashboards - Up to 10 hours | F17: 8 | G17: 12 | I17: Consulting
A19: • | B19: HubSpot AI Agents & Enrichments | F19: =IFERROR(__xludf.DUMMYFUNCTION("ROUNDUP( ( SUM( INDIRECT( ""F""&(ROW()+1)&"":F""& IFERROR( INDEX( FILTER( ROW(A:A), REGEXMATCH(A:A, ""^[•◆■※⊳]""), ROW(A:A) > ROW() ), 1 "&" )-1, 999 ) ) )+ SUM( INDIRECT( ""G""&(ROW()+1)&"":G""& IFERROR( INDEX( FILTER( ROW(A:A), REGEXMATCH(A:A, ""^[•◆■※⊳]""), ROW(A:A) "&"> ROW() ), 1 )-1, 999 ) ) ) )/2 )"),32.0) -> 32 | H19: Standard
B20: Create Prospecting Agent | C20: As a marketing leader, I need to automate the qualification of leads so that my team can focus their time on the highest-potential opportunities and reduce time spent researching unqualified prospects. | D20: - Conduct a discovery session to understand current qualification criteria (e.g., industry, company size, buyer role) and sales team workflows - Define and configure Selling Profiles in HubSpot with your key qualification signals (website, ICP traits, pain points) - Activate the Prospecting Agent in semi-autonomous mode to review AI-generated qualification summaries before contact is enriched or enrolled - Integrate the Prospecting Agent into the SDR or BDR workflow via list enrollment or CRM automation | E20: - Sales Hub Pro or Enterprise license with Prospecting Agent (Beta) enabled - Inbound or outbound contacts are available in CRM with minimal enrichment - Qualification criteria are clearly defined and documented by sales leadership - Website URLs are available or discoverable by HubSpot for research - Up to 3 selling profiles configured during implementation phase - Sales team has capacity to participate in pilot and provide feedback | F20: 12 | G20: 18 | I20: Consulting
B21: Implement Content Agent | C21: As a marketing leader, I need to scale content production without sacrificing brand quality, so that my team can meet growing demands across web, email, and social channels while staying aligned with our voice and customer segments. | D21: - Conduct a discovery session to understand the current content operations, workflows, and asset types in use (blog, landing pages, case studies, etc.) - Configure the Content Hub’s brand voice, tone, and audience parameters - Upload and tag a set of reference materials (PDFs, blogs, case studies, etc.) for training | E21: - Client has Content Hub Pro or Enterprise license with access to AI Agent functionality - Reference content and brand guidelines will be made available early in the engagement - CRM data is reasonably structured (e.g., contacts with lifecycle stages, personas, etc.) | F21: 8 | G21: 10 | I21: Consulting
B22: Implement Breeze Enrichment | C22: As a marketing leader, I want to enrich contact and company records, identify high-intent buyers, and shorten forms so that my teams can personalize outreach, improve conversion rates, and focus on leads that matter most. | D22: - Conduct a discovery session to understand current CRM data gaps, form strategy, and how sales teams identify buying signals - Review existing form strategy and identify high-traffic forms to apply form shortening and pre-fill logic - Configure Breeze Intelligence settings for: • Automatic enrichment for new records • On-demand enrichment for existing lists and views • Buyer intent signals with thresholds by visit count, page views, or industries - Activate the Buyer Intent CRM card for relevant user roles (BDRs, AEs, AMs) and define how to take action on signals (e.g. enroll in sequences, alert reps) - Pilot enrichment workflows and validate property population accuracy | E22: - HubSpot CRM includes contact/company records with emails and/or domains available for enrichment - Buyer intent is based on HubSpot-tracked website traffic (tracking code must be installed and active) - Target markets can be clearly defined (by industry, region, company size, etc.) - Form shortening is only applied to forms using HubSpot native forms - Users accessing intent data via CRM card have appropriate permissions - Up to 3 enrichment configurations and 2 form shortening use cases are included in this scope | F22: 5 | G22: 10 | I22: Consulting
A24: • | B24: Systems Integration | F24: =IFERROR(__xludf.DUMMYFUNCTION("ROUNDUP( ( SUM( INDIRECT( ""F""&(ROW()+1)&"":F""& IFERROR( INDEX( FILTER( ROW(A:A), REGEXMATCH(A:A, ""^[•◆■※⊳]""), ROW(A:A) > ROW() ), 1 "&" )-1, 999 ) ) )+ SUM( INDIRECT( ""G""&(ROW()+1)&"":G""& IFERROR( INDEX( FILTER( ROW(A:A), REGEXMATCH(A:A, ""^[•◆■※⊳]""), ROW(A:A) "&"> ROW() ), 1 )-1, 999 ) ) ) )/2 )"),112.0) -> 112 | H24: High
B25: Sendoso Gifting Analytics | C25: NTT Data needs to report on the impact of gifting initiatives via the Sendoso platform | D25: Design a solution for acquiring the Sendoso information and bringing it into HubSpot to enable campaign tracking for Gifting Initiatives | E25: - This is a one direction integration: Sendoso to HubSpot - Sendoso Sends will map to Custom Events in HubSpot to be used in lists, automation, and reporting in HubSpot - Aptitude 8 assumes this endpoint gives NTT Data the send information they need in HubSpot: https://developer.sendoso.com/rest-api/reference/sends/get-sends - Pipedream or an equivalent middleware must be purchased in order to manage the Sendoso --> HubSpot sync | F25: 35 | G25: 50 | I25: Solutions Engineering
B26: ZoomInfo Enrichment | C26: NTT Data needs ZoomInfo's connection reconfigured to properly enrich contacts and companies within HubSpot | D26: Review current integration, design a new set of integration and enrichment rules based on requirements, and re-configure the current ZoomInfo connector. | E26: - Aptitude 8 will create an MVP set of enrichment rules for ZoomInfo based on the specified needs. - Aptitude 8 will reconfigure the ZoomInfo connector only with no custom connectivity build | F26: 3 | G26: 5 | I26: Consulting
B27: C4C Integration Solution Engineering | C27: NTT Data needs a redesigned C4C integration so that HubSpot has visibility into post-SQL performance. | D27: Collaborate with a Solution Engineer to design an integration that syncs C4C outcomes, stage movement, and key fields into HubSpot. | E27: - Aptitude 8 will need a technical audit of the integration to determine what changes need to be made based off the marketing team's requirements - Requires participation from HQ IT or system owners. - Design contingent on HQ integration approval. - May require custom middleware or field mapping. - Aligns with HubSpot pipeline structure. | F27: 25 | G27: 35 | I27: Solutions Engineering
B28: C4C Integration Implementation Support | C28: NTT Data needs advisory support during C4C integration buildout so I can ensure the implementation matches design. | D28: Provide implementation oversight, QA, and strategy validation for C4C integration deployment. | E28: - NTT DATA is responsible for build. - Aptitude 8 provides advisory support only | F28: 30 | G28: 40 | I28: Development
A30: • | B30: Training & Documentation: Enable team success | F30: =IFERROR(__xludf.DUMMYFUNCTION("ROUNDUP( ( SUM( INDIRECT( ""F""&(ROW()+1)&"":F""& IFERROR( INDEX( FILTER( ROW(A:A), REGEXMATCH(A:A, ""^[•◆■※⊳]""), ROW(A:A) > ROW() ), 1 "&" )-1, 999 ) ) )+ SUM( INDIRECT( ""G""&(ROW()+1)&"":G""& IFERROR( INDEX( FILTER( ROW(A:A), REGEXMATCH(A:A, ""^[•◆■※⊳]""), ROW(A:A) "&"> ROW() ), 1 )-1, 999 ) ) ) )/2 )"),30.0) -> 30 | H30: Low
B31: Provide End-User Training | C31: NTT Data needs their support team to understand how to effectively use HubSpot Service Hub features to provide excellent customer service. | D31: Aptitude 8 will provide role-specific training sessions covering core functionality, service workflows, and HubSpot best practices. | E31: - Up to 3 virtual training sessions - Role-based curriculum - Session recordings provided - Basic training materials | F31: 8 | G31: 15 | I31: Consulting
B32: Create Training Documentation | C32: NTT Data needs reference materials to support ongoing training and new hire onboarding for their service teams. | D32: Aptitude 8 will create comprehensive documentation including process guides, system instructions, and troubleshooting resources. | E32: - Custom documentation for implemented features - Process workflows with visuals - System administration guidelines - Up to 3 role-specific guides | F32: 8 | G32: 12 | I32: Consulting
B33: Deliver Admin Training | C33: [Company] needs internal administrators to understand how to maintain and evolve their Service Hub implementation. | D33: Aptitude 8 will provide specialized training for HubSpot administrators on configuration, maintenance, and expansion of service capabilities. | E33: - Up to 2 admin training sessions - System management focus - Customization capabilities - Troubleshooting procedures | F33: 6 | G33: 10 | I33: Consulting
A35: ◆ | B35: Project Management + Strategy: Support this phase with transparency and regular progress reports | F35: =IFERROR(__xludf.DUMMYFUNCTION("ROUNDUP( ( SUM( FILTER( INDIRECT(""F4:F"" & ROW()-1), LEFT(INDIRECT(""A4:A"" & ROW()-1),1)=""•"" ) ) ) * Details!C12 )"),59.0) -> 59 | I35: Project Management
B36: Project Kickoff, Onboarding, and Closeout | C36: NTT Data needs a partner to support managing the HubSpot and consulting project, ensuring deadlines are clear and met. | D36: To support management and communication, a project manager and delivery lead will own all A8 tasks and clearly communicate needs to NTT Data. | E36: - Visibility to budget spend will be provided during the duration of the project - A8 will provide check-in agenda items and follow-ups - NTT Data to communicate to A8's shared inbox for easier collaboration and timely responses
B37: Recurring Project Check-ins
B38: Project Administration
A40: ■ | B40: NEXT Post-Launch Support | F40: =Details!C18*Details!C19 -> 180
B41: NEXT Post-Launch Support | C41: Hours dedicated to post go-live support. These hours can be used for anything HubSpot related (reporting, training, iterations, additional asks, etc.) | F41: Hours/Month: | G41: =Details!C18 -> 30
F42: # of Months: | G42: =Details!C19 -> 6
A45: ※ | E45: Total Estimated Engagement Hours: | F45: =SUMIFS(F:F, A:A, "*•*") + SUMIFS(F:F, A:A, "*◆*") + SUMIFS(F:F, A:A, "*■*") -> 533 | H45: Low Hour Estimate: | I45: {=INDIRECT("Details!G26")} -> 457.2
H46: High Hour Estimate: | I46: {=INDIRECT("Details!H26")} -> 604.8
A47: ⚑ | E47: Total Estimated Investment: | F47: =IFERROR(__xludf.DUMMYFUNCTION("ARRAYFORMULA( SUM( IF( REGEXMATCH(INDIRECT(""A4:A"" & MATCH(""※"",A:A,0)-1), ""^[•◆■]""), INDIRECT(""F4:F"" & MATCH(""※"",A:A,0)-1) * IF( REGEXMATCH(INDIRECT(""A4:A"" & MATCH(""※"",A:A,0)-1), ""^[•◆]""), Details!$C"&"$11, IF( REGEXMATCH(INDIRECT(""A4:A"" & MATCH(""※"",A:A,0)-1), ""^■""), Details!$C$17, 0 ) ), 0 ) ) )"),126085.0) -> 126085
A49: © | B49: 2025 Aptitude 8

Sheet Details
D1: Proposal + Project Details | G1: [Company] aims to enhance their CRM functionality by integrating HubSpot with key business systems like QuickBooks and Power BI, streamlining financial management and analytical reporting. They prioritize automation of sales pipelines and customization of quotes to improve operational efficiency and customer engagement. A strategic partnership is sought for long-term optimization and scalability of their CRM ecosystem. [Company] end goal is a cohesive, data-driven environment that supports growth and adapts to evolving business needs.
A2: • | B2: Deal Inputs | F2: Deal + Asset Links
B3: Company Name | C3: NTT Data | F3: Google Folder
B4: Deal Record ID | C4: 38399950765 | F4: Deal Link
B5: Last Sync to HubSpot | C5: 45784.321 | F5: Solutions Architect
B6: Request Scope Review | D6: scoping_status | F6: Service Library Message
B7: Scope Reviewed | C7: Yes | D7: scoped_reviewed
B9: Engagement Inputs
B10: NOW Project
B11: Hourly Project Rate | C11: 245 | D11: project_hourly_rate
B12: Project Management Factor | C12: 0.2
B13: SA Expected Start Date | C13: 45817
B14: Total Project Months | C14: 5 | D14: project_duration
B16: NEXT Retainer
B17: Hourly NEXT Retainer Rate | C17: 220 | D17: retainer_hourly_rate
B18: NEXT Hours Per Month | C18: 30 | D18: retainer_hours_per_month_sold
B19: NEXT Retainer Months | C19: 6 | D19: retainer_months_sold
B22: Calculated Project Details | F22: Calculated Ranges | G22: Low Hours | H22: High Hours
B23: Deal Amount | C23: {=INDEX(Overview!F:G, MATCH("⚑", Overview!A:A, 0), 1)} -> 126085 | D23: amount | F23: Service Estimates: | G23: =IFERROR(__xludf.DUMMYFUNCTION("ARRAYFORMULA( SUMIFS( Overview!F:F, Overview!F:F, "">0"", Overview!A:A, ""<>•*"", Overview!A:A, ""<>◆*"", ROW(Overview!A:A), "">""&MIN(IF(REGEXMATCH(Overview!A:A,""^•""),ROW(Overview!A:A))), ROW(Overview!A:A), ""<""&MIN(IF(REGEX"&"MATCH(Overview!A:A,""^※|^◆""),ROW(Overview!A:A),99999)) ) )"),231.0) -> 231 | H23: =IFERROR(__xludf.DUMMYFUNCTION("ARRAYFORMULA( SUMIFS( Overview!G:G, Overview!G:G, "">0"", Overview!A:A, ""<>•*"", Overview!A:A, ""<>◆*"", ROW(Overview!A:A), "">""&MIN(IF(REGEXMATCH(Overview!A:A,""^•""),ROW(Overview!A:A))), ROW(Overview!A:A), ""<""&MIN(IF(REGEX"&"MATCH(Overview!A:A,""^◆""),ROW(Overview!A:A),99999)) ) )"),354.0) -> 354
B24: Total Engagement Hours Sold | C24: =SUMIFS(Overview!F:F, Overview!A:A, "*•*") + SUMIFS(Overview!F:F, Overview!A:A, "*◆*") + SUMIFS(Overview!F:F, Overview!A:A, "*■*") -> 533 | D24: sold_hours | F24: Project Management: | G24: =G23 * C12 -> 46.2 | H24: =H23 * C12 -> 70.8
B25: Total Project Hours Sold | C25: =SUMIFS(Overview!F:F, Overview!A:A, "*•*") + SUMIFS(Overview!F:F, Overview!A:A, "*◆*") -> 353 | D25: project_hours_sold | F25: Post-Project Support: | G25: {=INDEX(Overview!F:G, MATCH("■*", Overview!A:A, 0), 1)} -> 180 | H25: {=INDEX(Overview!F:G, MATCH("■*", Overview!A:A, 0), 1)} -> 180
B26: Total Retainer Hours Sold | C26: =SUMIFS(Overview!F:F, Overview!A:A, "*■*") -> 180 | F26: Hour Estimates: | G26: =SUM(G23:G25) -> 457.2 | H26: =SUM(H23:H25) -> 604.8
B27: Expected End Date | C27: =EDATE(C13, C14) -> 45970 | F27: Investment Ranges: | G27: =G26*C11 -> 112014 | H27: =H26*C11 -> 148176
B28: Expected Project Hours/Month | C28: =roundup(C25/C14,0) -> 71
B29: Linear Expected Project Hours/Week | C29: =roundup(C28/4.3,0) -> 17 | F29: Total Estimated Engagement Hours: | G29: =SUMIFS(Overview!F:F, Overview!A:A, "*•*") + SUMIFS(Overview!F:F, Overview!A:A, "*◆*") + SUMIFS(Overview!F:F, Overview!A:A, "*■*") -> 533
B30: Peak Project Expected Hours | C30: =C29*1.2 -> 20.4 | F30: Total Estimated Investment: | G30: {=INDEX(Overview!F:G, MATCH("⚑", Overview!A:A, 0), 1)} -> 126085
B31: Low Project Expected Hours | C31: =C29*0.5 -> 8.5
B32: Dev Work Percentage | C32: =C39/C44 -> 0.099573257 | D32: dev_work_pct
B33: SE Work Percentage | C33: =C41/C44 -> 0.20625889 | D33: se_work_pct
A36: ※ | B36: Calculated Function Summary | F36: SOW Summarized Line Items
B37: =IFERROR(__xludf.DUMMYFUNCTION("LET( square_row, MATCH(""■"", Overview!A:A, 0) - 1, valid_range, SEQUENCE(square_row), raw_calcs, QUERY( ARRAYFORMULA({ IF(INDIRECT(""Overview!I1:I""&square_row) = """", ""Unassigned"", INDIRECT(""Overview!I1:I""&square_row)), IF( "&" REGEXMATCH(INDIRECT(""Overview!A1:A""&square_row), ""•""), 0, IF( REGEXMATCH(INDIRECT(""Overview!A1:A""&square_row), ""◆""), INDIRECT(""Overview!F1:F""&square_row), (INDIRECT(""Overview!F1:F""&square_row"&") + INDIRECT(""Overview!G1:G""&square_row))/2 ) ) }), ""select Col1, sum(Col2) where Col1 is not null and Col2 is not null group by Col1 label Col1 'Function', sum(Col2) 'Hours'"", 0 ), functions, {""F"&"unction"", ""Hours""; ""Consulting"", IFERROR(VLOOKUP(""Consulting"", raw_calcs, 2, FALSE), 0); ""Development"", IFERROR(VLOOKUP(""Development"", raw_calcs, 2, FALSE), 0); ""Project Management"", IFERROR(VLOOKUP("&"""Project Management"", raw_calcs, 2, FALSE), 0); ""Solutions Engineering"", IFERROR(VLOOKUP(""Solutions Engineering"", raw_calcs, 2, FALSE), 0); ""Strategy"", IFERROR(VLOOKUP(""Strategy"", raw_calcs, 2, FALSE), 0); "&" ""Unassigned"", IFERROR(VLOOKUP(""Unassigned"", raw_calcs, 2, FALSE), 0)}, functions )"),"Function") -> Function | C37: =IFERROR(__xludf.DUMMYFUNCTION("""COMPUTED_VALUE"""),"Hours") -> Hours | D37: Percent of | F37: =IFERROR(__xludf.DUMMYFUNCTION("QUERY( Overview!A4:F58, ""select B, F where (A = '•' or A = '◆' or A = '■') and B is not null"" )"),"Data Improvements") -> Data Improvements | G37: =IFERROR(__xludf.DUMMYFUNCTION("""COMPUTED_VALUE"""),25.0) -> 25
B38: =IFERROR(__xludf.DUMMYFUNCTION("""COMPUTED_VALUE"""),"Consulting") -> Consulting | C38: =IFERROR(__xludf.DUMMYFUNCTION("""COMPUTED_VALUE"""),185.0) -> 185 | D38: =C38/$C$44 -> 0.52631579 | F38: =IFERROR(__xludf.DUMMYFUNCTION("""COMPUTED_VALUE"""),"Marketing Optimization") -> Marketing Optimization | G38: =IFERROR(__xludf.DUMMYFUNCTION("""COMPUTED_VALUE"""),79.0) -> 79
B39: =IFERROR(__xludf.DUMMYFUNCTION("""COMPUTED_VALUE"""),"Development") -> Development | C39: =IFERROR(__xludf.DUMMYFUNCTION("""COMPUTED_VALUE"""),35.0) -> 35 | D39: =C39/$C$44 -> 0.099573257 | F39: =IFERROR(__xludf.DUMMYFUNCTION("""COMPUTED_VALUE"""),"Sales Process Optimization") -> Sales Process Optimization | G39: =IFERROR(__xludf.DUMMYFUNCTION("""COMPUTED_VALUE"""),16.0) -> 16
B40: =IFERROR(__xludf.DUMMYFUNCTION("""COMPUTED_VALUE"""),"Project Management") -> Project Management | C40: =IFERROR(__xludf.DUMMYFUNCTION("""COMPUTED_VALUE"""),59.0) -> 59 | D40: =C40/$C$44 -> 0.16785206 | F40: =IFERROR(__xludf.DUMMYFUNCTION("""COMPUTED_VALUE"""),"HubSpot AI Agents & Enrichments") -> HubSpot AI Agents & Enrichments | G40: =IFERROR(__xludf.DUMMYFUNCTION("""COMPUTED_VALUE"""),32.0) -> 32
B41: =IFERROR(__xludf.DUMMYFUNCTION("""COMPUTED_VALUE"""),"Solutions Engineering") -> Solutions Engineering | C41: =IFERROR(__xludf.DUMMYFUNCTION("""COMPUTED_VALUE"""),72.5) -> 72.5 | D41: =C41/$C$44 -> 0.20625889 | F41: =IFERROR(__xludf.DUMMYFUNCTION("""COMPUTED_VALUE"""),"Systems Integration") -> Systems Integration | G41: =IFERROR(__xludf.DUMMYFUNCTION("""COMPUTED_VALUE"""),112.0) -> 112
B42: =IFERROR(__xludf.DUMMYFUNCTION("""COMPUTED_VALUE"""),"Strategy") -> Strategy | C42: =IFERROR(__xludf.DUMMYFUNCTION("""COMPUTED_VALUE"""),0.0) -> 0 | D42: =C42/$C$44 -> 0 | F42: =IFERROR(__xludf.DUMMYFUNCTION("""COMPUTED_VALUE"""),"Training & Documentation: Enable team success") -> Training & Documentation: Enable team success | G42: =IFERROR(__xludf.DUMMYFUNCTION("""COMPUTED_VALUE"""),30.0) -> 30
B43: =IFERROR(__xludf.DUMMYFUNCTION("""COMPUTED_VALUE"""),"Unassigned") -> Unassigned | C43: =IFERROR(__xludf.DUMMYFUNCTION("""COMPUTED_VALUE"""),0.0) -> 0 | D43: =C43/$C$44 -> 0 | F43: =IFERROR(__xludf.DUMMYFUNCTION("""COMPUTED_VALUE"""),"Project Management + Strategy: Support this phase with transparency and regular progress reports") -> Project Management + Strategy: Support this phase with transparency and regular progress reports | G43: =IFERROR(__xludf.DUMMYFUNCTION("""COMPUTED_VALUE"""),59.0) -> 59
B44: Sum of Function-Based Hours | C44: =sum(C38:C43) -> 351.5 | D44: =SUM(D38:D43) -> 1 | F44: =IFERROR(__xludf.DUMMYFUNCTION("""COMPUTED_VALUE"""),"NEXT Post-Launch Support") -> NEXT Post-Launch Support | G44: =IFERROR(__xludf.DUMMYFUNCTION("""COMPUTED_VALUE"""),180.0) -> 180

Sheet Change Order Lead Score + Lifec
B1: NTT Data
A2: Service | B2: Customer Story | C2: Suggested Path | D2: Assumptions | E2: Estimated Low Hours | F2: Estimated High Hours | G2: Potential Variance | H2: Function | I2: POC
A4: Lifecycle Management | B4: NTT needs a lifecycle framework that accommodates movement through the Lead Pipeline and references Deals to allow for "Customer" updates. | C4: A8 to configure a lifecycle stages to align with NTT's marketing and sales processes and necessary integrations, as well as to align with the lead scoring model described. | D4: - Single lifecycle per person and account objects - Lifecycle automation will be integrated with lead scoring models - Both behavioral and demographic data will influence lifecycle progression - Custom lead scoring will support this strategy and will be implemented within its own service line - Custom properties to track lifecycle stages are not included | E4: 4 | F4: 6 | H4: Consulting
A5: Lead Scoring & Automations | B5: As a sales and marketing team, we need to utilize a lead score property to identify high-potential leads, enabling the sales team to prioritize outreach and improve conversion rates. | C5: Configure a custom lead score based on key engagement metrics, such as email interactions, form submissions, and website visits. Create automated workflows to update the lead score in real time and notify the sales team when leads reach a defined threshold. | D5: - Aptitude 8 will create up to 5 scores using the native functionality. - A8 to support with ad hoc training on how to create and update required lists and automations - Client will provide initial criteria for lead scoring and access to necessary data sources (e.g. forms are already implemented and referenceable.) - Any future adjustments to the lead scoring model beyond the initial setup will require additional time or a change request. - HubSpot has a limit of 50 custom lead scores | E5: 9 | F5: 11 | H5: Consulting

Sheet Change Order to Data Quality Pr
B1: NTT Data
A2: Service | B2: Customer Story | C2: Suggested Path | D2: Assumptions | E2: Estimated Low Hours | F2: Estimated High Hours | G2: Potential Variance | H2: Function | I2: POC
A4: Deduplication of Companies via CCA | B4: NTT Data needs company records deduplicated across the CRM in perpetuity. | C4: Deploy deduplication rules and tools (e.g. via HubSpot, Insycle, or Operations Hub) with support for automation where possible. | D4: - Aptitude 8 assumes there are at least 5,000 company duplicates to be addressed and will resolve all 5,000 - Duplicates currently stem from poor import logic. Aptitude 8 will provide training to help ensure that does not occur again. - Aptitude 8 assumes code will be written to programmatically solve for the current dupes and manage imported dupes if possible in the future. - The cleanup may require NTT Data to review large datasets in order to maintain a high level of accuracy. - Assumes we cannot merge any accounts with C4C Account IDs into any accounts without them. | E4: 18 | F4: 22 | H4: Consulting
H5: Consulting

Sheet Section
B1: New Section Template Note: Please do not edit rows 4 to 8, or change any volume of columns or it will break the script that pulls this content into the overview doc.
A4: • | B4: Generic Section: Summary about the delivery item | F4: =IFERROR(__xludf.DUMMYFUNCTION("ROUNDUP( ( SUM( INDIRECT( ""F""&(ROW()+1)&"":F""& IFERROR( INDEX( FILTER( ROW(A:A), REGEXMATCH(A:A, ""^[•◆■※⊳]""), ROW(A:A) > ROW() ), 1 "&" )-1, 999 ) ) )+ SUM( INDIRECT( ""G""&(ROW()+1)&"":G""& IFERROR( INDEX( FILTER( ROW(A:A), REGEXMATCH(A:A, ""^[•◆■※⊳]""), ROW(A:A) "&"> ROW() ), 1 )-1, 999 ) ) ) )/2 )"),23.0) -> 23 | H4: Low
B5: Lorem Ipsum | C5: Lorem Ipsum | D5: Lorem Ipsum | E5: Lorem Ipsum | F5: 5 | G5: 10
B6: Lorem Ipsum | C6: Lorem Ipsum | D6: Lorem Ipsum | E6: Lorem Ipsum | F6: 5 | G6: 10
B7: Lorem Ipsum | C7: Lorem Ipsum | D7: Lorem Ipsum | E7: Lorem Ipsum | F7: 5 | G7: 10
A12: ⊳ | B12: Generic: Summary about the delivery item | F12: =IFERROR(__xludf.DUMMYFUNCTION("ROUNDUP( ( SUM( INDIRECT( ""F""&(ROW()+1)&"":F""& IFERROR( INDEX( FILTER( ROW(A:A), REGEXMATCH(A:A, ""^[•◆■※⊳]""), ROW(A:A) > ROW() ), 1 "&" )-1, 999 ) ) )+ SUM( INDIRECT( ""G""&(ROW()+1)&"":G""& IFERROR( INDEX( FILTER( ROW(A:A), REGEXMATCH(A:A, ""^[•◆■※⊳]""), ROW(A:A) "&"> ROW() ), 1 )-1, 999 ) ) ) )/2 )"),30.0) -> 30 | H12: Low
B13: Lorem Ipsum | C13: Lorem Ipsum | D13: Lorem Ipsum | E13: Lorem Ipsum | F13: 10 | G13: 10
B14: Lorem Ipsum | C14: Lorem Ipsum | D14: Lorem Ipsum | E14: Lorem Ipsum | F14: 10 | G14: 10
B15: Lorem Ipsum | C15: Lorem Ipsum | D15: Lorem Ipsum | E15: Lorem Ipsum | F15: 10 | G15: 10
