Workbook

Sheet Input
A1: Display | B1: Workstream | C1: Service_Title | D1: Customer_Story | E1: Suggested_Path | F1: Assumptions | G1: Estimated_Low_Hours | H1: Estimated_High_Hours | I1: Contracted_Hours | J1: Requires_Clarification | K1: Function | L1: Library_ID | M1: Project_ID | N1: Internal_Notes | O1: Task_Link
A2: Now | B2: USPS Address Validation & Shipping Automation | C2: Discovery Workshops | D2: PBE requires consensus on USPS-native address validation, label creation, and tracking updates to remove manual effort and rework. | E2: Facilitate 3–4 workshops with Sales, Ops, and IT to define validation points, label flow, tracking cadence, Azure storage model, field mappings, and success criteria. | F2: - Includes up to 2 sessions with notes + playback. - Excludes formal technical design; covered by Solution Design. - Client provides USPS business rules and sandbox/credentials. - Scope changes after playback require change order. | G2: 8 | H2: 10 | I2: =IF(AND(G2<>"",H2<>""),ROUNDUP(AVERAGE(G2:H2),0),"") -> 9 | J2: FALSE | K2: Solutions Engineering | N2: - One row per business process - 2 meetings for low complexity, 3-4 meetings for moderate complexity, 5+ for high complexity projects
A3: Now | B3: USPS Address Validation & Shipping Automation | C3: Solution Design <br> (TRD & Architecture) | D3: PBE needs a defensible, secure design for HubSpot ⇄ USPS flows with Azure-based label storage. | E3: Produce TRD and architecture diagram covering USPS endpoints, HubSpot extension pattern, Azure Blob write/read path, mappings, error paths, and monitoring approach. | F3: - Includes 1 TRD (≤35 pp) + 1 architecture diagram; up to 2 rounds of revisions. - Excludes USPS/Azure procurement and on-prem components. - Client supplies USPS keys and Azure access model. - New endpoints or security changes post-approval trigger change order. | G3: 13 | H3: 15 | I3: =IF(AND(G3<>"",H3<>""),ROUNDUP(AVERAGE(G3:H3),0),"") -> 14 | J3: FALSE | K3: Solutions Engineering
A4: Now | B4: USPS Address Validation | C4: Build: Address Validation <br> (HubSpot → USPS) | D4: PBE needs automated address verification at creation/update to reduce failed deliveries. | E4: Implement a HubSpot workflow/custom action to call USPS /addresses/v3/standardize, persist standardized fields + “Address Verified” flag, and route failures to a queue. | F4: - Includes 1 validation flow, 1 exception queue, and up to 10 mapped fields across Contact/Company/Deal. - Excludes international validation. - Client provides test data and API keys. - Adding new objects or >10 fields triggers change order. - PBD will need to create a USPS account from their current provider and shipping orders. | G4: 20 | H4: 23 | I4: =IF(AND(G4<>"",H4<>""),ROUNDUP(AVERAGE(G4:H4),0),"") -> 22 | J4: FALSE | K4: Development | N4: - One row per business process - # of expected meetings for requirements gathering must have at least the equivalent SD workshops - 1 hour per deliverable, minimum - there are 8 deliverables listed, the minimum we create is 6 each time? with POC and UAT might not be applicable for the most basic projects? - Add to assumptions SE time is required when applicable, ensure hours align - Language in Red is optional for each scope. Only keep if applicable.
A5: Hide | B5: USPS Address Validation & Shipping Automation | C5: Build: Label Generation & <br> Azure Storage Linkage | D5: PBE wants label creation from HubSpot with PDFs stored in Azure and linked on Deals. | E5: Implement USPS /domesticlabelsv3/labels; upload to Azure Blob; write secure label link + metadata (service, ship date, cost) to HubSpot. | F5: - Includes 1 label flow and Azure upload integration with 1 container and up to 6 metadata fields. - Excludes custom label artwork and multi-package logic. - Client provisions Azure Blob container, keys, and access policies. - Changes to storage model or security posture may require change order. | G5: 26 | H5: 30 | I5: =IF(AND(G5<>"",H5<>""),ROUNDUP(AVERAGE(G5:H5),0),"") -> 28 | J5: TRUE | K5: Development | N5: - At least one 60 minute meeting for low complexity, at least two 60 minute meetings for moderate complexity, and at least 3 for high complexity projects
A6: Hide | B6: USPS Address Validation & Shipping Automation | C6: Build: Tracking Integration <br> (USPS → HubSpot) | D6: PBE needs automatic status and milestone updates on the Deal to avoid manual lookups. | E6: Implement USPS Tracking API (webhook or poll) to update Tracking #, Status, Last Scan, and Delivery Date; surface errors in an “Attention” list. | F6: - Includes up to 6 return fields and 1 error list/queue. - Excludes historical backfill and external BI dashboards. - Client enables outbound notifications or provides polling cadence + test numbers. - Expanding to other carriers or SLAs triggers change order. | G6: 25 | H6: 30 | I6: =IF(AND(G6<>"",H6<>""),ROUNDUP(AVERAGE(G6:H6),0),"") -> 28 | J6: FALSE | K6: Development
A7: Now | B7: USPS Address Validation | C7: UAT <br> (USPS Automation) | D7: PBE must validate end-to-end flows before launch. | E7: Run a structured UAT covering validation, label, error paths, and tracking updates; log defects and retests. | F7: - Includes 1 UAT cycle (≤15 cases) with summary. - Excludes live shipments; test mode only. - Client furnishes UAT users and scenarios. - Extra cycles or production pilots billed separately. | G7: 14 | H7: 15 | I7: =IF(AND(G7<>"",H7<>""),ROUNDUP(AVERAGE(G7:H7),0),"") -> 15 | J7: FALSE | K7: Development
A8: Now | B8: Dealer Bulk Submission Spreadsheet Process | C8: Discovery Workshops (Upload) | D8: CS needs a low-touch way to create many sample orders at once without manual entry. | E8: Host sessions to finalize CSV columns, validation rules, product/quantity logic, dedupe strategy, and import frequency. | F8: - Includes 2 sessions with playback + decision log. - Excludes technical design deliverables; covered by Solution Design. - Client provides sample spreadsheets and SKU logic. - Scope changes post-playback require change order. | G8: 6 | H8: 8 | I8: =IF(AND(G8<>"",H8<>""),ROUNDUP(AVERAGE(G8:H8),0),"") -> 7 | J8: FALSE | K8: Solutions Engineering
A9: Now | B9: Dealer Bulk Submission Spreadsheet Process | C9: Solution Design <br> (TRD & Mapping) | D9: PBE needs a blueprint to convert validated rows into Deals and Line Items reliably. | E9: Author TRD with template spec, field dictionary, validation matrix, mapping to objects/associations, and error-report approach. | F9: - Includes 1 TRD (≤25 pp) + 1 mapping diagram; up to 2 revisions. - Excludes historical imports. - Client approves template + mapping prior to build. - Template or mapping changes after sign-off require change order. | G9: 15 | H9: 18 | I9: =IF(AND(G9<>"",H9<>""),ROUNDUP(AVERAGE(G9:H9),0),"") -> 17 | J9: FALSE | K9: Development
A10: Now | B10: Dealer Bulk Submission Spreadsheet Process | C10: Build: Template & Upload <br> Automation / Process | D10: CS requires a governed import process that rejects bad rows and creates correct records. | E10: Deliver a locked CSV template; build validation/parsing; create records via API/workflows with proper associations and line items; tag created records for QA. | F10: - Includes 1 CSV template, 1 upload automation, up to 20 mapped fields, and 1 “Created via Upload” tag. - Excludes multi-file batching and dealer self-service portal. - Client approves template and provides SKU lists/values. - Changes to file structure, SKU logic, or >20 fields trigger change order. | G10: 28 | H10: 32 | I10: =IF(AND(G10<>"",H10<>""),ROUNDUP(AVERAGE(G10:H10),0),"") -> 30 | J10: FALSE | K10: Development
A11: Now | B11: Dealer Bulk Submission Spreadsheet Process | C11: UAT (Upload) | D11: PBE must confirm good/bad file handling and correct record creation. | E11: Execute UAT with valid/invalid files, partial failures, and rollback checks; finalize acceptance. | F11: - Includes 1 UAT cycle with ≤10 scenarios. - Excludes external dealer testing; client manages external comms. - Client supplies test data. - Additional cycles billed separately. | G11: 10 | H11: 14 | I11: =IF(AND(G11<>"",H11<>""),ROUNDUP(AVERAGE(G11:H11),0),"") -> 12 | J11: FALSE | K11: Development
A12: Later | B12: Attribution and Revenue Reporting | C12: Scalable Revenue/Growth Reporting – Discovery Workshops | D12: Stakeholders need guardrails for “samples → sales impact,” indirect vs. direct, and “referred by” logic at scale. | E12: Facilitate sessions to define KPIs, aggregation windows, eligible pipelines, property strategy (rollups/labels), and performance tradeoffs. | F12: - Includes up to 3 sessions + discovery notes/playback. - Excludes creation of properties/workflows/reports. - Client supplies example reports, fiscal/calendar rules, and volume estimates. - Discovery may recommend BI for certain visuals; tradeoffs will be documented. | G12: 12 | H12: 14 | I12: =IF(AND(G12<>"",H12<>""),ROUNDUP(AVERAGE(G12:H12),0),"") -> 13 | J12: TRUE | K12: Consulting
A13: Later | B13: Attribution and Revenue Reporting | C13: Custom Attribution Object – Solution Design (TRD & Data Model) | D13: Team requires a data model and execution plan before committing to implementation effort. | E13: Produce TRD + Lucid-style schema for object, properties, associations/labels, rollup strategy, and example reporting queries with a phased backlog. | F13: - Includes 1 TRD + 1 data model; up to 2 iterations. - Excludes implementation, migrations, and dashboards. - Material changes or platform limits encountered will trigger change order. | G13: 19 | H13: 20 | I13: =IF(AND(G13<>"",H13<>""),ROUNDUP(AVERAGE(G13:H13),0),"") -> 20 | J13: TRUE | K13: Solutions Engineering
A14: Later | B14: Attribution and Revenue Reporting | C14: Attribution Rollup Automation <br> & Property Framework | D14: PBE requires foundational rollup and calculated properties to operationalize the attribution model defined in discovery and design. | E14: Implement initial HubSpot properties, calculated fields, and workflows to test and operationalize attribution rollups once the TRD and data model are approved. | F14: - Includes an initial 25 hours for configuration and proof-of-concept implementation. - Scope and total LOE to be re-evaluated post-solution validation - final effort may range 25 – 70 hours depending on architecture complexity. - Excludes new custom objects, BI connectors, or large-scale data migrations. - Any additional effort beyond the initial 25 hours requires written approval or change order. | G14: 25 | H14: 25 | I14: =IF(AND(G14<>"",H14<>""),ROUNDUP(AVERAGE(G14:H14),0),"") -> 25 | J14: TRUE | K14: Development
A15: Later | B15: Attribution and Revenue Reporting | C15: Revenue & Growth Reporting Build | D15: PBE requires initial dashboards and reports linking attribution data, sample activity, and revenue trends, leveraging the confirmed reporting framework. | E15: Create early-stage dashboards within HubSpot using confirmed rollups and pipelines; validate structure and metrics with stakeholders before expanding. | F15: - Includes an initial 25 hours for report and dashboard buildout. - Final scope to be reassessed after validation of data model and property framework; expected range 25 – 70 hours. - Excludes external BI tools, ETL pipelines, or historical backfill. - Additional reporting requests or dataset changes post-validation require change order. | G15: 25 | H15: 25 | I15: =IF(AND(G15<>"",H15<>""),ROUNDUP(AVERAGE(G15:H15),0),"") -> 25 | J15: TRUE | K15: Development
A16: Now | B16: Launch, Training & Handoff | C16: Training & Enablement | D16: Sales/Ops/IT must adopt new screens, upload steps, and USPS workflows confidently. | E16: Deliver 2 recorded sessions (Ops, Sales, IT) on upload, USPS flows, exception handling, and dashboards. | F16: - Includes up to 2 sessions + recordings and slide handouts. - Client ensures attendance and environment access. - Extra sessions/materials beyond listed counts billed separately. | G16: 5 | H16: 7 | I16: =IF(AND(G16<>"",H16<>""),ROUNDUP(AVERAGE(G16:H16),0),"") -> 6 | J16: FALSE | K16: Consulting
A17: Now | B17: Launch, Training & Handoff | C17: Documentation & Handoff | D17: PBE requires clear admin/ops materials to support day-to-day ownership. | E17: Provide admin guide, integration runbook (error queues + remediation), and field mapping registry for USPS + Upload. | F17: - Includes 1 admin guide, 1 runbook, 1 mapping registry; up to 2 revisions. - Excludes IT policy documents and end-user SOPs beyond included guides. - Client owns credential storage and key rotation. - Requests beyond listed docs require change order. | G17: 10 | H17: 12 | I17: =IF(AND(G17<>"",H17<>""),ROUNDUP(AVERAGE(G17:H17),0),"") -> 11 | J17: FALSE | K17: Development
... A19: Now | B19: Launch, Training & Handoff | C19: Monitoring & Error Handling Setup | D19: PBE wants ongoing visibility into USPS API health and upload failures. | E19: Configure HubSpot dashboards/lists and a weekly digest covering failed validations, label/tracking errors, and rejected rows. | F19: - Includes up to 3 dashboards and 1 weekly digest. - Excludes third-party monitoring tools/alerting. - Client assigns an owner to review/action the queues. - Real-time alerting or external tools require change order. | G19: 10 | H19: 12 | I19: =IF(AND(G19<>"",H19<>""),ROUNDUP(AVERAGE(G19:H19),0),"") -> 11 | J19: FALSE | K19: Development
I20: =IF(AND(G20<>"",H20<>""),ROUNDUP(AVERAGE(G20:H20),0),"") | J20: FALSE
I21: =IF(AND(G21<>"",H21<>""),ROUNDUP(AVERAGE(G21:H21),0),"") | J21: FALSE
I22: =IF(AND(G22<>"",H22<>""),ROUNDUP(AVERAGE(G22:H22),0),"") | J22: FALSE
I23: =IF(AND(G23<>"",H23<>""),ROUNDUP(AVERAGE(G23:H23),0),"") | J23: FALSE
I24: =IF(AND(G24<>"",H24<>""),ROUNDUP(AVERAGE(G24:H24),0),"") | J24: FALSE
I25: =IF(AND(G25<>"",H25<>""),ROUNDUP(AVERAGE(G25:H25),0),"") | J25: FALSE
I26: =IF(AND(G26<>"",H26<>""),ROUNDUP(AVERAGE(G26:H26),0),"") | J26: FALSE
I27: =IF(AND(G27<>"",H27<>""),ROUNDUP(AVERAGE(G27:H27),0),"") | J27: FALSE
I28: =IF(AND(G28<>"",H28<>""),ROUNDUP(AVERAGE(G28:H28),0),"") | J28: FALSE
I29: =IF(AND(G29<>"",H29<>""),ROUNDUP(AVERAGE(G29:H29),0),"") | J29: FALSE
I30: =IF(AND(G30<>"",H30<>""),ROUNDUP(AVERAGE(G30:H30),0),"") | J30: FALSE
I31: =IF(AND(G31<>"",H31<>""),ROUNDUP(AVERAGE(G31:H31),0),"") | J31: FALSE
... I140: =IF(AND(G140<>"",H140<>""),ROUNDUP(AVERAGE(G140:H140),0),"") | J140: FALSE
J141: FALSE
J142: FALSE

Sheet ClickUp Import
A1: Task Type | B1: Task Name | C1: Description Content | D1: High Hours Estimate | E1: Contracted Hours
A2: Workstream | B2: Dealer Bulk Submission Spreadsheet Process
A3: Customer Story | B3: Discovery Workshops (Upload) | C3: CS needs a low-touch way to create many sample orders at once without manual entry. Host sessions to finalize CSV columns, validation rules, product/quantity logic, dedupe strategy, and import frequency. - Includes 2 sessions with playback + decision log. - Excludes technical design deliverables; covered by Solution Design. - Client provides sample spreadsheets and SKU logic. - Scope changes post-playback require change order. | D3: 8 | E3: 7
A4: Customer Story | B4: Solution Design <br> (TRD & Mapping) | C4: PBE needs a blueprint to convert validated rows into Deals and Line Items reliably. Author TRD with template spec, field dictionary, validation matrix, mapping to objects/associations, and error-report approach. - Includes 1 TRD (≤25 pp) + 1 mapping diagram; up to 2 revisions. - Excludes historical imports. - Client approves template + mapping prior to build. - Template or mapping changes after sign-off require change order. | D4: 18 | E4: 17
A5: Customer Story | B5: Build: Template & Upload <br> Automation / Process | C5: CS requires a governed import process that rejects bad rows and creates correct records. Deliver a locked CSV template; build validation/parsing; create records via API/workflows with proper associations and line items; tag created records for QA. - Includes 1 CSV template, 1 upload automation, up to 20 mapped fields, and 1 “Created via Upload” tag. - Excludes multi-file batching and dealer self-service portal. - Client approves template and provides SKU lists/values. - Changes to file structure, SKU logic, or >20 fields trigger change order. | D5: 32 | E5: 30
A6: Customer Story | B6: UAT (Upload) | C6: PBE must confirm good/bad file handling and correct record creation. Execute UAT with valid/invalid files, partial failures, and rollback checks; finalize acceptance. - Includes 1 UAT cycle with ≤10 scenarios. - Excludes external dealer testing; client manages external comms. - Client supplies test data. - Additional cycles billed separately. | D6: 14 | E6: 12
A7: Workstream | B7: Launch, Training & Handoff
A8: Customer Story | B8: Training & Enablement | C8: Sales/Ops/IT must adopt new screens, upload steps, and USPS workflows confidently. Deliver 2 recorded sessions (Ops, Sales, IT) on upload, USPS flows, exception handling, and dashboards. - Includes up to 2 sessions + recordings and slide handouts. - Client ensures attendance and environment access. - Extra sessions/materials beyond listed counts billed separately. | D8: 7 | E8: 6
A9: Customer Story | B9: Documentation & Handoff | C9: PBE requires clear admin/ops materials to support day-to-day ownership. Provide admin guide, integration runbook (error queues + remediation), and field mapping registry for USPS + Upload. - Includes 1 admin guide, 1 runbook, 1 mapping registry; up to 2 revisions. - Excludes IT policy documents and end-user SOPs beyond included guides. - Client owns credential storage and key rotation. - Requests beyond listed docs require change order. | D9: 12 | E9: 11
A10: Customer Story | B10: Cutover & Hypercare | C10: PBE needs a controlled rollout with short-term stabilization support. Execute cutover plan for USPS + Upload; monitor queues and remediate critical issues during hypercare (≤10 hrs over 2 weeks). - This hypercare period is for 2 weeks (10 business days) post-launch - Hypercare support is only available during regular business hours on regular working days (i.e. no holidays or weekends) - Any unused Hypercare hours can be applied to the first month of the NEXT retainer - Hypercare hours may be applied to any issues, bugs, or questions that relate to the launch, but any new functionality requests will be backlogged for the NEXT retainer - Any hours needed for bug fixes beyond the scoped Hypercare hours will be billed as overage hours | D10: 14 | E10: 13
A11: Customer Story | B11: Monitoring & Error Handling Setup | C11: PBE wants ongoing visibility into USPS API health and upload failures. Configure HubSpot dashboards/lists and a weekly digest covering failed validations, label/tracking errors, and rejected rows. - Includes up to 3 dashboards and 1 weekly digest. - Excludes third-party monitoring tools/alerting. - Client assigns an owner to review/action the queues. - Real-time alerting or external tools require change order. | D11: 12 | E11: 11
A12: Workstream | B12: USPS Address Validation
A13: Customer Story | B13: Build: Address Validation <br> (HubSpot → USPS) | C13: PBE needs automated address verification at creation/update to reduce failed deliveries. Implement a HubSpot workflow/custom action to call USPS /addresses/v3/standardize, persist standardized fields + “Address Verified” flag, and route failures to a queue. - Includes 1 validation flow, 1 exception queue, and up to 10 mapped fields across Contact/Company/Deal. - Excludes international validation. - Client provides test data and API keys. - Adding new objects or >10 fields triggers change order. - PBD will need to create a USPS account from their current provider and shipping orders. | D13: 23 | E13: 22
A14: Customer Story | B14: UAT <br> (USPS Automation) | C14: PBE must validate end-to-end flows before launch. Run a structured UAT covering validation, label, error paths, and tracking updates; log defects and retests. - Includes 1 UAT cycle (≤15 cases) with summary. - Excludes live shipments; test mode only. - Client furnishes UAT users and scenarios. - Extra cycles or production pilots billed separately. | D14: 15 | E14: 15
A15: Workstream | B15: USPS Address Validation & Shipping Automation
A16: Customer Story | B16: Discovery Workshops | C16: PBE requires consensus on USPS-native address validation, label creation, and tracking updates to remove manual effort and rework. Facilitate 3–4 workshops with Sales, Ops, and IT to define validation points, label flow, tracking cadence, Azure storage model, field mappings, and success criteria. - Includes up to 2 sessions with notes + playback. - Excludes formal technical design; covered by Solution Design. - Client provides USPS business rules and sandbox/credentials. - Scope changes after playback require change order. | D16: 10 | E16: 9
A17: Customer Story | B17: Solution Design <br> (TRD & Architecture) | C17: PBE needs a defensible, secure design for HubSpot ⇄ USPS flows with Azure-based label storage. Produce TRD and architecture diagram covering USPS endpoints, HubSpot extension pattern, Azure Blob write/read path, mappings, error paths, and monitoring approach. - Includes 1 TRD (≤35 pp) + 1 architecture diagram; up to 2 rounds of revisions. - Excludes USPS/Azure procurement and on-prem components. - Client supplies USPS keys and Azure access model. - New endpoints or security changes post-approval trigger change order. | D17: 15 | E17: 14
A18: Workstream | B18: Project Management | E18: 33
A19: Customer Story | B19: Project Kickoff, Onboarding, and Closeout
A20: Customer Story | B20: Recurring Project Check-ins
A21: Customer Story | B21: Project Administration

Sheet Config
A1: Configuration | B1: Value | C1: Description | D1: HubSpot Property
A2: GDrive + Deal Inputs
A3: Company Name | B3: PBE Net | C3: Client company name for proposals
A4: Google Folder | C4: Needs to be manually input for the time being, will be set by the Pipedream automation
A5: Deal Record ID | B5: 38372104066 | C5: HubSpot deal record ID, needs to be manually input for the time being, will be set by the Pipedream automation
A6: Last Sync to HubSpot | B6: 45975.623 | C6: The last time the story doc was sync'd to the HubSpot deal record
A7: Solutions Architect | C7: SA assigned to this project
A8: Scoping Status | B8: Scope Confirmation | D8: scoping_status
A9: Project ID | B9: ------ | C9: TBD on usage to facilitate project creation
A11: Client HTML Page
A12: Client Page URL | B12: https://script.google.com/macros/s/AKfycbzGfZXXrB8GB7kt-FSeTA8sL0Rw3BzaXwifNA9CDpjsqe8NBn4EL159NLqLBYwGjqUw/exec?sheetId=1APvZJQRd7hgMk2UowHkXDGeQKirg2wK8HE5hfPs8LrI | C12: The URL of the page that will be shared in Trumpet | D12: customer_stories_client_url
A13: Last Client Page URL Generated | B13: 45959.361 | C13: The last time you created/updated a URL so we can understand deployment app versions
A14: Client Page Status | B14: Final Presentation | C14: Determines page status for the shared link
A16: NOW Project
A17: Hourly Project Rate | B17: 245 | C17: Standard hourly rate for most services | D17: project_hourly_rate
A18: Project Management Factor | B18: 0.2 | C18: Percentage markup for project management
A19: Project Management Content | B19: To support management and communication, a project manager and delivery lead will own all A8 tasks and clearly communicate needs. - Visibility to budget spend will be provided during the duration of the project - A8 will provide check-in agenda items and follow-ups - PBE to communicate to A8's shared inbox for easier collaboration and timely responses - PBE driven delay will result in additional PM time billed to manage timeline | C19: Description text for the PM section. editable by you.
A20: SA Expected Start Date | B20: 45936 | C20: Project start date
A21: Total Project Months | B21: 6 | C21: Expected project duration | D21: project_duration
A23: NEXT Support Retainer
A24: Post-Launch Hourly Rate | B24: 245 | C24: Post-launch rate, a zero here will hide the workstream/section | D24: retainer_hourly_rate
A25: Post-Launch Hours Per Month | B25: 30 | C25: Post-launch hours per month, a zero here will hide the workstream/section | D25: retainer_hours_per_month_sold
A26: Post-Launch # of Months | B26: 1 | C26: Post-launch months, a zero here will hide the workstream/section | D26: retainer_months_sold
A27: Post-Launch Support Content | B27: Hours dedicated to post go-live support. These hours can be used for anything HubSpot related (reporting, training, iterations, additional asks, etc.) | C27: Description text for the post-launch section
A30: Additional Notes + Considerations
A31: Additional Notes | B31: - The assumptions content in this scope is based on information and discovery during the sales evaluation and is subject to change during the project if additional challenges or barriers are discovered. - A8 is a Time & Materials agency, we will provide transparent budget tracking throughout the project and change orders will require approvals. - We interchange between A8 and Aptitude 8 in this document. - Scope includes USPS Address Validation & Shipping Automation and Dealer Bulk Upload (Spreadsheet) Automation. - Customer Portal and Marketplace App options are excluded. - Reporting & Attribution are limited to discovery and design only; build to be estimated separately. - Automates address validation, label creation, and tracking using USPS REST APIs directly from HubSpot. - Labels are stored in client-managed Azure Blob Storage, with secure links written back to HubSpot. - Tracking updates are synced automatically via USPS API (polling or webhook). - All functionality runs within HubSpot workflows and CRM cards; no external app or UI. - Client provides USPS credentials and owns USPS account setup. - Mapping and validation logic defined during Solution Design and documented in the TRD. - Internal-only solution; no external dealer portal or login interface included. - Enables bulk order creation through a standardized CSV template processed via HubSpot automation. - Validates and rejects bad rows; creates Deals and Line Items from approved data. - Aptitude 8 integrates HubSpot and USPS with the Azure container and documents connection points. - Azure security, compliance, and maintenance remain under client ownership. - Client Azure team provisions and manages Blob Storage, keys, and permissions. - Only USPS is in scope; no additional carriers included. - Client provides all credentials, test data, and UAT participants. - Design assumes typical HubSpot API limits; major data scale or API changes may require redesign. - Hypercare includes up to 10 hours post-launch; ongoing governance transitions to client or separate retainer. - Any post-approval changes to USPS APIs, Azure setup, or HubSpot schema will require a change order. - Requires HubSpot Enterprise with Operations Hub and Custom Code Actions. | C31: Description text for below the investment summaries, but above the later phase workstreams

Sheet Calculations
D1: HubSpot Property
A2: Calculated Project Details
A3: Total Service Hours Hours | B3: =SUMIF(Input!A:A,"Now",Input!I:I) -> 167 | C3: Total amount of Input rows
A4: Total Project Management Hours | B4: =round(B3*Config!B18,0) -> 33 | C4: Based on PM % in Config Sheet
A5: Total Project Hours Sold | B5: =sum(B3:B4) -> 200 | C5: Service + PM | D5: project_hours_sold
A6: Total Retainer Hours Sold | B6: =Config!B25 * Config!B26 -> 30
A7: Total Engagement Hours Sold | B7: =sum(B5:B6) -> 230 | C7: This should match exactly to the investment block on the HTML Page | D7: sold_hours
A8: Deal Amount | B8: =(B5*Config!B17)+(B6*Config!B24) -> 56350 | C8: This should match exactly to the investment block on the HTML Page | D8: amount
A9: Expected End Date | B9: =EDATE(Config!B20, Config!B21) -> 46118
A10: Expected Project Hours/Month | B10: =roundup(B3/Config!B21,0) -> 28
A11: Linear Expected Project Hours/Week | B11: =roundup(B10/4.3,0) -> 7
A12: Peak Project Expected Hours/Week | B12: =B11*1.2 -> 8.4
A13: Low Project Expected Hours/Week | B13: =B11*0.5 -> 3.5
A14: Dev Work Percentage | B14: =C21 -> 0.59 | D14: dev_work_pct
A15: SE Work Percentage | B15: =C23 -> 0.15 | D15: se_work_pct
A18: Calculated Function Summary
B19: Sum of Hours | C19: Percent of
A20: Consulting | B20: =SUMIFS(Input!I:I,Input!K:K,"Consulting",Input!A:A,"Now") -> 19 | C20: =B20/B26 -> 0.095
A21: Development | B21: =SUMIFS(Input!I:I,Input!K:K,"Development",Input!A:A,"Now") -> 118 | C21: =B21/B26 -> 0.59
A22: Project Management | B22: =B4 -> 33 | C22: =B22/B26 -> 0.165
A23: Solutions Engineering | B23: =SUMIFS(Input!I:I,Input!K:K,"Solutions Engineering",Input!A:A,"Now") -> 30 | C23: =B23/B26 -> 0.15
A24: Strategy | B24: =SUMIFS(Input!I:I,Input!K:K,"Strategy",Input!A:A,"Now") -> 0 | C24: =B24/B26 -> 0
A26: Sum of Function-Based Hours | B26: =sum(B20:B24) -> 200 | C26: =sum(C20:C24) -> 1
A29: Calculated Ranges | B29: Low Hours | C29: High Hours
A30: Project Service Estimates: | B30: =SUMIF(Input!A:A,"Now",Input!G:G) -> 151 | C30: =SUMIF(Input!A:A,"Now",Input!H:H) -> 180
A31: Project Management: | B31: =round(B30*Config!B18,0) -> 30 | C31: =round(C30*Config!B18,0) -> 36
A32: Post-Project Support: | B32: =B6 -> 30 | C32: =B6 -> 30
A33: Hour Estimates: | B33: =SUM(B30:B32) -> 211 | C33: =SUM(C30:C32) -> 246
A34: Investment Ranges: | B34: =(sum(B30:B31)*Config!B17)+(B32*Config!B24) -> 51695 | C34: =(sum(C30:C31)*Config!B17)+(C32*Config!B24) -> 60270
A36: SOW Summarized Line Items
A37: =IFERROR(__xludf.DUMMYFUNCTION("VSTACK( QUERY(Input!A:I,""SELECT B, SUM(I), SUM(I)*""&Config!B17&"" WHERE B IS NOT NULL AND A = 'Now' GROUP BY B LABEL B 'Workstream', SUM(I) 'Total Hours', SUM(I)*""&Config!B17&"" 'Total Investment'"",1), {""Project Management"", ROUND(SUMPRODUCT(QUE"&"RY(Input!A:I,""SELECT SUM(I) WHERE B IS NOT NULL AND A = 'Now' GROUP BY B LABEL SUM(I) ''"",0))*Config!B18,0), ROUND(SUMPRODUCT(QUERY(Input!A:I,""SELECT SUM(I) WHERE B IS NOT NULL AND A = 'Now' GROUP BY B LABEL SUM(I) ''"",0))*Config!B18,0)*Config!B17}, "&" {""Post-Launch Support"", Config!B25*Config!B26, Config!B25*Config!B26*Config!B24} )"),"Workstream") -> Workstream | B37: =IFERROR(__xludf.DUMMYFUNCTION("""COMPUTED_VALUE"""),"Total Hours") -> Total Hours | C37: =IFERROR(__xludf.DUMMYFUNCTION("""COMPUTED_VALUE"""),"Total Investment") -> Total Investment
A38: =IFERROR(__xludf.DUMMYFUNCTION("""COMPUTED_VALUE"""),"Dealer Bulk Submission Spreadsheet Process") -> Dealer Bulk Submission Spreadsheet Process | B38: =IFERROR(__xludf.DUMMYFUNCTION("""COMPUTED_VALUE"""),66.0) -> 66 | C38: =IFERROR(__xludf.DUMMYFUNCTION("""COMPUTED_VALUE"""),16170.0) -> 16170
A39: =IFERROR(__xludf.DUMMYFUNCTION("""COMPUTED_VALUE"""),"Launch, Training & Handoff") -> Launch, Training & Handoff | B39: =IFERROR(__xludf.DUMMYFUNCTION("""COMPUTED_VALUE"""),41.0) -> 41 | C39: =IFERROR(__xludf.DUMMYFUNCTION("""COMPUTED_VALUE"""),10045.0) -> 10045
A40: =IFERROR(__xludf.DUMMYFUNCTION("""COMPUTED_VALUE"""),"USPS Address Validation ") -> USPS Address Validation | B40: =IFERROR(__xludf.DUMMYFUNCTION("""COMPUTED_VALUE"""),37.0) -> 37 | C40: =IFERROR(__xludf.DUMMYFUNCTION("""COMPUTED_VALUE"""),9065.0) -> 9065
A41: =IFERROR(__xludf.DUMMYFUNCTION("""COMPUTED_VALUE"""),"USPS Address Validation & Shipping Automation") -> USPS Address Validation & Shipping Automation | B41: =IFERROR(__xludf.DUMMYFUNCTION("""COMPUTED_VALUE"""),23.0) -> 23 | C41: =IFERROR(__xludf.DUMMYFUNCTION("""COMPUTED_VALUE"""),5635.0) -> 5635
A42: =IFERROR(__xludf.DUMMYFUNCTION("""COMPUTED_VALUE"""),"Project Management") -> Project Management | B42: =IFERROR(__xludf.DUMMYFUNCTION("""COMPUTED_VALUE"""),33.0) -> 33 | C42: =IFERROR(__xludf.DUMMYFUNCTION("""COMPUTED_VALUE"""),8085.0) -> 8085
A43: =IFERROR(__xludf.DUMMYFUNCTION("""COMPUTED_VALUE"""),"Post-Launch Support") -> Post-Launch Support | B43: =IFERROR(__xludf.DUMMYFUNCTION("""COMPUTED_VALUE"""),30.0) -> 30 | C43: =IFERROR(__xludf.DUMMYFUNCTION("""COMPUTED_VALUE"""),7350.0) -> 7350
