Workbook

Sheet Input
A1: Display | B1: Workstream | C1: Service_Title | D1: Customer_Story | E1: Suggested_Path | F1: Assumptions | G1: Estimated_Low_Hours | H1: Estimated_High_Hours | I1: Contracted_Hours | J1: Requires_Clarification | K1: Function | L1: Library_ID | M1: Project_ID | N1: Internal_Notes | O1: Task_Link
A2: Now | B2: Mobilization | C2: Project Kickoff & Team Alignment | D2: As the JLG team, we need to review all sales calls, technical diagrams, and documentation to ensure alignment before discovery begins. | E2: A8 will review sales call recordings, technical architecture diagrams from JLG, existing HubSpot portal, Dynamics 365 setup, and SAP Business One documentation to prepare for stakeholder interviews and create detailed interview agendas. | F2: - Aptitude 8 team will review JLG Demo recordings, intro call, and technical deep dive - JLG technical diagrams and data flow documentation available - Access to existing HubSpot portal (Library Journal, School Library Journal, Hornbook brands) | G2: 8 | H2: 10 | I2: =IF(AND(G2<>"",H2<>""),ROUNDUP(AVERAGE(G2:H2),0),"") -> 9 | J2: FALSE | K2: Strategy | N2: Includes review of Gong recordings and Lucid diagrams
A3: Now | B3: Discovery | C3: Requirements Gathering - Sales & CRM Operations | D3: As the JLG team, we need to understand how our current Dynamics 365 processes for new business and renewals will transition to HubSpot, including our complex school/district data model. | E3: A8 will conduct interviews with Scott Crawford and sales team to map current Dynamics 365 workflows, understand the many-to-many relationship requirements (contacts to schools to districts), renewal cohort processes, quote generation workflows, and self-service portal requirements. | F3: - Interviews with the sales team - Current process includes: renewal cohorts, auto-generated opportunities, manual quotes, web one-click quotes, self-service upsell portal - Complex data model: Districts > Schools > Contacts with many-to-many relationships | G3: 9 | H3: 15 | I3: =IF(AND(G3<>"",H3<>""),ROUNDUP(AVERAGE(G3:H3),0),"") -> 12 | J3: FALSE | K3: Strategy | N3: Multiple sales processes to document: new business vs renewals
A4: Now | B4: Discovery | C4: Requirements Gathering - Marketing & Marketo Migration | D4: As the JLG team, we need to understand our current Marketo setup, workflows, and journeys to plan the migration to HubSpot Marketing Hub. | E4: A8 will conduct interviews to document current Marketo implementation including workflows, lead scoring, landing pages, 5-6 detailed journeys, email templates, and segmentation strategy. Map out how 100K contacts are currently managed and what needs to migrate. | F4: - Interview with marketing - Marketo renewal is end of February (tight timeline) - Current Marketo setup includes: workflows, lead scoring, landing pages, 5-6 detailed journeys - 100K contacts in Marketo - Marketing migration is lower priority than CRM/SAP integration | G4: 6 | H4: 9 | I4: =IF(AND(G4<>"",H4<>""),ROUNDUP(AVERAGE(G4:H4),0),"") -> 8 | J4: FALSE | K4: Strategy
A5: Now | B5: Discovery | C5: Requirements Gathering - Technical Architecture & Data | D5: As the JLG team, we need to map our complex technical architecture including SAP Business One, Dynamics 365, Magento, and all data flows between systems. | E5: A8 will conduct technical interviews with the IT team to understand: SAP B1 custom subscription module, database views and connections, data transformation rules, current API integrations, Power BI reporting requirements, and the 30-person data team's daily operations (6-7K records moved daily). | F5: - Interviews with Data/Finance, IT team member(s) - Ben's team: 30 people making changes to records daily - Average 6-7K records moved between systems daily - SAP Business One has custom subscription module (not accessible via standard API) - Database views used for CRM to pull from SAP - Current integrations: Dynamics <> SAP, Dynamics <> Magento, MDR enrichment tool - SQL Server hosting: Azure (Dynamics), SMB hosting partner (SAP) | G5: 9 | H5: 12 | I5: =IF(AND(G5<>"",H5<>""),ROUNDUP(AVERAGE(G5:H5),0),"") -> 11 | J5: FALSE | K5: Solutions Engineering | N5: Critical path item - SAP integration is most complex element
A6: Now | B6: Discovery | C6: Requirements Gathering - Existing HubSpot Portal | D6: As the JLG team, we need to understand how the existing HubSpot portal is structured and what will change when JLG brand is added as the fourth brand. | E6: A8 will review existing HubSpot portal setup with team to understand: current data model, brand segmentation approach, Darwin subscription fulfillment integration, renewal processes, and any constraints or requirements for adding JLG as fourth brand. | F6: - Interview with team - Three existing brands in HubSpot: Library Journal, School Library Journal, Hornbook - Darwin subscription fulfillment platform currently integrated - Different business model than JLG (less complex renewals) - Portal will be "hijacked" to add JLG - need to understand impact - 2 interviews expected | G6: 6 | H6: 9 | I6: =IF(AND(G6<>"",H6<>""),ROUNDUP(AVERAGE(G6:H6),0),"") -> 8 | J6: FALSE | K6: Strategy
A7: Now | B7: Discovery | C7: Requirements Gathering - E-commerce & Magento | D7: As the JLG team, we need to document our Magento e-commerce setup including subscription orders, book orders, loyalty programs, and how they integrate with CRM and SAP. | E7: A8 will interview team members to map: Magento subscription order flow, book order flow, loyalty program (4 tiers based on annual revenue), checkout process, and how website data flows to Dynamics and SAP. Also explore future Shopify Plus migration plans. | F7: - Interview with team- Magento handles both subscription orders and book orders differently - Subscription orders: Website > CRM > SAP - Book orders: Website > SAP directly - 4-tier loyalty program based on annual revenue - Web one-click self-service renewal portal - RFP sent to CQL and others for potential Shopify Plus migration in 2026 | G7: 6 | H7: 9 | I7: =IF(AND(G7<>"",H7<>""),ROUNDUP(AVERAGE(G7:H7),0),"") -> 8 | J7: FALSE | K7: Strategy
A8: Now | B8: Discovery | C8: Requirements Gathering - Customer Service & SAP Operations | D8: As the JLG team, we need to understand how customer service operations in SAP will interact with HubSpot CRM. | E8: A8 will interview customer service leads to understand: how customer service makes changes in SAP, what data needs to sync back to CRM, order management workflows, subscription management, and financial reporting needs. | F8: - Interview with CFO and customer service team member(s) - Most customer service work happens in SAP, not CRM - Customer service can make changes to accounts that sync back - SAP is source of truth for subscriptions and orders - Need to understand what CS needs to see/do in HubSpot | G8: 6 | H8: 9 | I8: =IF(AND(G8<>"",H8<>""),ROUNDUP(AVERAGE(G8:H8),0),"") -> 8 | J8: FALSE | K8: Solutions Engineering
A9: Now | B9: User Stories Creation | C9: Technical User Stories - Data Model & Integrations | D9: As the JLG team, we need detailed technical user stories covering the data model, SAP integration, Magento integration, and data migrations. | E9: Create comprehensive technical user stories for: custom objects (Schools, Districts, Subscriptions, Subscription Details), SAP Business One bi-directional integration, Magento integration, Dynamics data migration, Marketo asset migration. | F9: - Complex data model: Accounts, Contacts, Schools, Districts with many-to-many relationships - SAP Business One custom subscription module requires custom integration approach - Magento integration for subscription orders (bidirectional) - Multiple custom objects needed: Subscriptions, Subscription Detail, Suggested Products, Processing Cohort, Loyalty, Tax Exemption, One Click, Discount Pricing, Bids and Contracts - Data flows documented in JLG's technical diagrams | G9: 8 | H9: 12 | I9: =IF(AND(G9<>"",H9<>""),ROUNDUP(AVERAGE(G9:H9),0),"") -> 10 | J9: FALSE | K9: Solutions Engineering
A10: Now | B10: User Stories Creation | C10: Functional User Stories - Sales Processes | D10: As the JLG team, we need detailed functional user stories covering new business sales, renewal sales, quote generation, and upsell processes. | E10: Create functional user stories for: new business pipeline and workflow, renewal pipeline and cohort-based opportunity generation, manual quote creation, web one-click quote generation with self-service upsell, suggested products algorithm, discount pricing automation. | F10: - Two distinct sales processes: new business vs renewals - Renewal process: cohort-based, auto-generated opportunities, scheduler opens cohorts - Quote generation: manual PDF option OR dynamic URL for self-service - Self-service portal allows customer to upsell themselves - Suggested products based on district/school/state data and purchase patterns - 73 product categories (not individual books) - Discount pricing based on create date and seasonal factors | G10: 8 | H10: 12 | I10: =IF(AND(G10<>"",H10<>""),ROUNDUP(AVERAGE(G10:H10),0),"") -> 10 | J10: FALSE | K10: Strategy
A11: Now | B11: User Stories Creation | C11: Functional User Stories - Marketing & Lead Management | D11: As the JLG team, we need functional user stories covering marketing automation, lead management, and cross-brand data sharing. | E11: Create functional user stories for: marketing automation workflows, lead scoring, landing pages, forms, email templates, brand segmentation, cross-sell/upsell opportunities between JLG and other brands, data sharing protocols. | F11: - Goal: reduce digital footprint and combine systems for cross-sell/upsell - Currently siloed - need shared data access - 5-6 detailed journeys to migrate from Marketo - Lead scoring in place - Four brands need segmentation but shared data visibility - No lead object currently used in Dynamics - accounts only | G11: 8 | H11: 12 | I11: =IF(AND(G11<>"",H11<>""),ROUNDUP(AVERAGE(G11:H11),0),"") -> 10 | J11: FALSE | K11: Strategy
A12: Now | B12: Solution Design | C12: Technical Specifications - SAP Business One Integration | D12: As the JLG team, we need detailed technical specifications for how HubSpot will integrate bi-directionally with SAP Business One, including the custom subscription module. | E12: A8 will create comprehensive Technical Requirements Document (TRD) including: ERD for SAP-HubSpot data model, integration architecture (database view access vs API), sync frequency and triggers, data transformation rules, error handling, and testing approach. Work with SAP hosting partner (SMB) for vendor approval process. | F12: - SAP Business One hosted by third-party (SMB) on SQL Server - Custom subscription module not accessible via standard SAP API - Current approach: CRM pulls from database views, pushes via API - Data flows: Customers/Subscriptions (bidirectional), Products/Calculations, Primary Contact, Orders - 30-person data team moves 6-7K records daily - Need IT team involvement for database access and architecture decisions - Vendor security approval process required with SAP hosting partner - Power BI pulls from both Dynamics and SAP - need to understand reporting needs - Solution Engineering hours included | G12: 15 | H12: 20 | I12: =IF(AND(G12<>"",H12<>""),ROUNDUP(AVERAGE(G12:H12),0),"") -> 18 | J12: FALSE | K12: Solutions Engineering
A13: Now | B13: Solution Design | C13: Technical Specifications - Magento Integration | D13: As the JLG team, we need technical specifications for how HubSpot will integrate with Magento for subscription orders and loyalty data. | E13: A8 will create TRD for Magento integration including: subscription order sync (Magento > HubSpot > SAP), book order handling, loyalty tier sync, order data mapping, and integration method (likely custom given no in-house developers). | F13: - Magento hosted on Linux/MySQL on AWS - Bidirectional connection for subscription orders - Subscription orders must flow through CRM/HubSpot before SAP - Book orders go directly to SAP (may not need HubSpot integration) - 4-tier loyalty program based on annual revenue - Web one-click renewal process needs to integrate - No in-house developers - A8 must build integration - Potential Shopify Plus migration in late 2026 (may make this sunken cost) - Solution Engineering hours included | G13: 15 | H13: 18 | I13: =IF(AND(G13<>"",H13<>""),ROUNDUP(AVERAGE(G13:H13),0),"") -> 17 | J13: FALSE | K13: Solutions Engineering
A14: Now | B14: Solution Design | C14: Technical Specifications - Data Model & Custom Objects | D14: As the JLG team, we need a detailed data model that supports our complex school/district relationships and subscription management. | E14: A8 will create ERD showing: Company (Districts), Custom Object (Schools), Contacts with many-to-many associations, Deals/Opportunities, Custom Objects (Subscriptions, Subscription Detail, Suggested Products, Processing Cohort, Loyalty, Tax Exemption, Bids and Contracts). Include association labels, required properties, and data flow diagrams. | F14: - Many-to-many relationship required: Contacts can be associated to multiple Schools, Schools associated to Districts - Notes flow up from School to District level - Deals stay at individual School level (don't roll up) - Custom objects needed from Dynamics: Subscriptions, Subscription Detail, Issue Table (Product Calculation), Loyalty, Suggested Products, Tax Exemption, Processing Cohort Opportunities, One Click, Discount Pricing, Bids and Contracts - No Lead object used - Accounts only - Email/call/meeting logging must work at School level - Solution Engineering hours included | G14: 15 | H14: 18 | I14: =IF(AND(G14<>"",H14<>""),ROUNDUP(AVERAGE(G14:H14),0),"") -> 17 | J14: FALSE | K14: Solutions Engineering
A15: Now | B15: Solution Design | C15: Technical Specifications - Dynamics 365 Data Migration | D15: As the JLG team, we need a detailed migration plan to move our Dynamics 365 data to HubSpot without disruption. | E15: A8 will create migration specification including: objects to migrate (Accounts, Contacts, Opportunities, Orders, all custom objects), data mapping document, data cleansing requirements, historical data retention rules, delta migration approach, cutover plan. | F15: - Dynamics 365 hosted on Azure SQL Server - 70 users currently in Dynamics - Migration objects: Contacts, Companies, Deals, Custom Objects (Schools, Districts, Subscriptions, etc.), Workflows, Sales automation, Lists - Historical activities and engagements to migrate - Need to define what constitutes "historical" for migration - MDR enrichment tool currently synced - needs to continue in HubSpot - Dynamics is month-to-month - flexible cutover timing - Solution Engineering hours included | G15: 15 | H15: 18 | I15: =IF(AND(G15<>"",H15<>""),ROUNDUP(AVERAGE(G15:H15),0),"") -> 17 | J15: FALSE | K15: Solutions Engineering
A16: Now | B16: Solution Design | C16: Technical Specifications - Marketo Asset Migration | D16: As the JLG team we need specifications for migrating our Marketo assets and automations to HubSpot Marketing Hub. | E16: A8 will create migration specification including: workflows/journey mapping, email template migration approach, landing page recreation strategy, form migration, list segmentation, lead scoring model transition, and contact migration plan (100K contacts). | F16: - 100K contacts in Marketo - 5-6 detailed journeys to recreate - Workflows with lead scoring - Landing pages (quantity TBD in discovery) - Email templates (quantity TBD) - Forms (quantity TBD) - Lists and segmentation rules - Note: Marketo renewal Feb 28 - timeline very tight, extension needed - May be Phase 2 after CRM/SAP integration per JLG's priorities - Solution Engineering hours included | G16: 12 | H16: 15 | I16: =IF(AND(G16<>"",H16<>""),ROUNDUP(AVERAGE(G16:H16),0),"") -> 14 | J16: FALSE | K16: Strategy
A17: Now | B17: Solution Design | C17: Functional Requirements - Sales Process Automation | D17: As the JLG team, we need detailed functional requirements for our new business and renewal sales processes in HubSpot. | E17: A8 will create FRD including: pipeline stage definitions for new business and renewals, automation workflows for cohort-based renewal opportunity generation, task assignment rules, notification triggers, required properties per stage, deal record layouts, and reporting requirements. | F17: - Two pipelines needed: New Business and Renewal - Renewal process: scheduler opens cohorts, auto-generates opportunities with quotes - Quote generation: manual PDF option OR dynamic URL self-service - Self-service portal allows customer to select upsells - Processing Cohort custom object manages renewal timing - Suggested Products algorithm recommends upsells based on district/school/state data - Discount Pricing automation based on timing and fulfillment status - 35-40 sales users need adoption | G17: 12 | H17: 15 | I17: =IF(AND(G17<>"",H17<>""),ROUNDUP(AVERAGE(G17:H17),0),"") -> 14 | J17: FALSE | K17: Strategy
... A26: Now | B26: Presentation | C26: Executive Presentation - Discovery Findings | D26: As the JLG team, and leadership, we need a presentation of discovery findings and recommendations. | E26: A8 will create and present executive-level presentation covering: current state assessment, key findings, recommended solution architecture, phasing strategy, timeline, budget estimates, risk assessment, and ROI projections. Present to leadership for approval to proceed. | F26: - Presentation - Deck should cover: current pain points, recommended HubSpot solution, integration strategy, phasing, timeline, detailed budget, ROI - Need to present cost comparison: current state (Marketo $20K/qtr, Dynamics $27K/qtr) vs HubSpot - Integration costs for SAP and Magento will be significant - Emphasize: cost savings, efficiency gains, cross-sell/upsell revenue potential - 1 presentation expected - Includes prep time for deck creation | G26: 15 | H26: 20 | I26: =IF(AND(G26<>"",H26<>""),ROUNDUP(AVERAGE(G26:H26),0),"") -> 18 | J26: FALSE | K26: Strategy
B27: Presentation | C27: Solution Design Presentation - Detailed Walkthrough | D27: As the JLG team, we need a detailed presentation of the solution design and implementation plan. | E27: A8 will present detailed solution design including: technical architecture, data model, integration specifications, process flows, UI/UX designs, implementation plan, testing approach, training plan, and change management strategy. Gather feedback and obtain sign-off. | F27: - Presentation - Detailed walkthrough of all technical specifications and functional requirements - Review ERD, data flows, integration architecture, process maps - Demo POCs of key functionality (renewal automation, suggested products, etc.) - Review implementation timeline and dependencies - Obtain sign-off on solution before build begins - Includes prep time | G27: 12 | H27: 15 | I27: =IF(AND(G27<>"",H27<>""),ROUNDUP(AVERAGE(G27:H27),0),"") -> 14 | J27: FALSE | K27: Strategy
B28: Implementation Support | C28: Implementation Handoff & Team Onboarding | D28: As the JLG project team, we need Aptitude 8 strategy team to support the implementation team during transition and first month of build. | E28: A8 strategy team will: onboard implementation team on all requirements and design documents, attend first 4 weekly status meetings, be available for clarification questions, support scope management, and ensure smooth transition from design to build. | F28: - Strategy team will support implementation team - Handoff sessions to review all documentation - First month of weekly status meetings to support questions - Scope clarification and change request management - Support with client communication if issues arise - Does not include ongoing project management (separate line item) | G28: 10 | H28: 15 | I28: =IF(AND(G28<>"",H28<>""),ROUNDUP(AVERAGE(G28:H28),0),"") -> 13 | J28: FALSE | K28: Strategy
I29: =IF(AND(G29<>"",H29<>""),ROUNDUP(AVERAGE(G29:H29),0),"") | J29: FALSE
I30: =IF(AND(G30<>"",H30<>""),ROUNDUP(AVERAGE(G30:H30),0),"") | J30: FALSE
I31: =IF(AND(G31<>"",H31<>""),ROUNDUP(AVERAGE(G31:H31),0),"") | J31: FALSE
I32: =IF(AND(G32<>"",H32<>""),ROUNDUP(AVERAGE(G32:H32),0),"") | J32: FALSE
I33: =IF(AND(G33<>"",H33<>""),ROUNDUP(AVERAGE(G33:H33),0),"") | J33: FALSE
I34: =IF(AND(G34<>"",H34<>""),ROUNDUP(AVERAGE(G34:H34),0),"") | J34: FALSE
I35: =IF(AND(G35<>"",H35<>""),ROUNDUP(AVERAGE(G35:H35),0),"") | J35: FALSE
I36: =IF(AND(G36<>"",H36<>""),ROUNDUP(AVERAGE(G36:H36),0),"") | J36: FALSE
I37: =IF(AND(G37<>"",H37<>""),ROUNDUP(AVERAGE(G37:H37),0),"") | J37: FALSE
I38: =IF(AND(G38<>"",H38<>""),ROUNDUP(AVERAGE(G38:H38),0),"") | J38: FALSE
I39: =IF(AND(G39<>"",H39<>""),ROUNDUP(AVERAGE(G39:H39),0),"") | J39: FALSE
I40: =IF(AND(G40<>"",H40<>""),ROUNDUP(AVERAGE(G40:H40),0),"") | J40: FALSE
... I108: =IF(AND(G108<>"",H108<>""),ROUNDUP(AVERAGE(G108:H108),0),"") | J108: FALSE
J109: FALSE
J110: FALSE

Sheet Config
A1: Configuration | B1: Value | C1: Description | D1: HubSpot Property
A2: GDrive + Deal Inputs
A3: Company Name | C3: Client company name for proposals
A4: Google Folder | C4: Needs to be manually input for the time being, will be set by the Pipedream automation
A5: Deal Record ID | C5: HubSpot deal record ID, needs to be manually input for the time being, will be set by the Pipedream automation
A6: Last Sync to HubSpot | C6: The last time the story doc was sync'd to the HubSpot deal record
A7: Solutions Architect | C7: SA assigned to this project
A8: Scoping Status | B8: Not Started | D8: scoping_status
A9: Project ID | B9: ------ | C9: TBD on usage to facilitate project creation
A11: Client HTML Page
A12: Client Page URL | B12: https://script.google.com/macros/s/AKfycbzGfZXXrB8GB7kt-FSeTA8sL0Rw3BzaXwifNA9CDpjsqe8NBn4EL159NLqLBYwGjqUw/exec?sheetId=1qgkUllcl5UxR4mhuejTzliVFPuVNmuP9ND02kUtrf_Y | C12: The URL of the page that will be shared in Trumpet | D12: customer_stories_client_url
A13: Last Client Page URL Generated | B13: 46006.463 | C13: The last time you created/updated a URL so we can understand deployment app versions
A14: Client Page Status | B14: Final Presentation | C14: Determines page status for the shared link
A16: NOW Project
A17: Hourly Project Rate | B17: 325 | C17: Standard hourly rate for most services | D17: project_hourly_rate
A18: Project Management Factor | B18: 0.2 | C18: Percentage markup for project management
A19: Project Management Content | B19: To support management and communication, a project manager and delivery lead will own all A8 tasks and clearly communicate needs. - Visibility to budget spend will be provided during the duration of the project - A8 will provide check-in agenda items and follow-ups - JLG to communicate to A8's shared inbox for easier collaboration and timely responses - JLG driven delay will result in additional PM time billed to manage timeline | C19: Description text for the PM section. editable by you.
A20: SA Expected Start Date | B20: 45936 | C20: Project start date
A21: Total Project Months | B21: 3 | C21: Expected project duration | D21: project_duration
A23: NEXT Support Retainer
A24: Post-Launch Hourly Rate | C24: Post-launch rate, a zero here will hide the workstream/section | D24: retainer_hourly_rate
A25: Post-Launch Hours Per Month | C25: Post-launch hours per month, a zero here will hide the workstream/section | D25: retainer_hours_per_month_sold
A26: Post-Launch # of Months | C26: Post-launch months, a zero here will hide the workstream/section | D26: retainer_months_sold
A27: Post-Launch Support Content | B27: Hours dedicated to post go-live support. These hours can be used for anything HubSpot related (reporting, training, iterations, additional asks, etc.) | C27: Description text for the post-launch section
A30: Additional Notes + Considerations
A31: Additional Notes | B31: - The assumptions content in this scope is based on information and discovery during the sales evaluation and is subject to change during the project if additional challenges or barriers are discovered. - A8 is a Time & Materials agency, we will provide transparent budget tracking throughout the project and change orders will require approvals. - We interchange between A8 and Aptitude 8 in this document. | C31: Description text for below the investment summaries, but above the later phase workstreams

Sheet Calculations
D1: HubSpot Property
A2: Calculated Project Details
A3: Total Service Hours Hours | B3: =SUMIF(Input!A:A,"Now",Input!I:I) -> 322 | C3: Total amount of Input rows
A4: Total Project Management Hours | B4: =round(B3*Config!B18,0) -> 64 | C4: Based on PM % in Config Sheet
A5: Total Project Hours Sold | B5: =sum(B3:B4) -> 386 | C5: Service + PM | D5: project_hours_sold
A6: Total Retainer Hours Sold | B6: =Config!B25 * Config!B26 -> 0
A7: Total Engagement Hours Sold | B7: =sum(B5:B6) -> 386 | C7: This should match exactly to the investment block on the HTML Page | D7: sold_hours
A8: Deal Amount | B8: =(B5*Config!B17)+(B6*Config!B24) -> 125450 | C8: This should match exactly to the investment block on the HTML Page | D8: amount
A9: Expected End Date | B9: =EDATE(Config!B20, Config!B21) -> 46028
A10: Expected Project Hours/Month | B10: =roundup(B3/Config!B21,0) -> 108
A11: Linear Expected Project Hours/Week | B11: =roundup(B10/4.3,0) -> 26
A12: Peak Project Expected Hours/Week | B12: =B11*1.2 -> 31.2
A13: Low Project Expected Hours/Week | B13: =B11*0.5 -> 13
A14: Dev Work Percentage | B14: =C21 -> 0 | D14: dev_work_pct
A15: SE Work Percentage | B15: =C23 -> 0.31865285 | D15: se_work_pct
A18: Calculated Function Summary
B19: Sum of Hours | C19: Percent of
A20: Consulting | B20: =SUMIFS(Input!I:I,Input!K:K,"Consulting",Input!A:A,"Now") -> 17 | C20: =B20/B26 -> 0.044041451
A21: Development | B21: =SUMIFS(Input!I:I,Input!K:K,"Development",Input!A:A,"Now") -> 0 | C21: =B21/B26 -> 0
A22: Project Management | B22: =B4 -> 64 | C22: =B22/B26 -> 0.16580311
A23: Solutions Engineering | B23: =SUMIFS(Input!I:I,Input!K:K,"Solutions Engineering",Input!A:A,"Now") -> 123 | C23: =B23/B26 -> 0.31865285
A24: Strategy | B24: =SUMIFS(Input!I:I,Input!K:K,"Strategy",Input!A:A,"Now") -> 182 | C24: =B24/B26 -> 0.47150259
A26: Sum of Function-Based Hours | B26: =sum(B20:B24) -> 386 | C26: =sum(C20:C24) -> 1
A29: Calculated Ranges | B29: Low Hours | C29: High Hours
A30: Project Service Estimates: | B30: =SUMIF(Input!A:A,"Now",Input!G:G) -> 268 | C30: =SUMIF(Input!A:A,"Now",Input!H:H) -> 359
A31: Project Management: | B31: =round(B30*Config!B18,0) -> 54 | C31: =round(C30*Config!B18,0) -> 72
A32: Post-Project Support: | B32: =B6 -> 0 | C32: =B6 -> 0
A33: Hour Estimates: | B33: =SUM(B30:B32) -> 322 | C33: =SUM(C30:C32) -> 431
A34: Investment Ranges: | B34: =(sum(B30:B31)*Config!B17)+(B32*Config!B24) -> 104650 | C34: =(sum(C30:C31)*Config!B17)+(C32*Config!B24) -> 140075
A36: SOW Summarized Line Items
A37: =IFERROR(__xludf.DUMMYFUNCTION("VSTACK( QUERY(Input!A:I,""SELECT B, SUM(I), SUM(I)*""&Config!B17&"" WHERE B IS NOT NULL AND A = 'Now' GROUP BY B LABEL B 'Workstream', SUM(I) 'Total Hours', SUM(I)*""&Config!B17&"" 'Total Investment'"",1), {""Project Management"", ROUND(SUMPRODUCT(QUE"&"RY(Input!A:I,""SELECT SUM(I) WHERE B IS NOT NULL AND A = 'Now' GROUP BY B LABEL SUM(I) ''"",0))*Config!B18,0), ROUND(SUMPRODUCT(QUERY(Input!A:I,""SELECT SUM(I) WHERE B IS NOT NULL AND A = 'Now' GROUP BY B LABEL SUM(I) ''"",0))*Config!B18,0)*Config!B17}, "&" {""Post-Launch Support"", Config!B25*Config!B26, Config!B25*Config!B26*Config!B24} )"),"Workstream") -> Workstream | B37: =IFERROR(__xludf.DUMMYFUNCTION("""COMPUTED_VALUE"""),"Total Hours") -> Total Hours | C37: =IFERROR(__xludf.DUMMYFUNCTION("""COMPUTED_VALUE"""),"Total Investment") -> Total Investment
A38: =IFERROR(__xludf.DUMMYFUNCTION("""COMPUTED_VALUE"""),"Discovery") -> Discovery | B38: =IFERROR(__xludf.DUMMYFUNCTION("""COMPUTED_VALUE"""),55.0) -> 55 | C38: =IFERROR(__xludf.DUMMYFUNCTION("""COMPUTED_VALUE"""),17875.0) -> 17875
A39: =IFERROR(__xludf.DUMMYFUNCTION("""COMPUTED_VALUE"""),"Mobilization") -> Mobilization | B39: =IFERROR(__xludf.DUMMYFUNCTION("""COMPUTED_VALUE"""),9.0) -> 9 | C39: =IFERROR(__xludf.DUMMYFUNCTION("""COMPUTED_VALUE"""),2925.0) -> 2925
A40: =IFERROR(__xludf.DUMMYFUNCTION("""COMPUTED_VALUE"""),"Presentation") -> Presentation | B40: =IFERROR(__xludf.DUMMYFUNCTION("""COMPUTED_VALUE"""),18.0) -> 18 | C40: =IFERROR(__xludf.DUMMYFUNCTION("""COMPUTED_VALUE"""),5850.0) -> 5850
A41: =IFERROR(__xludf.DUMMYFUNCTION("""COMPUTED_VALUE"""),"Project Planning") -> Project Planning | B41: =IFERROR(__xludf.DUMMYFUNCTION("""COMPUTED_VALUE"""),22.0) -> 22 | C41: =IFERROR(__xludf.DUMMYFUNCTION("""COMPUTED_VALUE"""),7150.0) -> 7150
A42: =IFERROR(__xludf.DUMMYFUNCTION("""COMPUTED_VALUE"""),"Solution Design") -> Solution Design | B42: =IFERROR(__xludf.DUMMYFUNCTION("""COMPUTED_VALUE"""),142.0) -> 142 | C42: =IFERROR(__xludf.DUMMYFUNCTION("""COMPUTED_VALUE"""),46150.0) -> 46150
A43: =IFERROR(__xludf.DUMMYFUNCTION("""COMPUTED_VALUE"""),"User Stories Creation") -> User Stories Creation | B43: =IFERROR(__xludf.DUMMYFUNCTION("""COMPUTED_VALUE"""),30.0) -> 30 | C43: =IFERROR(__xludf.DUMMYFUNCTION("""COMPUTED_VALUE"""),9750.0) -> 9750
A44: =IFERROR(__xludf.DUMMYFUNCTION("""COMPUTED_VALUE"""),"Workshops") -> Workshops | B44: =IFERROR(__xludf.DUMMYFUNCTION("""COMPUTED_VALUE"""),46.0) -> 46 | C44: =IFERROR(__xludf.DUMMYFUNCTION("""COMPUTED_VALUE"""),14950.0) -> 14950
A45: =IFERROR(__xludf.DUMMYFUNCTION("""COMPUTED_VALUE"""),"Project Management") -> Project Management | B45: =IFERROR(__xludf.DUMMYFUNCTION("""COMPUTED_VALUE"""),64.0) -> 64 | C45: =IFERROR(__xludf.DUMMYFUNCTION("""COMPUTED_VALUE"""),20800.0) -> 20800
A46: =IFERROR(__xludf.DUMMYFUNCTION("""COMPUTED_VALUE"""),"Post-Launch Support") -> Post-Launch Support | B46: =IFERROR(__xludf.DUMMYFUNCTION("""COMPUTED_VALUE"""),0.0) -> 0 | C46: =IFERROR(__xludf.DUMMYFUNCTION("""COMPUTED_VALUE"""),0.0) -> 0
